Workbook

Sheet GEVEv2_full_ano
B1: gene | C1: contig | D1: source | E1: start | F1: end | G1: strand | H1: ncldv_marker | I1: marker_evalue | J1: marker_score | K1: gvog | L1: gvog_evalue | M1: gvog_score | N1: eggnog_ogs | O1: eggnog_name | P1: eggnog_desc | Q1: cog_cat | R1: max_annot_lvl | S1: eggnog_evalue | T1: eggnog_score | U1: eggnog_pfam | V1: pfam | W1: pfam_desc | X1: pfam_score | Y1: hhpred_n_hits | Z1: hhpred_n_regions | AA1: top_targets | AB1: top_descriptions | AC1: avg_query_cover | AD1: max_probability | AE1: mod_6mA | AF1: cluster | AG1: cds_per_transcript | AH1: introns_per_gene | AI1: introns | AJ1: NCLDV promoter | AK1: old_prodigal_id | AL1: comments
A2: 1 | B2: GEVEv2_1 | C2: contig_536 | D2: AUGUSTUS | E2: 2024298 | F2: 2028206 | G2: - | K2: GVOG01792 | L2: 8.1e-06 | M2: 20.5 | X2: 1303 | AF2: BVP | AG2: t1 (1) | AK2: contig_536_22 | AL2: =VLOOKUP(AK2,viral_genes!$C$2:$P$661,14, FALSE) -> TIR 1 start; early high expressed
A3: 2 | B3: GEVEv2_2 | C3: contig_536 | D3: Prodigal_v2.6.3 | E3: 2028209 | F3: 2028847 | G3: - | X3: 213 | AF3: BVP | AK3: contig_536_23 | AL3: =VLOOKUP(AK3,viral_genes!$C$2:$P$661,14, FALSE) -> early high expressed
A4: 3 | B4: GEVEv2_3 | C4: contig_536 | D4: AUGUSTUS | E4: 2033161 | F4: 2034048 | G4: - | X4: 178 | AE4: yes | AF4: BVP | AG4: t1 (4) | AH4: 3 | AI4: yes | AK4: contig_536_24-25 | AL4: =VLOOKUP(AK4,viral_genes!$C$2:$P$661,14, FALSE) -> #N/A
A5: 4 | B5: GEVEv2_4 | C5: contig_536 | D5: Prodigal_v2.6.3 | E5: 2034637 | F5: 2034777 | G5: + | X5: 47 | AE5: yes | AK5: contig_536_26 | AL5: =VLOOKUP(AK5,viral_genes!$C$2:$P$661,14, FALSE)
A6: 5 | B6: GEVEv2_5 | C6: contig_536 | D6: AUGUSTUS | E6: 2035275 | F6: 2038133 | G6: + | K6: GVOG01534 | L6: 2.8 | M6: 3.1 | X6: 492 | Y6: 9 | Z6: 6 | AA6: 5YVG_X; 6Y53_o; 7DVQ_4; 7OBR_u; 6Y50_q; 6Y5Q_q; 7BGB_H; 6GOS_A; 7OBQ_u | AB6: Transportin-1, RNA-binding protein FUS; Importin family, PROTEIN TRANSPORT, PROTEIN; 4.05A {Homo sapiens} | U2 small nuclear ribonucleoprotein A'; 17S U2 snRNP, SPLICING; 7.1A {Homo sapiens} | Pre-mRNA-processing-splicing factor 8, 116 kDa; spliceosome, minor spliceosome, Bact complex; HET: TPO, GTP, G5J, IHP, SEP; 2.89A {Homo sapiens} | SRP SRP receptor, co-translational protein; HET: MG, GDP; 2.8A {Canis lupus familiaris} | Splicing factor 3A subunit 3; 17S U2 snRNP, SPLICING; 4.1A {Homo sapiens} | U2 small nuclear ribonucleoprotein A'; 17S U2 snRNP, SPLICING; 7.1A {Homo sapiens} | Telomerase Cajal body protein 1; H/ACA RNP, ribonucleoprotein, complex, RNA; 3.39A {Homo sapiens} | Bacteriocin microcin B17, Microcin B17-processing; microcin, DNA gyrase, heterocyclization, posttranslational; HET: EDO, TOZ, OTZ, FMN; 2.1A {Escherichia coli str. K-12 substr. MG1655} | SRP SRP receptor, co-translational protein; HET: GTP, GNP; 3.9A {Canis lupus familiaris} | AC6: 0.187825299841593 | AD6: 97.67 | AE6: yes | AG6: t1 (10)| t2 (10) | AH6: 9 | AI6: yes | AK6: contig_536_27-30 | AL6: =VLOOKUP(AK6,viral_genes!$C$2:$P$661,14, FALSE) -> #N/A
A7: 6 | B7: GEVEv2_6 | C7: contig_536 | D7: Prodigal_v2.6.3 | E7: 2038470 | F7: 2038604 | G7: - | X7: 45 | AK7: contig_536_31 | AL7: =VLOOKUP(AK7,viral_genes!$C$2:$P$661,14, FALSE)
A8: 7 | B8: GEVEv2_7 | C8: contig_536 | D8: Prodigal_v2.6.3 | E8: 2038662 | F8: 2038952 | G8: - | X8: 97 | AK8: contig_536_32 | AL8: =VLOOKUP(AK8,viral_genes!$C$2:$P$661,14, FALSE)
A9: 8 | B9: GEVEv2_8 | C9: contig_536 | D9: AUGUSTUS | E9: 2040070 | F9: 2042203 | G9: + | K9: GVOGm1001 | L9: 0.037 | M9: 7.1 | X9: 568 | Y9: 1 | Z9: 1 | AA9: PF13388.9 | AB9: ; DUF4106 ; Protein of unknown function (DUF4106) | AC9: 0.155202821869489 | AD9: 81.45 | AE9: yes | AG9: t1 (4) | AH9: 3 | AI9: yes | AK9: contig_536_33-35 | AL9: =VLOOKUP(AK9,viral_genes!$C$2:$P$661,14, FALSE) -> #N/A
A10: 9 | B10: GEVEv2_9 | C10: contig_536 | D10: Prodigal_v2.6.3 | E10: 2042581 | F10: 2042712 | G10: - | X10: 44 | AK10: contig_536_36 | AL10: =VLOOKUP(AK10,viral_genes!$C$2:$P$661,14, FALSE)
A11: 10 | B11: GEVEv2_10 | C11: contig_536 | D11: Prodigal_v2.6.3 | E11: 2042985 | F11: 2043368 | G11: - | K11: GVOG01164 | L11: 0.87 | M11: 2.4 | X11: 128 | AK11: contig_536_37 | AL11: =VLOOKUP(AK11,viral_genes!$C$2:$P$661,14, FALSE)
A12: 11 | B12: GEVEv2_11 | C12: contig_536 | D12: Prodigal_v2.6.3 | E12: 2043368 | F12: 2043577 | G12: - | X12: 70 | AK12: contig_536_38 | AL12: =VLOOKUP(AK12,viral_genes!$C$2:$P$661,14, FALSE)
A13: 12 | B13: GEVEv2_12 | C13: contig_536 | D13: AUGUSTUS | E13: 2043578 | F13: 2044496 | G13: - | X13: 240 | AE13: yes | AF13: DVP | AG13: t1 (3) | AH13: 2 | AI13: yes | AK13: contig_536_39-40 | AL13: =VLOOKUP(AK13,viral_genes!$C$2:$P$661,14, FALSE) -> #N/A
A14: 13 | B14: GEVEv2_13 | C14: contig_536 | D14: AUGUSTUS | E14: 2044895 | F14: 2045514 | G14: + | X14: 135 | AE14: yes | AF14: BVP | AG14: t1 (2) | AH14: 1 | AI14: yes | AK14: contig_536_41-42 | AL14: =VLOOKUP(AK14,viral_genes!$C$2:$P$661,14, FALSE) -> #N/A
A15: 14 | B15: GEVEv2_14 | C15: contig_536 | D15: Prodigal_v2.6.3 | E15: 2046300 | F15: 2046890 | G15: + | X15: 197 | AF15: BVP | AK15: contig_536_43 | AL15: =VLOOKUP(AK15,viral_genes!$C$2:$P$661,14, FALSE)
A16: 15 | B16: GEVEv2_15 | C16: contig_536 | D16: Prodigal_v2.6.3 | E16: 2047033 | F16: 2050878 | G16: + | K16: GVOGm0180 | L16: 2.2e-09 | M16: 30.9 | V16: PF02037 | W16: SAP domain | X16: 1282 | Y16: 8 | Z16: 3 | AA16: 7C7L_B; 7L49_A; 7ODF_A; 6NY2_Y; 6NY3_Y; PF18516.4; 7OBR_u; 7OBQ_u | AB16: CRISPR-associated protein Cas14a.1/RNA/DNA Complex; Cas12f, Cas14, sgRNA, target DNA; 3.0A {uncultured archaeon} | Cas12f1/DNA Complex; CRISPR CAS, RNA BINDING PROTEIN;{unidentified} | CRISPR-Cas, RNA-guided endonuclease, R-loop, RNA; 2.7A {Phage #D} | CasX/DNA/RNA Complex; CasX, sgRNA, target DNA, CRISPR; 3.2A {Deltaproteobacteria bacterium} | CasX/DNA Complex; CasX, sgRNA, target DNA, CRISPR; 3.7A {Deltaproteobacteria bacterium} | ; RuvC_1 ; RuvC nuclease domain | SRP SRP receptor, co-translational protein; HET: MG, GDP; 2.8A {Canis lupus familiaris} | SRP SRP receptor, co-translational protein; HET: GTP, GNP; 3.9A {Canis lupus familiaris} | AC16: 0.080015612802498 | AD16: 96.77 | AJ16: yes | AK16: contig_536_44 | AL16: =VLOOKUP(AK16,viral_genes!$C$2:$P$661,14, FALSE) -> Fanzor_B_nuclease
A17: 16 | B17: GEVEv2_16 | C17: contig_536 | D17: Prodigal_v2.6.3 | E17: 2050869 | F17: 2051777 | G17: + | X17: 303 | AF17: DVP | AK17: contig_536_45 | AL17: =VLOOKUP(AK17,viral_genes!$C$2:$P$661,14, FALSE)
A18: 17 | B18: GEVEv2_17 | C18: contig_536 | D18: gmst | E18: 2051780 | F18: 2058806 | G18: + | K18: GVOG09276 | L18: 6.7 | M18: 0.2 | X18: 1260 | AE18: yes | AG18: t1 (10) | AH18: 9 | AI18: yes | AK18: contig_536_46-55 | AL18: =VLOOKUP(AK18,viral_genes!$C$2:$P$661,14, FALSE) -> #N/A
A19: 18 | B19: GEVEv2_18 | C19: contig_536 | D19: Prodigal_v2.6.3 | E19: 2058886 | F19: 2059026 | G19: + | X19: 47 | AK19: contig_536_56 | AL19: =VLOOKUP(AK19,viral_genes!$C$2:$P$661,14, FALSE)
A20: 19 | B20: GEVEv2_19 | C20: contig_536 | D20: AUGUSTUS | E20: 2060026 | F20: 2060606 | G20: + | X20: 72 | AE20: yes | AF20: BVP | AG20: t1 (4) | AH20: 3 | AI20: yes | AL20: =VLOOKUP(AK20,viral_genes!$C$2:$P$661,14, FALSE) -> #N/A
A21: 20 | B21: GEVEv2_20 | C21: contig_536 | D21: AUGUSTUS | E21: 2060789 | F21: 2061235 | G21: g | X21: 104 | AE21: yes | AF21: BVP | AG21: t1 (2) | AH21: 1 | AI21: yes | AL21: =VLOOKUP(AK21,viral_genes!$C$2:$P$661,14, FALSE) -> #N/A
A22: 21 | B22: GEVEv2_21 | C22: contig_536 | D22: AUGUSTUS | E22: 2062616 | F22: 2066455 | G22: + | K22: GVOGm1062 | L22: 1.7e-27 | M22: 91.8 | N22: COG0123@1|root,KOG1342@2759|Eukaryota,37MPC@33090|Viridiplantae,34H80@3041|Chlorophyta | P22: Belongs to the histone deacetylase family. HD Type 1 subfamily | Q22: B | R22: 33090|Viridiplantae | S22: 1.17e-54 | T22: 202 | U22: Hist_deacetyl | V22: PF00850 | W22: Histone deacetylase domain | X22: 1175 | Y22: 3 | Z22: 1 | AA22: 4BKX_B; 7AO8_B; 3MAX_A | AB22: METASTASIS-ASSOCIATED PROTEIN MTA1, HISTONE DEACETYLASE; TRANSCRIPTION, INOSITOL PHOSPHATE SIGNALLING, ELM2-SANT; HET: SO4; 3.0A {HOMO SAPIENS} | Methyl-CpG-binding domain protein 2, Metastasis-associated; Deacetylase, Complex, TRANSCRIPTION; HET: IHP; 4.5A {Homo sapiens} | Histone deacetylase 2 (E.C.3.5.1.98); Class 2, HDAC, foot pocket; HET: NHE, LLX; 2.05A {Homo sapiens} | AC22: 0.296422487223169 | AD22: 100 | AF22: BVP | AG22: t1 (3)| t2 (2) | AH22: 2 | AI22: yes | AK22: contig_536_58-59 | AL22: =VLOOKUP(AK22,viral_genes!$C$2:$P$661,14, FALSE) -> #N/A
A23: 22 | B23: GEVEv2_22 | C23: contig_536 | D23: gmst | E23: 2063639 | F23: 2064118 | G23: - | X23: 160 | AG23: t1 (1) | AL23: =VLOOKUP(AK23,viral_genes!$C$2:$P$661,14, FALSE) -> #N/A
A24: 23 | B24: GEVEv2_23 | C24: contig_536 | D24: Prodigal_v2.6.3 | E24: 2066529 | F24: 2067242 | G24: + | X24: 238 | AF24: BVP | AK24: contig_536_60 | AL24: =VLOOKUP(AK24,viral_genes!$C$2:$P$661,14, FALSE)
A25: 24 | B25: GEVEv2_24 | C25: contig_536 | D25: Prodigal_v2.6.3 | E25: 2067583 | F25: 2069337 | G25: + | X25: 585 | AE25: yes | AF25: DVP | AK25: contig_536_61 | AL25: =VLOOKUP(AK25,viral_genes!$C$2:$P$661,14, FALSE)
A26: 25 | B26: GEVEv2_25 | C26: contig_536 | D26: Prodigal_v2.6.3 | E26: 2069880 | F26: 2070125 | G26: + | K26: GVOG08592 | L26: 2.2e-05 | M26: 18.9 | X26: 82 | Y26: 4 | Z26: 2 | AA26: 5FJ9_I; 6TUT_I; 7AOC_I; PF04233.17 | AB26: DNA-DIRECTED RNA POLYMERASE III SUBUNIT; RNA POLYMERASE III, POL III; 4.6A {SACCHAROMYCES CEREVISIAE} | DNA-directed RNA polymerase III subunit; Transcription, RNA Polymerase III, Pol; 3.25A {Saccharomyces cerevisiae S288C} | DNA-directed RNA polymerase I subunit; TRANSCRIPTION;{Schizosaccharomyces pombe (strain 972 / ATCC 24843)} | ; Phage_Mu_F ; Phage Mu protein F like protein | AC26: 0.17283950617284 | AD26: 83.56 | AK26: contig_536_62 | AL26: =VLOOKUP(AK26,viral_genes!$C$2:$P$661,14, FALSE)
A27: 26 | B27: GEVEv2_26 | C27: contig_536 | D27: Prodigal_v2.6.3 | E27: 2070529 | F27: 2070774 | G27: + | X27: 82 | AE27: yes | AK27: contig_536_63 | AL27: =VLOOKUP(AK27,viral_genes!$C$2:$P$661,14, FALSE)
A28: 27 | B28: GEVEv2_27 | C28: contig_536 | D28: Prodigal_v2.6.3 | E28: 2070835 | F28: 2071419 | G28: + | X28: 195 | AE28: yes | AK28: contig_536_64 | AL28: =VLOOKUP(AK28,viral_genes!$C$2:$P$661,14, FALSE)
A29: 28 | B29: GEVEv2_28 | C29: contig_536 | D29: Prodigal_v2.6.3 | E29: 2071534 | F29: 2072646 | G29: + | K29: GVOG07877 | L29: 0.0031 | M29: 12.8 | X29: 371 | AE29: yes | AK29: contig_536_65 | AL29: =VLOOKUP(AK29,viral_genes!$C$2:$P$661,14, FALSE)
A30: 29 | B30: GEVEv2_29 | C30: contig_536 | D30: Prodigal_v2.6.3 | E30: 2072711 | F30: 2072863 | G30: + | X30: 51 | AK30: contig_536_66 | AL30: =VLOOKUP(AK30,viral_genes!$C$2:$P$661,14, FALSE)
A31: 30 | B31: GEVEv2_30 | C31: contig_536 | D31: Prodigal_v2.6.3 | E31: 2072835 | F31: 2073212 | G31: - | X31: 126 | AK31: contig_536_67 | AL31: =VLOOKUP(AK31,viral_genes!$C$2:$P$661,14, FALSE)
A32: 31 | B32: GEVEv2_31 | C32: contig_536 | D32: Prodigal_v2.6.3 | E32: 2073511 | F32: 2073654 | G32: + | X32: 48 | AK32: contig_536_68 | AL32: =VLOOKUP(AK32,viral_genes!$C$2:$P$661,14, FALSE)
A33: 32 | B33: GEVEv2_32 | C33: contig_536 | D33: Prodigal_v2.6.3 | E33: 2073786 | F33: 2074331 | G33: + | X33: 182 | AK33: contig_536_69 | AL33: =VLOOKUP(AK33,viral_genes!$C$2:$P$661,14, FALSE)
A34: 33 | B34: GEVEv2_33 | C34: contig_536 | D34: Prodigal_v2.6.3 | E34: 2074948 | F34: 2075100 | G34: + | X34: 51 | AF34: BVP | AK34: contig_536_70 | AL34: =VLOOKUP(AK34,viral_genes!$C$2:$P$661,14, FALSE) -> early high expressed
A35: 34 | B35: GEVEv2_34 | C35: contig_536 | D35: Prodigal_v2.6.3 | E35: 2076530 | F35: 2078923 | G35: + | V35: PF17879 | W35: DNA ligase C-terminal domain | X35: 798 | Y35: 6 | Z35: 3 | AA35: 6SC2_C; 6RLB_C; 3PGW_S; 6QX9_1K; 6QW6_5X; 6QX9_5X | AB35: DYNC2H1 variant protein; dynein, cilia, intraflagellar transport, complex; HET: ADP, ATP; 3.9A {Homo sapiens} | PROTEIN; dynein, cilia, intraflagellar transport, complex; 4.5A {Homo sapiens} | U1-A , U1-70K , Sm-D3; PROTEIN-RNA COMPLEX, U1 snRNA, Sm; 4.4A {Homo sapiens} | Splicing factor 3B subunit 4; RNP complex, splicing, RNA, protein; HET: M7M, GTP, IHP; 3.28A {Homo sapiens} | Small nuclear ribonucleoprotein Sm D1; RNP complex, splicing, RNA, protein; HET: M7M, GTP, IHP; 2.92A {Homo sapiens} | Splicing factor 3B subunit 4; RNP complex, splicing, RNA, protein; HET: M7M, GTP, IHP; 3.28A {Homo sapiens} | AC35: 0.240694270179841 | AD35: 97.37 | AF35: BVP | AK35: contig_536_71 | AL35: =VLOOKUP(AK35,viral_genes!$C$2:$P$661,14, FALSE) -> early high expressed
A36: 35 | B36: GEVEv2_35 | C36: contig_536 | D36: Prodigal_v2.6.3 | E36: 2079584 | F36: 2079799 | G36: - | X36: 72 | AF36: DVP | AK36: contig_536_72 | AL36: =VLOOKUP(AK36,viral_genes!$C$2:$P$661,14, FALSE)
A37: 36 | B37: GEVEv2_36 | C37: contig_536 | D37: AUGUSTUS | E37: 2080397 | F37: 2081495 | G37: - | X37: 182 | AE37: yes | AF37: DVP | AG37: t1 (6) | AH37: 5 | AI37: yes | AK37: contig_536_73 | AL37: =VLOOKUP(AK37,viral_genes!$C$2:$P$661,14, FALSE)
A38: 37 | B38: GEVEv2_37 | C38: contig_536 | D38: Prodigal_v2.6.3 | E38: 2082756 | F38: 2087447 | G38: - | K38: GVOG01434 | L38: 9.9e-11 | M38: 35.8 | N38: COG2801@1|root,KOG0017@2759|Eukaryota,37RRH@33090|Viridiplantae,3G8MV@35493|Streptophyta,3HVTZ@3699|Brassicales | P38: DNA RNA polymerases superfamily protein | Q38: L | R38: 35493|Streptophyta | S38: 2.11e-128 | T38: 431 | U38: RVP_2,RVT_1,Retrotrans_gag,rve,zf-CCHC | V38: PF13650 | PF00385 | PF13975 | PF17921 | PF17917 | PF17919 | PF00665 | PF00078 | W38: Aspartyl protease | Chromo (CHRromatin Organisation MOdifier) domain | gag-polyprotein putative aspartyl protease | Integrase zinc binding domain | RNase H-like domain found in reverse transcriptase | RNase H-like domain found in reverse transcriptase | Integrase core domain | Reverse transcriptase (RNA-dependent DNA polymerase) | X38: 1564 | Y38: 26 | Z38: 10 | AA38: 7Q5B_C; 4OL8_A; 4OL8_B; 7O0H_A; 7O0H_B; 7KSE_A; 1R0A_B; 5FRN_B; 3OYM_A; 6VOY_A; 3F9K_s; 3HPG_B; 3HPH_D; 1ZTW_A; 6B1R_A; 6MIH_A; PF05585.15; 2JYS_A; 1XYI_A; 1WD0_A; 1WVL_A; PF00336.21; 3S8I_A; 5HHL_A; 5HHJ_A; PF00078.30 | AC38: 0.181677247896058 | AD38: 100 | AF38: BVP | AK38: contig_536_74 | AL38: =VLOOKUP(AK38,viral_genes!$C$2:$P$661,14, FALSE) -> early high expressed
A39: 38 | B39: GEVEv2_38 | C39: contig_536 | D39: AUGUSTUS | E39: 2087496 | F39: 2089260 | G39: - | K39: GVOG01534 | L39: 1.5 | M39: 3.9 | X39: 256 | Y39: 12 | Z39: 5 | AA39: 5YVG_X; 3CW1_8; 3CW1_K; 3JCT_o; 7OHS_o; PF05918.14; 7OBR_u; 7OBQ_u; 1NJI_I; 1VQO_G; 2QA4_G; 6V7B_g | AB39: Transportin-1, RNA-binding protein FUS; Importin family, PROTEIN TRANSPORT, PROTEIN; 4.05A {Homo sapiens} | Spliceosomal U1 small nuclear ribonucleoprotein; pre-mRNA splicing, spliceosome, RNA-binding domain; 5.493A {Homo sapiens} | Spliceosomal U1 small nuclear ribonucleoprotein; pre-mRNA splicing, spliceosome, RNA-binding domain; 5.493A {Homo sapiens} | 60S ribosomal protein L2-A, 60S; pre-60S ribosome, RIBOSOME; HET: GTP; 3.08A {Saccharomyces cerevisiae S288c} | ribosomal assembly state, RIBOSOME; 4.38A {Saccharomyces cerevisiae S288C} | ; API5 ; Apoptosis inhibitory protein 5 (API5) | SRP SRP receptor, co-translational protein; HET: MG, GDP; 2.8A {Canis lupus familiaris} | SRP SRP receptor, co-translational protein; HET: GTP, GNP; 3.9A {Canis lupus familiaris} | large ribosomal subunit 50S; 50S, antibiotic, chloramphenicol, LSU, RIBOSOME; HET: NA, CL, MG, CLM; 3.0A {Haloarcula marismortui} SCOP: j.84.1.1 | 50S RIBOSOMAL SUBUNIT; ribosome 50S, PROTEIN-PROTEIN COMPLEX, RNA-RNA; HET: CL, 1MA, MG, PPU, UR3, PSU, OMU, SR, NA, OMG; 2.2A {Haloarcula marismortui} SCOP: j.84.1.1 | 50S RIBOSOMAL SUBUNIT; Large ribosomal subunit, Ribonucleoprotein, Ribosomal; HET: CL, MG, UR3, PSU, OMU, NA, OMG; 3.0A {Haloarcula marismortui} SCOP: j.84.1.1 | Structural protein VP1, Structural protein; helical symmetry, archaeal pilus, STRUCTURAL; 3.4A {Pyrobaculum filamentous virus 1} | AC39: 0.247058823529412 | AD39: 97.77 | AE39: yes | AF39: BVP | AG39: t1 (4) | AH39: 3 | AI39: yes | AK39: contig_536_75 | AL39: =VLOOKUP(AK39,viral_genes!$C$2:$P$661,14, FALSE) -> early high expressed
A40: 39 | B40: GEVEv2_39 | C40: contig_536 | D40: AUGUSTUS | E40: 2090146 | F40: 2092125 | G40: - | K40: GVOGm0180 | L40: 9.9e-62 | M40: 203.8 | N40: 2EG1T@1|root,2SM3P@2759|Eukaryota | P40: function. Source PGD | Q40: S | R40: 2759|Eukaryota | S40: 1.61e-119 | T40: 362 | X40: 660 | Y40: 7 | Z40: 3 | AA40: 7L49_A; 7C7L_B; 7ODF_A; 6NY2_Y; 6NY3_Y; 6XMG_A; PF07282.14 | AB40: Cas12f1/DNA Complex; CRISPR CAS, RNA BINDING PROTEIN;{unidentified} | CRISPR-associated protein Cas14a.1/RNA/DNA Complex; Cas12f, Cas14, sgRNA, target DNA; 3.0A {uncultured archaeon} | CRISPR-Cas, RNA-guided endonuclease, R-loop, RNA; 2.7A {Phage #D} | CasX/DNA/RNA Complex; CasX, sgRNA, target DNA, CRISPR; 3.2A {Deltaproteobacteria bacterium} | CasX/DNA Complex; CasX, sgRNA, target DNA, CRISPR; 3.7A {Deltaproteobacteria bacterium} | Cas12i/DNA Complex; CRISPR, HYDROLASE-RNA complex;{Lachnospiraceae bacterium ND2006} | ; OrfB_Zn_ribbon ; Putative transposase DNA-binding domain | AC40: 0.228267938434858 | AD40: 98.85 | AF40: DVP | AG40: t1 (1) | AJ40: yes | AK40: contig_536_76 | AL40: =VLOOKUP(AK40,viral_genes!$C$2:$P$661,14, FALSE) -> putative transposase; Fanzor_C_nuclease
A41: 40 | B41: GEVEv2_40 | C41: contig_536 | D41: Prodigal_v2.6.3 | E41: 2092162 | F41: 2092455 | G41: + | X41: 98 | AK41: contig_536_77 | AL41: =VLOOKUP(AK41,viral_genes!$C$2:$P$661,14, FALSE)
A42: 41 | B42: GEVEv2_41 | C42: contig_536 | D42: Prodigal_v2.6.3 | E42: 2092338 | F42: 2093330 | G42: - | K42: GVOGm1077 | L42: 5.5e-37 | M42: 122.6 | N42: COG3335@1|root,COG3335@2|Bacteria,1G6HS@1117|Cyanobacteria | P42: DDE superfamily endonuclease | Q42: L | R42: 1117|Cyanobacteria | S42: 9.42e-09 | T42: 61.6 | U42: DDE_3 | V42: PF13358 | W42: DDE superfamily endonuclease | X42: 331 | Y42: 9 | Z42: 3 | AA42: 4U7B_G; PF07592.14; 4FCY_A; PF13358.9; PF01710.19; 1PDN_C; 6PAX_A; 6QBV_C; 6QBV_D | AB42: Mos transposase/DNA Complex; transposase, transposon synaptic complex, helix-turn-helix; HET: SO4; 3.09A {Drosophila mauritiana} | ; DDE_Tnp_ISAZ013 ; Rhodopirellula transposase DDE domain | Transposase, DNA; RNaseH, DDE transposase, DNA BINDING; 3.706A {Enterobacteria phage Mu} | ; DDE_3 ; DDE superfamily endonuclease | ; HTH_Tnp_IS630 ; Transposase | PRD PAIRED/DNA COMPLEX; PROTEIN-DNA COMPLEX, DOUBLE HELIX, PAX; 2.5A {Drosophila melanogaster} SCOP: a.4.1.5 | HOMEOBOX PROTEIN PAX-6/DNA COMPLEX; PAX, PAIRED DOMAIN, TRANSCRIPTION, PROTEIN-DNA; 2.5A {Homo sapiens} SCOP: a.4.1.5 | integrase; retrovirus, deltaretrovirus, integration, strand-transfer, nucleotidyltransferase; 2.45A {Human T-cell leukemia virus 2} | integrase; retrovirus, deltaretrovirus, integration, strand-transfer, nucleotidyltransferase; 2.45A {Human T-cell leukemia virus 2} | AC42: 0.473063973063973 | AD42: 99.85 | AJ42: yes | AK42: contig_536_78 | AL42: =VLOOKUP(AK42,viral_genes!$C$2:$P$661,14, FALSE) -> Fanzor_C_transposase
A43: 42 | B43: GEVEv2_42 | C43: contig_536 | D43: Prodigal_v2.6.3 | E43: 2094780 | F43: 2095115 | G43: - | X43: 112 | AK43: contig_536_79 | AL43: =VLOOKUP(AK43,viral_genes!$C$2:$P$661,14, FALSE)
A44: 43 | B44: GEVEv2_43 | C44: contig_536 | D44: Prodigal_v2.6.3 | E44: 2095082 | F44: 2095309 | G44: - | X44: 76 | AK44: contig_536_80 | AL44: =VLOOKUP(AK44,viral_genes!$C$2:$P$661,14, FALSE)
A45: 44 | B45: GEVEv2_44 | C45: contig_536 | D45: Prodigal_v2.6.3 | E45: 2095568 | F45: 2095846 | G45: + | X45: 93 | AE45: yes | AK45: contig_536_81 | AL45: =VLOOKUP(AK45,viral_genes!$C$2:$P$661,14, FALSE)
A46: 45 | B46: GEVEv2_45 | C46: contig_536 | D46: Prodigal_v2.6.3 | E46: 2095957 | F46: 2096091 | G46: - | X46: 45 | AK46: contig_536_82 | AL46: =VLOOKUP(AK46,viral_genes!$C$2:$P$661,14, FALSE)
A47: 46 | B47: GEVEv2_46 | C47: contig_536 | D47: Prodigal_v2.6.3 | E47: 2096304 | F47: 2096465 | G47: + | X47: 54 | AE47: yes | AK47: contig_536_83 | AL47: =VLOOKUP(AK47,viral_genes!$C$2:$P$661,14, FALSE)
A48: 47 | B48: GEVEv2_47 | C48: contig_536 | D48: AUGUSTUS | E48: 2096935 | F48: 2097381 | G48: + | K48: GVOG05897 | L48: 0.0048 | M48: 11.9 | X48: 149 | AG48: t1 (1) | AK48: contig_536_84 | AL48: =VLOOKUP(AK48,viral_genes!$C$2:$P$661,14, FALSE)
A49: 48 | B49: GEVEv2_48 | C49: contig_536 | D49: Prodigal_v2.6.3 | E49: 2097768 | F49: 2097911 | G49: - | X49: 48 | AK49: contig_536_85 | AL49: =VLOOKUP(AK49,viral_genes!$C$2:$P$661,14, FALSE)
A50: 49 | B50: GEVEv2_49 | C50: contig_536 | D50: Prodigal_v2.6.3 | E50: 2097887 | F50: 2098336 | G50: - | K50: GVOGm1077 | L50: 7.5e-09 | M50: 30.1 | V50: PF13592 | W50: Winged helix-turn helix | X50: 150 | Y50: 6 | Z50: 2 | AA50: PF01710.19; 1PDN_C; 1U78_A; PF11242.11; PF05344.14; PF08822.14 | AB50: ; HTH_Tnp_IS630 ; Transposase | PRD PAIRED/DNA COMPLEX; PROTEIN-DNA COMPLEX, DOUBLE HELIX, PAX; 2.5A {Drosophila melanogaster} SCOP: a.4.1.5 | transposase, transposon DNA, bipartite DNA-binding; 2.69A {Caenorhabditis elegans} SCOP: a.4.1.2 | ; DUF2774 ; Protein of unknown function (DUF2774) | ; DUF746 ; Domain of Unknown Function (DUF746) | ; DUF1804 ; Protein of unknown function (DUF1804) | AC50: 0.511185682326622 | AD50: 98.24 | AK50: contig_536_86 | AL50: =VLOOKUP(AK50,viral_genes!$C$2:$P$661,14, FALSE)
A51: 50 | B51: GEVEv2_50 | C51: contig_536 | D51: Prodigal_v2.6.3 | E51: 2099327 | F51: 2099425 | G51: - | X51: 33 | AE51: yes | AK51: contig_536_87 | AL51: =VLOOKUP(AK51,viral_genes!$C$2:$P$661,14, FALSE)
A52: 51 | B52: GEVEv2_51 | C52: contig_536 | D52: Prodigal_v2.6.3 | E52: 2099410 | F52: 2099634 | G52: - | X52: 75 | AK52: contig_536_88 | AL52: =VLOOKUP(AK52,viral_genes!$C$2:$P$661,14, FALSE)
A53: 52 | B53: GEVEv2_52 | C53: contig_536 | D53: Prodigal_v2.6.3 | E53: 2100266 | F53: 2100508 | G53: + | X53: 81 | AK53: contig_536_89 | AL53: =VLOOKUP(AK53,viral_genes!$C$2:$P$661,14, FALSE)
A54: 53 | B54: GEVEv2_53 | C54: contig_536 | D54: Prodigal_v2.6.3 | E54: 2101085 | F54: 2101711 | G54: + | K54: GVOG02548 | L54: 0.0026 | M54: 12.6 | X54: 209 | AK54: contig_536_90 | AL54: =VLOOKUP(AK54,viral_genes!$C$2:$P$661,14, FALSE)
A55: 54 | B55: GEVEv2_54 | C55: contig_536 | D55: Prodigal_v2.6.3 | E55: 2102059 | F55: 2102199 | G55: + | X55: 47 | AK55: contig_536_91 | AL55: =VLOOKUP(AK55,viral_genes!$C$2:$P$661,14, FALSE)
A56: 55 | B56: GEVEv2_55 | C56: contig_536 | D56: Prodigal_v2.6.3 | E56: 2102389 | F56: 2103339 | G56: + | K56: GVOGm1077 | L56: 4.7e-45 | M56: 149.1 | N56: COG3335@1|root,COG3335@2|Bacteria,1P76X@1224|Proteobacteria,2U16U@28211|Alphaproteobacteria,2JSK6@204441|Rhodospirillales | P56: Evidence 3 Function proposed based on presence of conserved amino acid motif, structural feature or limited homology | Q56: L | R56: 204441|Rhodospirillales | S56: 1.53e-09 | T56: 62.8 | U56: DDE_3 | V56: PF13358 | PF13592 | W56: DDE superfamily endonuclease | Winged helix-turn helix | X56: 317 | Y56: 6 | Z56: 2 | AA56: 4U7B_G; 4FCY_A; 4FCY_B; 1PDN_C; PF04552.16; 6PAX_A | AB56: Mos transposase/DNA Complex; transposase, transposon synaptic complex, helix-turn-helix; HET: SO4; 3.09A {Drosophila mauritiana} | Transposase, DNA; RNaseH, DDE transposase, DNA BINDING; 3.706A {Enterobacteria phage Mu} | Transposase, DNA; RNaseH, DDE transposase, DNA BINDING; 3.706A {Enterobacteria phage Mu} | PRD PAIRED/DNA COMPLEX; PROTEIN-DNA COMPLEX, DOUBLE HELIX, PAX; 2.5A {Drosophila melanogaster} SCOP: a.4.1.5 | ; Sigma54_DBD ; Sigma-54, DNA binding domain | HOMEOBOX PROTEIN PAX-6/DNA COMPLEX; PAX, PAIRED DOMAIN, TRANSCRIPTION, PROTEIN-DNA; 2.5A {Homo sapiens} SCOP: a.4.1.5 | AC56: 0.57753164556962 | AD56: 99.88 | AK56: contig_536_92 | AL56: =VLOOKUP(AK56,viral_genes!$C$2:$P$661,14, FALSE) -> Fanzor_A_transposase
A57: 56 | B57: GEVEv2_56 | C57: contig_536 | D57: GeneMark.hmm3 | E57: 2103640 | F57: 2107116 | G57: + | K57: GVOGm0180 | L57: 1.1e-16 | M57: 55 | X57: 1159 | Y57: 3 | Z57: 1 | AA57: 7C7L_B; 7L49_A; 6XMG_A | AB57: CRISPR-associated protein Cas14a.1/RNA/DNA Complex; Cas12f, Cas14, sgRNA, target DNA; 3.0A {uncultured archaeon} | Cas12f1/DNA Complex; CRISPR CAS, RNA BINDING PROTEIN;{unidentified} | Cas12i/DNA Complex; CRISPR, HYDROLASE-RNA complex;{Lachnospiraceae bacterium ND2006} | AC57: 0.160621761658031 | AD57: 94.76 | AF57: DVP | AG57: t1 (1) | AK57: contig_536_93 | AL57: =VLOOKUP(AK57,viral_genes!$C$2:$P$661,14, FALSE) -> Fanzor_A_nuclease
A58: 57 | B58: GEVEv2_57 | C58: contig_536 | D58: Prodigal_v2.6.3 | E58: 2107284 | F58: 2107541 | G58: - | X58: 86 | Y58: 3 | Z58: 1 | AA58: PF05344.14; 7LWR_D; 6AMA_G | AB58: ; DUF746 ; Domain of Unknown Function (DUF746) | DNA Packaging, Terminase, VIRAL PROTEIN; 2.35A {Enterobacteria phage P21} | DNA binding domain-containing protein, excisionase; BldC, S. coelicolor, developmental switch; 3.09A {Streptomyces venezuelae} | AC58: 0.537254901960784 | AD58: 97 | AK58: contig_536_94 | AL58: =VLOOKUP(AK58,viral_genes!$C$2:$P$661,14, FALSE)
A59: 58 | B59: GEVEv2_58 | C59: contig_536 | D59: AUGUSTUS | E59: 2107722 | F59: 2108360 | G59: - | X59: 182 | Y59: 3 | Z59: 1 | AA59: 2HL8_A; 1EUV_A; 2G4D_C | AB59: Ubiquitin-like-specific protease 1 (E.C.3.4.22.-); hydrolase; 2.0A {Saccharomyces cerevisiae} SCOP: d.3.1.7 | ULP1 PROTEASE/UBITQUTIN-LIKE PROTEIN SMT3; SUMO HYDROLASE, UBIQUITIN-LIKE PROTEASE 1; 1.6A {Saccharomyces cerevisiae} SCOP: d.3.1.7 | protease, ubiquitin-like protein, SUMO maturation; 2.8A {Homo sapiens} SCOP: d.3.1.7 | AC59: 0.907918968692449 | AD59: 92.35 | AE59: yes | AG59: t1 (2) | AH59: 1 | AI59: yes | AK59: contig_536_95-96 | AL59: =VLOOKUP(AK59,viral_genes!$C$2:$P$661,14, FALSE) -> #N/A
A60: 59 | B60: GEVEv2_59 | C60: contig_536 | D60: Prodigal_v2.6.3 | E60: 2108357 | F60: 2108485 | G60: - | X60: 43 | AK60: contig_536_97 | AL60: =VLOOKUP(AK60,viral_genes!$C$2:$P$661,14, FALSE)
A61: 60 | B61: GEVEv2_60 | C61: contig_536 | D61: AUGUSTUS | E61: 2108984 | F61: 2110546 | G61: - | K61: GVOGm0339 | L61: 1.9e-06 | M61: 22.5 | X61: 160 | AF61: DVP | AG61: t1 (4) | AH61: 3 | AI61: yes | AK61: contig_536_98 | AL61: =VLOOKUP(AK61,viral_genes!$C$2:$P$661,14, FALSE)
A62: 61 | B62: GEVEv2_61 | C62: contig_536 | D62: AUGUSTUS | E62: 2110626 | F62: 2110871 | G62: - | K62: GVOG09246 | L62: 4.3e-15 | M62: 50 | X62: 82 | AF62: DVP | AG62: t1 (1) | AK62: contig_536_99 | AL62: =VLOOKUP(AK62,viral_genes!$C$2:$P$661,14, FALSE)
A63: 62 | B63: GEVEv2_62 | C63: contig_536 | D63: AUGUSTUS | E63: 2111842 | F63: 2115344 | G63: - | V63: PF13229 | PF12708 | W63: Right handed beta helix region | Pectate lyase superfamily protein | X63: 1117 | Y63: 5 | Z63: 2 | AA63: 2PYH_B; 5LW3_A; 7CHU_B; PF13229.9; PF05048.16 | AB63: Poly(beta-D-mannuronate) C5 epimerase 4 (E.C.5.1.3.-); beta-helix, epimerase, mannuronic acid, ISOMERASE; HET: MAV; 2.7A {Azotobacter vinelandii} | Poly(beta-D-mannuronate) C5 epimerase 6 (E.C.5.1.3.-); C-5 Epimerase, isomerase; HET: B3P; 1.19A {Azotobacter vinelandii} | Putative pectin lyase; Tailspike protein, Thermophilic bacteriophage, CELL; 2.008A {Geobacillus virus E2} | ; Beta_helix ; Right handed beta helix region | ; NosD ; Periplasmic copper-binding protein (NosD) | AC63: 0.203405017921147 | AD63: 99.41 | AG63: t1 (2) | AH63: 1 | AI63: yes | AK63: contig_536_100 | AL63: =VLOOKUP(AK63,viral_genes!$C$2:$P$661,14, FALSE)
A64: 63 | B64: GEVEv2_63 | C64: contig_536 | D64: AUGUSTUS | E64: 2115435 | F64: 2119490 | G64: + | K64: GVOGm0669 | L64: 3.4e-17 | M64: 57.7 | V64: PF02839 | W64: Carbohydrate-binding module family 5/12 | X64: 1352 | AF64: DVP | AG64: t1 (1) | AK64: contig_536_101 | AL64: =VLOOKUP(AK64,viral_genes!$C$2:$P$661,14, FALSE)
A65: 64 | B65: GEVEv2_64 | C65: contig_536 | D65: AUGUSTUS | E65: 2119504 | F65: 2136261 | G65: - | V65: PF02839 | W65: Carbohydrate-binding module family 5/12 | X65: 5564 | AF65: DVP | AG65: t1 (2) | AH65: 1 | AI65: yes | AK65: contig_536_102 | AL65: =VLOOKUP(AK65,viral_genes!$C$2:$P$661,14, FALSE)
A66: 65 | B66: GEVEv2_65 | C66: contig_536 | D66: Prodigal_v2.6.3 | E66: 2136414 | F66: 2136740 | G66: + | X66: 109 | AF66: DVP | AK66: contig_536_103 | AL66: =VLOOKUP(AK66,viral_genes!$C$2:$P$661,14, FALSE)
A67: 66 | B67: GEVEv2_66 | C67: contig_536 | D67: AUGUSTUS | E67: 2136731 | F67: 2147622 | G67: - | K67: GVOG04913 | L67: 9.5e-27 | M67: 87.9 | X67: 3598 | AG67: t1 (2) | AH67: 1 | AI67: yes | AL67: =VLOOKUP(AK67,viral_genes!$C$2:$P$661,14, FALSE) -> #N/A
A68: 67 | B68: GEVEv2_67 | C68: contig_536 | D68: AUGUSTUS | E68: 2147842 | F68: 2149074 | G68: + | X68: 411 | AG68: t1 (1) | AK68: contig_536_106 | AL68: =VLOOKUP(AK68,viral_genes!$C$2:$P$661,14, FALSE)
A69: 68 | B69: GEVEv2_68 | C69: contig_536 | D69: AUGUSTUS | E69: 2149090 | F69: 2153397 | G69: - | K69: GVOGm0272 | L69: 1.7e-09 | M69: 31.9 | X69: 1436 | Y69: 6 | Z69: 2 | AA69: 1W36_D; 3K70_D; 7MR3_D; PF13086.9; PF00580.24; 6JDS_A | AB69: EXODEOXYRIBONUCLEASE V BETA CHAIN (E.C.3.1.11.5); RECOMBINATION, HELICASE, NUCLEASE, HYDROLASE, DNA; 3.1A {ESCHERICHIA COLI} SCOP: c.37.1.19 | Exodeoxyribonuclease V beta chain (E.C.3.1.11.5); RECOMBINATION, HELICASE, NUCLEASE, HYDROLASE, DNA; HET: 5IU; 3.59A {Escherichia coli K-12} | SF1 helicase, complex, DNA repair;{Escherichia coli (strain K12)} | ; AAA_11 ; AAA domain | ; UvrD-helicase ; UvrD/REP helicase N-terminal domain | PP1b; Helicase, ATPase, Truncated, VIRAL PROTEIN; 2.5A {Porcine reproductive and respiratory syndrome virus} | AC69: 0.169337979094077 | AD69: 99.9 | AG69: t1 (1) | AJ69: yes | AK69: contig_536_107 | AL69: =VLOOKUP(AK69,viral_genes!$C$2:$P$661,14, FALSE)
A70: 69 | B70: GEVEv2_69 | C70: contig_536 | D70: AUGUSTUS | E70: 2153447 | F70: 2154238 | G70: - | K70: GVOGm0423 | L70: 0.074 | M70: 7.6 | X70: 264 | AG70: t1 (1) | AK70: contig_536_108 | AL70: =VLOOKUP(AK70,viral_genes!$C$2:$P$661,14, FALSE)
A71: 70 | B71: GEVEv2_70 | C71: contig_536 | D71: AUGUSTUS | E71: 2154361 | F71: 2155200 | G71: + | K71: GVOGm0099 | L71: 4.3e-06 | M71: 21.3 | X71: 280 | AF71: DVP | AG71: t1 (1) | AK71: contig_536_109 | AL71: =VLOOKUP(AK71,viral_genes!$C$2:$P$661,14, FALSE)
A72: 71 | B72: GEVEv2_71 | C72: contig_536 | D72: AUGUSTUS | E72: 2155214 | F72: 2155783 | G72: - | N72: COG1435@1|root,KOG4197@1|root,KOG3125@2759|Eukaryota,KOG4197@2759|Eukaryota,37N7B@33090|Viridiplantae,3G9NU@35493|Streptophyta | P72: Pentatricopeptide repeat-containing protein | Q72: F | R72: 35493|Streptophyta | S72: 4.18e-23 | T72: 103 | U72: PPR,PPR_2,TK | V72: PF00265 | W72: Thymidine kinase | X72: 190 | Y72: 3 | Z72: 1 | AA72: 2J9R_A; 2JA1_A; 2B8T_A | AB72: THYMIDINE KINASE (E.C.2.7.1.21); TK1, DNK, LASSO, KINASE, TRANSFERASE; HET: THM; 2.7A {BACILLUS ANTHRACIS} | THYMIDINE KINASE (E.C.2.7.1.21); TK1, DNK, LASSO, KINASE, TRANSFERASE; HET: TTP; 2.8A {BACILLUS CEREUS} | DEOXYRIBONUCLEOSIDE KINASE, ZINC-BINDING DOMAIN, TK1; HET: THM; 2.0A {Ureaplasma parvum} SCOP: g.39.1.14, c.37.1.24 | AC72: 0.957671957671958 | AD72: 100 | AG72: t1 (1) | AJ72: yes | AK72: contig_536_110 | AL72: =VLOOKUP(AK72,viral_genes!$C$2:$P$661,14, FALSE)
A73: 72 | B73: GEVEv2_72 | C73: contig_536 | D73: AUGUSTUS | E73: 2155846 | F73: 2156712 | G73: - | K73: GVOG01720 | L73: 0.0044 | M73: 10.8 | X73: 289 | AG73: t1 (1) | AK73: contig_536_111 | AL73: =VLOOKUP(AK73,viral_genes!$C$2:$P$661,14, FALSE)
A74: 73 | B74: GEVEv2_73 | C74: contig_536 | D74: AUGUSTUS | E74: 2156782 | F74: 2158278 | G74: - | K74: GVOGm1581 | L74: 2.4e-15 | M74: 51.5 | X74: 499 | Y74: 4 | Z74: 2 | AA74: PF01743.23; 4X4W_A; 3H38_A; 3H39_B | AB74: ; PolyA_pol ; Poly A polymerase head domain | A.fulgidus CCA-adding enzyme (E.C.2.7.7.72); protein-RNA complex, tRNA, non-coding RNA; HET: SO4, GOL, FLC; 1.9A {Homo sapiens} | TRNA nucleotidyl transferase-related protein (E.C.2.7.7.25); TRANSFERASE/RNA, Nucleotide-binding, Nucleotidyltransferase, RNA-binding, Transferase; 2.37A {Thermotoga maritima} | TRNA nucleotidyl transferase-related protein (E.C.2.7.7.25); TRANSFERASE/RNA, Nucleotide-binding, Nucleotidyltransferase, RNA-binding, Transferase; HET: ATP; 2.854A {Thermotoga maritima} | AC74: 0.229417670682731 | AD74: 96.26 | AF74: DVP | AG74: t1 (1) | AK74: contig_536_112 | AL74: =VLOOKUP(AK74,viral_genes!$C$2:$P$661,14, FALSE)
A75: 74 | B75: GEVEv2_74 | C75: contig_536 | D75: AUGUSTUS | E75: 2158833 | F75: 2160116 | G75: - | H75: mcp | I75: 1.2e-99 | J75: 328.9 | K75: GVOGm0003 | L75: 7.1e-117 | M75: 385.6 | V75: PF16903 | PF04451 | W75: Major capsid protein N-terminus | Large eukaryotic DNA virus major capsid protein | X75: 428 | Y75: 5 | Z75: 3 | AA75: 6OJN_A; 5TIP_B; 6KU9_B; PF16903.8; PF04451.15 | AB75: Major capsid protein; icosahedral, trimers, outer coat, anchor; 8.6A {Singapore grouper iridovirus} | Major capsid protein; VIRAL PROTEIN; HET: FUC, XXR, GLA, RM4, 7CV, BGC, MAN, XYP; 2.0A {Paramecium bursaria Chlorella virus 1} | B646L; capsid protein, VIRAL PROTEIN; 2.67A {African swine fever virus} | ; Capsid_N ; Major capsid protein N-terminus | ; Capsid_NCLDV ; Large eukaryotic DNA virus major capsid protein | AC75: 0.724121779859485 | AD75: 100 | AF75: DVP | AG75: t1 (1) | AJ75: yes | AK75: contig_536_114 | AL75: =VLOOKUP(AK75,viral_genes!$C$2:$P$661,14, FALSE) -> other MCP
A76: 75 | B76: GEVEv2_75 | C76: contig_536 | D76: AUGUSTUS | E76: 2160288 | F76: 2161577 | G76: + | K76: GVOGm0014 | L76: 1.1e-29 | M76: 98.8 | X76: 430 | AG76: t1 (1) | AJ76: yes | AK76: contig_536_115 | AL76: =VLOOKUP(AK76,viral_genes!$C$2:$P$661,14, FALSE)
A77: 76 | B77: GEVEv2_76 | C77: contig_536 | D77: AUGUSTUS | E77: 2161647 | F77: 2162282 | G77: + | K77: GVOGm0144 | L77: 3.3e-11 | M77: 38.6 | V77: PF13884 | W77: Chaperone of endosialidase | X77: 212 | Y77: 1 | Z77: 1 | AA77: 1COI_A | AB77: COIL-VALD; ALPHA-HELICAL BUNDLE, PROTEIN DESIGN, COILED; 2.1A {synthetic construct} SCOP: k.40.1.1 | AC77: 0.127962085308057 | AD77: 84.85 | AF77: DVP | AG77: t1 (1) | AK77: contig_536_116 | AL77: =VLOOKUP(AK77,viral_genes!$C$2:$P$661,14, FALSE)
A78: 77 | B78: GEVEv2_77 | C78: contig_536 | D78: AUGUSTUS | E78: 2162311 | F78: 2164019 | G78: + | K78: GVOG06153 | L78: 8.8e-13 | M78: 42.9 | X78: 498 | Y78: 3 | Z78: 1 | AA78: 3OY2_A; 7MI0_A; 4N9W_A | AB78: Glycosyltransferase B736L; Rossmann fold, glycosyltransferase, GDP-mannose, sugar; 2.31A {Paramecium bursaria Chlorella virus NY2A} | Glycosyltransferase; SSGCID, Glycosyltransferase, Rickettsia africae, transferase; 2.9A {Rickettsia africae (strain ESF-5)} | GDP-mannose-dependent alpha-(1-2)-phosphatidylinositol mannosyltransferase (E.C.2.4.1.57); GT-B, transferase; HET: GDP; 1.94A {Mycobacterium smegmatis} | AC78: 0.707578806170356 | AD78: 99.87 | AF78: DVP | AG78: t1 (3) | AH78: 2 | AI78: yes | AK78: contig_536_117 | AL78: =VLOOKUP(AK78,viral_genes!$C$2:$P$661,14, FALSE)
A79: 78 | B79: GEVEv2_78 | C79: contig_536 | D79: AUGUSTUS | E79: 2164129 | F79: 2165379 | G79: - | X79: 417 | AG79: t1 (1) | AK79: contig_536_118 | AL79: =VLOOKUP(AK79,viral_genes!$C$2:$P$661,14, FALSE)
A80: 79 | B80: GEVEv2_79 | C80: contig_536 | D80: Prodigal_v2.6.3 | E80: 2165552 | F80: 2165806 | G80: + | X80: 85 | AF80: DVP | AK80: contig_536_119 | AL80: =VLOOKUP(AK80,viral_genes!$C$2:$P$661,14, FALSE)
A81: 80 | B81: GEVEv2_80 | C81: contig_536 | D81: AUGUSTUS | E81: 2165827 | F81: 2166399 | G81: - | X81: 191 | AF81: DVP | AG81: t1 (1) | AK81: contig_536_120 | AL81: =VLOOKUP(AK81,viral_genes!$C$2:$P$661,14, FALSE)
A82: 81 | B82: GEVEv2_81 | C82: contig_536 | D82: AUGUSTUS | E82: 2166527 | F82: 2166997 | G82: + | X82: 157 | AG82: t1 (1) | AK82: contig_536_121 | AL82: =VLOOKUP(AK82,viral_genes!$C$2:$P$661,14, FALSE)
A83: 82 | B83: GEVEv2_82 | C83: contig_536 | D83: AUGUSTUS | E83: 2167032 | F83: 2168201 | G83: - | K83: GVOGm0685 | L83: 1.1e-10 | M83: 35.7 | X83: 390 | AG83: t1 (1) | AK83: contig_536_122 | AL83: =VLOOKUP(AK83,viral_genes!$C$2:$P$661,14, FALSE)
A84: 83 | B84: GEVEv2_83 | C84: contig_536 | D84: AUGUSTUS | E84: 2168276 | F84: 2169325 | G84: - | K84: GVOGm0099 | L84: 7.5e-08 | M84: 27.1 | X84: 350 | Y84: 1 | Z84: 1 | AA84: 2ZAA_A | AB84: ALGINATE LYASE, POLYSACCHARIDE LYASE FAMILY; HET: BEM, MAW, LGU; 1.8A {Sphingomonas sp.} | AC84: 0.106017191977077 | AD84: 80.19 | AG84: t1 (1) | AK84: contig_536_123 | AL84: =VLOOKUP(AK84,viral_genes!$C$2:$P$661,14, FALSE)
A85: 84 | B85: GEVEv2_84 | C85: contig_536 | D85: Prodigal_v2.6.3 | E85: 2169385 | F85: 2170083 | G85: + | K85: GVOG00104 | L85: 0.00068 | M85: 14.2 | X85: 233 | AK85: contig_536_124 | AL85: =VLOOKUP(AK85,viral_genes!$C$2:$P$661,14, FALSE)
A86: 85 | B86: GEVEv2_85 | C86: contig_536 | D86: AUGUSTUS | E86: 2170042 | F86: 2170608 | G86: - | K86: GVOGm1399 | L86: 2.5e-37 | M86: 122.9 | V86: PF01652 | W86: Eukaryotic initiation factor 4E | X86: 189 | Y86: 4 | Z86: 2 | AA86: 1WKW_A; 4B6V_A; 5ME5_A; PF08939.13 | AB86: Eukaryotic translation initiation factor 4E/Eukaryotic; translation, initiation factor, cap-binding protein; HET: GTA; 2.1A {Homo sapiens} SCOP: d.86.1.1 | EUKARYOTIC TRANSLATION INITIATION FACTOR 4E; TRANSLATION, M7G CAP; NMR {MUS MUSCULUS} | Eukaryotic transcription initiation factor 4E; translation initiation eIF4F complex, translation; HET: SO4; 1.9A {Cucumis melo} | ; DUF1917 ; Domain of unknown function (DUF1917) | AC86: 0.710106382978723 | AD86: 99.94 | AG86: t1 (1) | AK86: contig_536_125 | AL86: =VLOOKUP(AK86,viral_genes!$C$2:$P$661,14, FALSE)
A87: 86 | B87: GEVEv2_86 | C87: contig_536 | D87: AUGUSTUS | E87: 2170673 | F87: 2171271 | G87: - | K87: GVOGm0004 | L87: 7.9e-21 | M87: 69.5 | V87: PF04777 | W87: Erv1 / Alr family | X87: 145 | Y87: 6 | Z87: 2 | AA87: 4E0I_A; 4E0I_B; 3W4Y_C; PF05214.15; 3P0K_A; 5XTQ_D | AB87: Mitochondrial FAD-linked sulfhydryl oxidase ERV1; Flavin-linked sulfhydryl oxidase, Mia40, oxidation; HET: FAD; 3.0A {Saccharomyces cerevisiae} | Mitochondrial FAD-linked sulfhydryl oxidase ERV1; Flavin-linked sulfhydryl oxidase, Mia40, oxidation; HET: FAD; 3.0A {Saccharomyces cerevisiae} | Mitochondrial FAD-linked sulfhydryl oxidase ERV1; alpha helix, disulfide bond, redox; HET: FAD; 2.0A {Saccharomyces cerevisiae} | ; Baculo_p33 ; Baculovirus P33 | 33 kDa early protein homolog; 4-helix bundle, 5-helix bundle, flavin; HET: FAD; 1.47A {Autographa californica nucleopolyhedrovirus} | FAD-linked sulfhydryl oxidase (E.C.1.8.3.2); sulfhydryl oxidase, OXIDOREDUCTASE; HET: FAD, GOL; 2.04A {Autographa californica nucleopolyhedrovirus} | AC87: 0.533564814814815 | AD87: 99.85 | AG87: t1 (2) | AH87: 1 | AI87: yes | AL87: =VLOOKUP(AK87,viral_genes!$C$2:$P$661,14, FALSE) -> #N/A
A88: 87 | B88: GEVEv2_87 | C88: contig_536 | D88: AUGUSTUS | E88: 2171379 | F88: 2173539 | G88: + | X88: 693 | AG88: t1 (2) | AH88: 1 | AI88: yes | AL88: =VLOOKUP(AK88,viral_genes!$C$2:$P$661,14, FALSE) -> #N/A
A89: 88 | B89: GEVEv2_88 | C89: contig_536 | D89: AUGUSTUS | E89: 2173555 | F89: 2177280 | G89: - | K89: GVOGm0461 | L89: 0 | M89: 1390.9 | N89: COG0187@1|root,KOG0355@2759|Eukaryota,38CPA@33154|Opisthokonta,3NWYX@4751|Fungi | O89: TOP2 | P89: Control of topological states of DNA by transient breakage and subsequent rejoining of DNA strands. Topoisomerase II makes double-strand breaks | Q89: B | R89: 4751|Fungi | S89: 9.07e-305 | T89: 917 | U89: DNA_gyraseB,DNA_topoisoIV,HATPase_c,TOPRIM_C,Toprim | V89: PF00204 | PF00521 | PF02518 | PF01751 | PF16898 | W89: DNA gyrase B | DNA gyrase/topoisomerase IV, subunit A | Histidine kinase-, DNA gyrase B-, and HSP90-like ATPase | Toprim domain | C-terminal associated domain of TOPRIM | X89: 1242 | Y89: 28 | Z89: 12 | AA89: 6ZY7_B; 4GFH_A; 4GFH_F; 6CA8_A; 4FM9_A; 3QX3_A; 4JUO_C; 6RKV_D; 6RKW_B; 2INR_A; 5IWI_C; 4Z2C_A; 7L6S_A; 1PVG_B; 1QZR_A; 5BTG_D; 4Z2C_D; 4Z2D_C; 4DUH_B; 6YD9_A; 4K4O_A; PF00204.28; PF16898.8; 4ELY_A; 4ELZ_A; 5NP6_C; 1X75_A; PF01751.25 | AB89: DNA topoisomerase 2-alpha/DNA Complex; Human Topoisomerase, Etoposide, DNA, ISOMERASE; HET: ANP, EVP;{Homo sapiens} | DNA topoisomerase 2 (E.C.5.99.1.3)/DNA complex; TOPOISOMERASE, PROTEIN-DNA COMPLEX, DNA SUPERCOILING; HET: TSP, PTR, ANP; 4.408A {Saccharomyces cerevisiae} | DNA topoisomerase 2 (E.C.5.99.1.3)/DNA complex; TOPOISOMERASE, PROTEIN-DNA COMPLEX, DNA SUPERCOILING; HET: TSP, PTR, ANP; 4.408A {Saccharomyces cerevisiae} | Topoisomerase 2 (E.C.5.99.1.3); Topoisomerase, DNA-binding domain, ISOMERASE; 2.331A {Plasmodium falciparum} | DNA topoisomerase 2-alpha (E.C.5.99.1.3)/DNA complex; TOPOISOMERASE, DNA-BINDING, PROTEIN-DNA COMPLEX, ISOMERASE-DNA; 2.901A {Homo sapiens} | DNA topoisomerase 2-beta (E.C.5.99.1.3)/DNA complex; TOPRIM domain, winged-helix domain, coiled-coil; HET: EVP; 2.162A {Homo sapiens} | DNA topoisomerase 4 subunit A; full-length ParE, ParC55, open N-gate; HET: LFX; 6.53A {Streptococcus pneumoniae} | DNA gyrase subunit A, DNA; Isomerase, Complex, DNA Gyrase, Inhibitor; 4.6A {Escherichia coli (strain K12)} | DNA gyrase subunit A, DNA; Isomerase, Complex, DNA Gyrase, Inhibitor; HET: JHN, ANP; 6.6A {Escherichia coli (strain K12)} | DNA topoisomerase 4 subunit A; topoisomerase II fold, ISOMERASE; HET: EDO; 2.8A {Staphylococcus aureus} | DNA gyrase subunit A, DNA; TYPE IIA TOPOISOMERASE, ANTIBACTERIAL, INHIBITOR; HET: 6EJ, GOL; 1.98A {Staphylococcus aureus} | GyrA59 from S. pneumoniae, GyrB30; Gyrase, Cleavage complex, DNA, quinolone; HET: MFX; 3.19A {Streptococcus pneumoniae} | DNA topoisomerase II; SSGCID, DNA topoisomerase II, Balamuthia; HET: EDO, ANP; 1.95A {Balamuthia mandrillaris} | DNA topoisomerase II (E.C.5.99.1.3); GHKL ATPase domain, ISOMERASE; HET: ANP, MSE; 1.8A {Saccharomyces cerevisiae} SCOP: d.14.1.3, d.122.1.2 | DNA topoisomerase II (E.C.5.99.1.3); GHKL ATPASE DOMAIN, ICRF, ICRF-187; HET: CDX, ANP; 1.9A {Saccharomyces cerevisiae} SCOP: d.14.1.3, d.122.1.2 | DNA gyrase subunit A, DNA; protein-DNA complex, topoisomerase II, Isomerase-DNA; HET: LFX, PTR; 2.5A {Mycobacterium tuberculosis (strain ATCC 25618 / H37Rv)} | GyrA59 from S. pneumoniae, GyrB30; Gyrase, Cleavage complex, DNA, quinolone; HET: MFX; 3.19A {Streptococcus pneumoniae} | GyrA59 subunit of gyrase from; Gyrase, Cleavage complex, DNA, quinolone; HET: LFX; 3.38A {Streptococcus pneumoniae} | DNA gyrase subunit B (E.C.5.99.1.3); structure-based drug design, antibacterial, DNA; HET: RLI; 1.5A {Escherichia coli} | DNA gyrase, topoisomerase IV, inhibitor; HET: ON2; 1.6A {Escherichia coli (strain K12)} | DNA gyrase subunit B (E.C.5.99.1.3); ATP-binding, Nucleotide-binding, Topoisomerase, ATP-binding domain; HET: DOO; 1.3A {Enterococcus faecalis} | ; DNA_gyraseB ; DNA gyrase B | ; TOPRIM_C ; C-terminal associated domain of TOPRIM | DNA gyrase subunit A (E.C.5.99.1.3); ALPHA+BETA, TOPOISOMERASE, TOXIN-ISOMERASE complex; 1.932A {Shigella flexneri} | DNA gyrase subunit A (E.C.5.99.1.3); ALPHA+BETA, TOPOISOMERASE, TOXIN-ISOMERASE complex; 2.2A {Vibrio fischeri} | DNA topoisomerase small subunit, 30S; ribosome, translation, bypassing, protein; HET: 5MC, 5MU, OMC, 4OC, 1MG, 2MG, PSU, UR3, 7MG, MA6, 6MZ, H2U, 2MA, OMU, 3TD, OMG; 3.6A {Escherichia coli} | DNA gyrase subunit A (E.C.5.99.1.3)/Cytotoxic; gyrase, CcdB, topoisomerase, plasmid addiction; 2.8A {Escherichia coli} SCOP: e.11.1.1 | ; Toprim ; Toprim domain | AC89: 0.338494301830321 | AD89: 100 | AG89: t1 (1) | AJ89: yes | AK89: contig_536_130 | AL89: =VLOOKUP(AK89,viral_genes!$C$2:$P$661,14, FALSE) -> Topoisomerase II
A90: 89 | B90: GEVEv2_89 | C90: contig_536 | D90: AUGUSTUS | E90: 2177982 | F90: 2179472 | G90: + | K90: GVOGm0339 | L90: 1.7e-28 | M90: 94.7 | V90: PF00535 | W90: Glycosyl transferase family 2 | X90: 381 | Y90: 3 | Z90: 1 | AA90: 3BCV_B; 5HEA_B; 5HEC_A | AB90: Putative glycosyltransferase protein; Glycosyltransferase, Protein Structure Initiative II; HET: MSE; 2.35A {Bacteroides fragilis} | Putative glycosyltransferase (GalT1); Glycosyltransferase, helix binding domain, TRANSFERASE; 2.003A {Streptococcus parasanguinis FW213} | Putative glycosyltransferase (GalT1); glycosyltransferase, helix binding domain, TRANSFERASE; 2.395A {Streptococcus parasanguinis FW213} | AC90: 0.292105263157895 | AD90: 99.26 | AG90: t1 (3) | AH90: 2 | AI90: yes | AL90: =VLOOKUP(AK90,viral_genes!$C$2:$P$661,14, FALSE) -> #N/A
A91: 90 | B91: GEVEv2_90 | C91: contig_536 | D91: AUGUSTUS | E91: 2179668 | F91: 2180189 | G91: - | K91: GVOGm0717 | L91: 1.7e-06 | M91: 22.2 | X91: 174 | AG91: t1 (1) | AK91: contig_536_133 | AL91: =VLOOKUP(AK91,viral_genes!$C$2:$P$661,14, FALSE)
A92: 91 | B92: GEVEv2_91 | C92: contig_536 | D92: AUGUSTUS | E92: 2180310 | F92: 2180831 | G92: + | K92: GVOGm0263 | L92: 7.9e-36 | M92: 118.1 | V92: PF19065 | W92: Family of unknown function (DUF5761) | X92: 174 | Y92: 2 | Z92: 2 | AA92: 6NCL_c9; PF19065.3 | AB92: PBCV-1 capsid; tape-measure protein, minor capsid proteins; 3.5A {Paramecium bursaria Chlorella virus 1} | ; DUF5761 ; Family of unknown function (DUF5761) | AC92: 0.58092485549133 | AD92: 100 | AG92: t1 (1)| t2 (1) | AK92: contig_536_134 | AL92: =VLOOKUP(AK92,viral_genes!$C$2:$P$661,14, FALSE)
A93: 92 | B93: GEVEv2_92 | C93: contig_536 | D93: AUGUSTUS | E93: 2180896 | F93: 2181852 | G93: + | K93: GVOGm0056 | L93: 2.7e-56 | M93: 185.6 | V93: PF00352 | W93: Transcription factor TFIID (or TATA-binding protein, TBP) | X93: 319 | Y93: 4 | Z93: 2 | AA93: 2Z8U_Q; 1YTB_A; 6UEP_B; PF00352.24 | AB93: TATA-box-binding protein; Transcription, DNA-binding protein, transcription factor; 1.9A {Methanococcus jannaschii} | TATA BINDING PROTEIN (TBP)/DNA COMPLEX; PROTEIN-DNA COMPLEX, TRANSCRIPTION-DNA COMPLEX; 1.8A {Saccharomyces cerevisiae} SCOP: d.129.1.1 | TATA-box-binding protein 1/DNA Complex; TBP, TATA, C-C mismatch, NER; HET: GOL; 2.05A {Arabidopsis thaliana} | ; TBP ; Transcription factor TFIID (or TATA-binding protein, TBP) | AC93: 0.488207547169811 | AD93: 99.87 | AF93: DVP | AG93: t1 (1) | AK93: contig_536_135 | AL93: =VLOOKUP(AK93,viral_genes!$C$2:$P$661,14, FALSE)
A94: 93 | B94: GEVEv2_93 | C94: contig_536 | D94: AUGUSTUS | E94: 2181922 | F94: 2182869 | G94: + | K94: GVOGm0056 | L94: 1.9e-48 | M94: 159.9 | V94: PF00352 | W94: Transcription factor TFIID (or TATA-binding protein, TBP) | X94: 316 | Y94: 4 | Z94: 2 | AA94: 1RM1_A; 2Z8U_Q; 1YTB_A; PF00352.24 | AB94: TATA-box binding PROTEIN/Transcription initiation factor; Yeast TFIIA, TBP protein, ATA-box; 2.5A {Saccharomyces cerevisiae} SCOP: d.129.1.1 | TATA-box-binding protein; Transcription, DNA-binding protein, transcription factor; 1.9A {Methanococcus jannaschii} | TATA BINDING PROTEIN (TBP)/DNA COMPLEX; PROTEIN-DNA COMPLEX, TRANSCRIPTION-DNA COMPLEX; 1.8A {Saccharomyces cerevisiae} SCOP: d.129.1.1 | ; TBP ; Transcription factor TFIID (or TATA-binding protein, TBP) | AC94: 0.475396825396825 | AD94: 99.76 | AF94: DVP | AG94: t1 (1) | AJ94: yes | AK94: contig_536_136 | AL94: =VLOOKUP(AK94,viral_genes!$C$2:$P$661,14, FALSE)
A95: 94 | B95: GEVEv2_94 | C95: contig_536 | D95: Prodigal_v2.6.3 | E95: 2182866 | F95: 2183378 | G95: - | X95: 171 | AK95: contig_536_137 | AL95: =VLOOKUP(AK95,viral_genes!$C$2:$P$661,14, FALSE)
A96: 95 | B96: GEVEv2_95 | C96: contig_536 | D96: AUGUSTUS | E96: 2183440 | F96: 2185143 | G96: + | K96: GVOG03032 | L96: 7.8e-27 | M96: 89.3 | X96: 568 | AG96: t1 (1) | AK96: contig_536_138 | AL96: =VLOOKUP(AK96,viral_genes!$C$2:$P$661,14, FALSE)
A97: 96 | B97: GEVEv2_96 | C97: contig_536 | D97: AUGUSTUS | E97: 2185148 | F97: 2185525 | G97: - | K97: GVOGm0530 | L97: 5.2e-10 | M97: 34.6 | X97: 126 | Y97: 1 | Z97: 1 | AA97: PF19064.3 | AB97: ; DUF5760 ; Family of unknown function (DUF5760) | AC97: 0.256 | AD97: 84.84 | AG97: t1 (1) | AJ97: yes | AK97: contig_536_139 | AL97: =VLOOKUP(AK97,viral_genes!$C$2:$P$661,14, FALSE)
A98: 97 | B98: GEVEv2_97 | C98: contig_536 | D98: AUGUSTUS | E98: 2185670 | F98: 2187487 | G98: + | H98: A32 | I98: 0.0024 | J98: 12.1 | K98: GVOGm0272 | L98: 1.2e-59 | M98: 197.6 | V98: PF13086 | PF13245 | PF13401 | PF13604 | PF00580 | PF13538 | PF01443 | W98: AAA domain | AAA domain | AAA domain | AAA domain | UvrD/REP helicase N-terminal domain | UvrD-like helicase C-terminal domain | Viral (Superfamily 1) RNA helicase | X98: 606 | Y98: 11 | Z98: 4 | AA98: 3E1S_A; 3GP8_A; 1W36_D; 2ZPA_B; 6LQP_RM; 7AJT_JB; 4L0J_A; PF13087.9; 6VSX_A; 3DMN_A; 1QHH_D | AB98: Exodeoxyribonuclease V, subunit RecD; alpha and beta protein, ATP-binding; 2.2A {Deinococcus radiodurans} | Exodeoxyribonuclease V, subunit RecD, putative; ALPHA AND BETA PROTEIN, ATP-BINDING; 2.5A {Deinococcus radiodurans R1} | EXODEOXYRIBONUCLEASE V BETA CHAIN (E.C.3.1.11.5); RECOMBINATION, HELICASE, NUCLEASE, HYDROLASE, DNA; 3.1A {ESCHERICHIA COLI} SCOP: c.37.1.19 | Uncharacterized protein ypfI; RNA MODIFICATION ENZYME, RNA HELICASE; HET: ADP, ACO, MSE; 2.35A {Escherichia coli K12} | 40S ribosomal protein S1-A, 40S; ribosome assembly, 90S to pre-40S; HET: GTP; 3.2A {Saccharomyces cerevisiae S288C} | rRNA 2'-O-methyltransferase fibrillarin, 40S ribosomal; Ribosome, Ribosome biogenesis, Exosome, 90S; HET: GTP; 4.6A {Saccharomyces cerevisiae (strain ATCC 204508 / S288c)} | DNA helicase I (E.C.3.6.1.-); SH3 like domains, DNA binding; HET: MSE; 1.85A {Escherichia coli} | ; AAA_12 ; AAA domain | DNA helicase (E.C.3.6.4.12); RNA polymerase, Helicase, TRANSCRIPTION; 2.0A {Bacillus subtilis} | Putative DNA helicase; APC89291.2, DNA helicase, Lactobacillus plantarum; HET: ACT, MSE; 1.66A {Lactobacillus plantarum} | PCRA + ATP; DNA REPAIR, DNA REPLICATION, SOS; HET: ATP; 2.5A {Geobacillus stearothermophilus} | AC98: 0.360480841472577 | AD98: 99.9 | AG98: t1 (1) | AJ98: yes | AK98: contig_536_140 | AL98: =VLOOKUP(AK98,viral_genes!$C$2:$P$661,14, FALSE)
A99: 98 | B99: GEVEv2_98 | C99: contig_536 | D99: Prodigal_v2.6.3 | E99: 2187530 | F99: 2193019 | G99: + | K99: GVOGm0328 | L99: 4.6e-05 | M99: 16.8 | X99: 1830 | Y99: 3 | Z99: 1 | AA99: 6TPI_A; 7N85_J; 7N9F_z | AB99: Murein hydrolase activator EnvC, Cell; Complex, PROTEIN BINDING; 2.1A {Escherichia coli (strain K12)} | nuclear pore complex, inner ring; 7.6A {Saccharomyces cerevisiae} | NPC, nucleocytoplasmic transport, TRANSLOCASE; 37.0A {Saccharomyces cerevisiae} | AC99: 0.108984873336978 | AD99: 94.88 | AF99: DVP | AK99: contig_536_141 | AL99: =VLOOKUP(AK99,viral_genes!$C$2:$P$661,14, FALSE)
A100: 99 | B100: GEVEv2_99 | C100: contig_536 | D100: AUGUSTUS | E100: 2193070 | F100: 2193867 | G100: + | K100: GVOGm1454 | L100: 0.00076 | M100: 14.4 | X100: 266 | AF100: DVP | AG100: t1 (1) | AK100: contig_536_142 | AL100: =VLOOKUP(AK100,viral_genes!$C$2:$P$661,14, FALSE)
...

Sheet viral_genes
A1: V2 | B1: mCG | D1: number | E1: GVOG | F1: virbit | G1: vdesc | H1: pfam | I1: pfambit | J1: eggNOG_OGs | K1: COG_category | L1: Functional category | M1: eggNOG_Desc | N1: HHPred | O1: hits_to_chlamy | P1: annotation_notes | Q1: protlength | R1: strand | S1: start | T1: end | U1: contig_start | V1: contig_end | W1: Proteome1_score | X1: Proteom2_score | Y1: MeanRPKM_cf20 | Z1: MeanCounts_cf20 | AA1: ExprCluster | AB1: Proteomics
C2: contig_536_1 | D2: 1 | E2: no_hit | F2: 0 | G2: no_hit | H2: no_hit | I2: 0 | Q2: 75 | R2: -1 | S2: 35 | T2: 259 | U2: =2003807+S2 -> 2003842 | V2: =2003808+T2 -> 2004067 | Y2: 0.10215924 | Z2: 0.2
C3: contig_536_2 | D3: 2 | E3: no_hit | F3: 0 | G3: no_hit | H3: no_hit | I3: 0 | O3: Cre11.g801258_4532.1 | Q3: 338 | R3: -1 | S3: 579 | T3: 1592 | U3: =2003807+S3 -> 2004386 | V3: =2003808+T3 -> 2005400 | Y3: 1.4216146 | Z3: 11.8
C4: contig_536_3 | D4: 3 | E4: no_hit | F4: 0 | G4: no_hit | H4: no_hit | I4: 0 | Q4: 144 | R4: 1 | S4: 3098 | T4: 3529 | U4: =2003807+S4 -> 2006905 | V4: =2003808+T4 -> 2007337 | Y4: 0.07121621 | Z4: 0.2
C5: contig_536_4 | D5: 4 | E5: no_hit | F5: 0 | G5: no_hit | H5: no_hit | I5: 0 | O5: Cre01.g800142_4532.1 | Q5: 204 | R5: -1 | S5: 3786 | T5: 4397 | U5: =2003807+S5 -> 2007593 | V5: =2003808+T5 -> 2008205 | Y5: 239.83192 | Z5: 957.7
C6: contig_536_5 | D6: 5 | E6: no_hit | F6: 0 | G6: no_hit | H6: no_hit | I6: 0 | Q6: 212 | R6: 1 | S6: 5604 | T6: 6239 | U6: =2003807+S6 -> 2009411 | V6: =2003808+T6 -> 2010047 | Y6: 0.2941414 | Z6: 1.3
C7: contig_536_6 | D7: 6 | E7: no_hit | F7: 0 | G7: no_hit | H7: no_hit | I7: 0 | Q7: 111 | R7: 1 | S7: 6343 | T7: 6675 | U7: =2003807+S7 -> 2010150 | V7: =2003808+T7 -> 2010483 | Y7: 1.0941073 | Z7: 2.4
C8: contig_536_7 | D8: 7 | E8: no_hit | F8: 0 | G8: no_hit | H8: no_hit | I8: 0 | O8: Cre01.g800142_4532.1 | Q8: 135 | R8: 1 | S8: 6984 | T8: 7388 | U8: =2003807+S8 -> 2010791 | V8: =2003808+T8 -> 2011196 | Y8: 706.63425 | Z8: 1864.6
C9: contig_536_8 | D9: 8 | E9: no_hit | F9: 0 | G9: no_hit | H9: no_hit | I9: 0 | Q9: 124 | R9: -1 | S9: 7700 | T9: 8071 | U9: =2003807+S9 -> 2011507 | V9: =2003808+T9 -> 2011879 | Y9: 35.998925 | Z9: 78.4
C10: contig_536_9 | D10: 9 | E10: no_hit | F10: 0 | G10: no_hit | H10: no_hit | I10: 0 | Q10: 68 | R10: 1 | S10: 8102 | T10: 8305 | U10: =2003807+S10 -> 2011909 | V10: =2003808+T10 -> 2012113 | Y10: 0.38770977 | Z10: 0.5
C11: contig_536_10 | D11: 10 | E11: no_hit | F11: 0 | G11: no_hit | H11: no_hit | I11: 0 | Q11: 140 | R11: 1 | S11: 8430 | T11: 8849 | U11: =2003807+S11 -> 2012237 | V11: =2003808+T11 -> 2012657 | Y11: 1.8584556 | Z11: 4.8
C12: contig_536_11 | D12: 11 | E12: no_hit | F12: 0 | G12: no_hit | H12: no_hit | I12: 0 | Q12: 87 | R12: 1 | S12: 8809 | T12: 9069 | U12: =2003807+S12 -> 2012616 | V12: =2003808+T12 -> 2012877 | Y12: 2.8228675 | Z12: 5.2 | AA12: pre_induc
C13: contig_536_12 | D13: 12 | E13: no_hit | F13: 0 | G13: no_hit | H13: no_hit | I13: 0 | Q13: 96 | R13: -1 | S13: 10637 | T13: 10924 | U13: =2003807+S13 -> 2014444 | V13: =2003808+T13 -> 2014732 | Y13: 210.96673 | Z13: 404.6
C14: contig_536_13 | D14: 13 | E14: no_hit | F14: 0 | G14: no_hit | H14: no_hit | I14: 0 | Q14: 122 | R14: 1 | S14: 11216 | T14: 11581 | U14: =2003807+S14 -> 2015023 | V14: =2003808+T14 -> 2015389 | Y14: 38.392109 | Z14: 94.1
C15: contig_536_14 | D15: 14 | E15: no_hit | F15: 0 | G15: no_hit | H15: no_hit | I15: 0 | Q15: 39 | R15: 1 | S15: 11836 | T15: 11952 | U15: =2003807+S15 -> 2015643 | V15: =2003808+T15 -> 2015760 | Y15: 3.5570678 | Z15: 2.5
C16: contig_536_15 | D16: 15 | E16: no_hit | F16: 0 | G16: no_hit | H16: no_hit | I16: 0 | O16: Cre15.g635717_4532.1 | Q16: 99 | R16: -1 | S16: 12352 | T16: 12648 | U16: =2003807+S16 -> 2016159 | V16: =2003808+T16 -> 2016456 | Y16: 53.53054 | Z16: 100.7
C17: contig_536_16 | D17: 16 | E17: no_hit | F17: 0 | G17: no_hit | H17: no_hit | I17: 0 | J17: 2E0K7@1 | K17: - | M17: - | Q17: 168 | R17: -1 | S17: 14143 | T17: 14646 | U17: =2003807+S17 -> 2017950 | V17: =2003808+T17 -> 2018454 | Y17: 203.10499 | Z17: 655.2 | AA17: post_induc
C18: contig_536_17 | D18: 17 | E18: no_hit | F18: 0 | G18: no_hit | H18: no_hit | I18: 0 | O18: Cre07.g800828_4532.1 | Q18: 182 | R18: -1 | S18: 14848 | T18: 15393 | U18: =2003807+S18 -> 2018655 | V18: =2003808+T18 -> 2019201 | Y18: 642.21406 | Z18: 2112.5 | AA18: post_induc
C19: contig_536_18 | D19: 18 | E19: no_hit | F19: 0 | G19: no_hit | H19: no_hit | I19: 0 | Q19: 126 | R19: -1 | S19: 16657 | T19: 17034 | U19: =2003807+S19 -> 2020464 | V19: =2003808+T19 -> 2020842 | Y19: 1076.7721 | Z19: 2657 | AA19: post_induc
C20: contig_536_19 | D20: 19 | E20: no_hit | F20: 0 | G20: no_hit | H20: no_hit | I20: 0 | Q20: 36 | R20: 1 | S20: 17214 | T20: 17321 | U20: =2003807+S20 -> 2021021 | V20: =2003808+T20 -> 2021129 | Y20: 149.03284 | Z20: 109.7
C21: contig_536_20 | D21: 20 | E21: no_hit | F21: 0 | G21: no_hit | H21: no_hit | I21: 0 | P21: early high expressed | Q21: 288 | R21: -1 | S21: 17549 | T21: 18412 | U21: =2003807+S21 -> 2021356 | V21: =2003808+T21 -> 2022220 | Y21: 52.410252 | Z21: 304.4 | AA21: pre_induc
C22: contig_536_21 | D22: 21 | E22: GVOGm1522 | F22: 10.15382 | G22: A helicase nuclease that prepares dsDNA breaks (DSB) for recombinational DNA repair. Binds to DSBs and unwinds DNA via a highly rapid and processive ATP-dependent bidirectional helicase activity. Unwinds dsDNA until it encounters a Chi (crossover hotspot instigator) sequence from the 3' direction. Cuts ssDNA a few nucleotides 3' to the Chi site. The properties and activities of the enzyme are changed at Chi. The Chi-altered holoenzyme produces a long 3'-ssDNA overhang and facilitates RecA-binding to the ssDNA for homologous DNA recombination and repair. Holoenzyme degrades any linearized DNA that is unable to undergo homologous recombination. In the holoenzyme this subunit has ssDNA-dependent ATPase and 5'-3' helicase activity. When added to pre-assembled RecBC greatly stimulates nuclease activity and augments holoenzyme processivity. Negatively regulates the RecA-loading ability of RecBCD | Helix-turn-helix domain | G-quadruplex DNA unwinding | unknown | Helix-hairpin-helix containing domain | unknown | four-way junction helicase activity | unknown | unknown | unknown | PIF1-like helicase | Superfamily I DNA and RNA helicases and helicase subunits | DNA helicase | A helicase nuclease that prepares dsDNA breaks (DSB) for recombinational DNA repair. Binds to DSBs and unwinds DNA via a highly rapid and processive ATP-dependent bidirectional helicase activity. Unwinds dsDNA until it encounters a Chi (crossover hotspot instigator) sequence from the 3' direction. Cuts ssDNA a few nucleotides 3' to the Chi site. The properties and activities of the enzyme are changed at Chi. The Chi-altered holoenzyme produces a long 3'-ssDNA overhang and facilitates RecA-binding to the ssDNA for homologous DNA recombination and repair. Holoenzyme degrades any linearized DNA that is unable to undergo homologous recombination. In the holoenzyme this subunit has ssDNA-dependent ATPase and 5'-3' helicase activity. When added to pre-assembled RecBC greatly stimulates nuclease activity and augments holoenzyme processivity. Negatively regulates the RecA-loading ability of RecBCD | H22: AAA_30 | I22: 13.70782 | P22: early high expressed | Q22: 300 | R22: -1 | S22: 18682 | T22: 19581 | U22: =2003807+S22 -> 2022489 | V22: =2003808+T22 -> 2023389 | Y22: 97.312297 | Z22: 611.6 | AA22: pre_induc
C23: contig_536_22 | D23: 22 | E23: no_hit | F23: 0 | G23: no_hit | H23: no_hit | I23: 0 | P23: TIR 1 start; early high expressed | Q23: 1303 | R23: -1 | S23: 20490 | T23: 24398 | U23: =2003807+S23 -> 2024297 | V23: =2003808+T23 -> 2028206 | Y23: 50.09561 | Z23: 1345.3 | AA23: pre_induc
C24: contig_536_23 | D24: 23 | E24: no_hit | F24: 0 | G24: no_hit | H24: no_hit | I24: 0 | P24: early high expressed | Q24: 213 | R24: -1 | S24: 24401 | T24: 25039 | U24: =2003807+S24 -> 2028208 | V24: =2003808+T24 -> 2028847 | Y24: 716.52141 | Z24: 3162 | AA24: pre_induc
C25: contig_536_24 | D25: 24 | E25: no_hit | F25: 0 | G25: no_hit | H25: no_hit | I25: 0 | Q25: 62 | R25: 1 | S25: 29503 | T25: 29688 | U25: =2003807+S25 -> 2033310 | V25: =2003808+T25 -> 2033496 | Y25: 0.8973179 | Z25: 1.3
C26: contig_536_25 | D26: 25 | E26: no_hit | F26: 0 | G26: no_hit | H26: no_hit | I26: 0 | Q26: 159 | R26: -1 | S26: 29653 | T26: 30129 | U26: =2003807+S26 -> 2033460 | V26: =2003808+T26 -> 2033937 | Y26: 24.079208 | Z26: 75.2
C27: contig_536_26 | D27: 26 | E27: no_hit | F27: 0 | G27: no_hit | H27: no_hit | I27: 0 | Q27: 47 | R27: 1 | S27: 30829 | T27: 30969 | U27: =2003807+S27 -> 2034636 | V27: =2003808+T27 -> 2034777 | Y27: 25.077644 | Z27: 24.7
C28: contig_536_27 | D28: 27 | E28: no_hit | F28: 0 | G28: no_hit | H28: no_hit | I28: 0 | Q28: 251 | R28: 1 | S28: 31467 | T28: 32219 | U28: =2003807+S28 -> 2035274 | V28: =2003808+T28 -> 2036027 | Y28: 18.947865 | Z28: 96.5
C29: contig_536_28 | D29: 28 | E29: no_hit | F29: 0 | G29: no_hit | H29: no_hit | I29: 0 | Q29: 57 | R29: -1 | S29: 32569 | T29: 32739 | U29: =2003807+S29 -> 2036376 | V29: =2003808+T29 -> 2036547 | Y29: 10.730382 | Z29: 12.6
C30: contig_536_29 | D30: 29 | E30: no_hit | F30: 0 | G30: no_hit | H30: no_hit | I30: 0 | P30: TIR 1 end | Q30: 95 | R30: -1 | S30: 33143 | T30: 33427 | U30: =2003807+S30 -> 2036950 | V30: =2003808+T30 -> 2037235 | Y30: 6.6609876 | Z30: 12.7
C31: contig_536_30 | D31: 30 | E31: no_hit | F31: 0 | G31: no_hit | H31: no_hit | I31: 0 | Q31: 116 | R31: 1 | S31: 33978 | T31: 34325 | U31: =2003807+S31 -> 2037785 | V31: =2003808+T31 -> 2038133 | Y31: 44.252759 | Z31: 103.1
C32: contig_536_31 | D32: 31 | E32: no_hit | F32: 0 | G32: no_hit | H32: no_hit | I32: 0 | Q32: 45 | R32: -1 | S32: 34662 | T32: 34796 | U32: =2003807+S32 -> 2038469 | V32: =2003808+T32 -> 2038604 | Y32: 95.093289 | Z32: 89.4
C33: contig_536_32 | D33: 32 | E33: no_hit | F33: 0 | G33: no_hit | H33: no_hit | I33: 0 | Q33: 97 | R33: -1 | S33: 34854 | T33: 35144 | U33: =2003807+S33 -> 2038661 | V33: =2003808+T33 -> 2038952 | Y33: 14.629262 | Z33: 28.4
C34: contig_536_33 | D34: 33 | E34: no_hit | F34: 0 | G34: no_hit | H34: no_hit | I34: 0 | Q34: 177 | R34: 1 | S34: 36556 | T34: 37086 | U34: =2003807+S34 -> 2040363 | V34: =2003808+T34 -> 2040894 | Y34: 8.1042005 | Z34: 29.6
C35: contig_536_34 | D35: 34 | E35: no_hit | F35: 0 | G35: no_hit | H35: no_hit | I35: 0 | Q35: 178 | R35: -1 | S35: 37338 | T35: 37871 | U35: =2003807+S35 -> 2041145 | V35: =2003808+T35 -> 2041679 | Y35: 5.9505576 | Z35: 22
C36: contig_536_35 | D36: 35 | E36: no_hit | F36: 0 | G36: no_hit | H36: no_hit | I36: 0 | Q36: 174 | R36: 1 | S36: 37874 | T36: 38395 | U36: =2003807+S36 -> 2041681 | V36: =2003808+T36 -> 2042203 | Y36: 11.680902 | Z36: 37.3
C37: contig_536_36 | D37: 36 | E37: no_hit | F37: 0 | G37: no_hit | H37: no_hit | I37: 0 | Q37: 44 | R37: -1 | S37: 38773 | T37: 38904 | U37: =2003807+S37 -> 2042580 | V37: =2003808+T37 -> 2042712 | Y37: 0.481057 | Z37: 0.5
C38: contig_536_37 | D38: 37 | E38: no_hit | F38: 0 | G38: no_hit | H38: no_hit | I38: 0 | Q38: 128 | R38: -1 | S38: 39177 | T38: 39560 | U38: =2003807+S38 -> 2042984 | V38: =2003808+T38 -> 2043368 | Y38: 12077.39 | Z38: 29703.4
C39: contig_536_38 | D39: 38 | E39: no_hit | F39: 0 | G39: no_hit | H39: no_hit | I39: 0 | Q39: 70 | R39: -1 | S39: 39560 | T39: 39769 | U39: =2003807+S39 -> 2043367 | V39: =2003808+T39 -> 2043577 | Y39: 33.516795 | Z39: 47.1
C40: contig_536_39 | D40: 39 | E40: no_hit | F40: 0 | G40: no_hit | H40: no_hit | I40: 0 | Q40: 136 | R40: -1 | S40: 39770 | T40: 40177 | U40: =2003807+S40 -> 2043577 | V40: =2003808+T40 -> 2043985 | Y40: 30.688597 | Z40: 73.9 | AA40: post_induc
C41: contig_536_40 | D41: 40 | E41: no_hit | F41: 0 | G41: no_hit | H41: no_hit | I41: 0 | Q41: 173 | R41: -1 | S41: 40170 | T41: 40688 | U41: =2003807+S41 -> 2043977 | V41: =2003808+T41 -> 2044496 | Y41: 19.874542 | Z41: 70.3
C42: contig_536_41 | D42: 41 | E42: no_hit | F42: 0 | G42: no_hit | H42: no_hit | I42: 0 | P42: early high expressed | Q42: 125 | R42: 1 | S42: 41087 | T42: 41461 | U42: =2003807+S42 -> 2044894 | V42: =2003808+T42 -> 2045269 | Y42: 56.215534 | Z42: 149.3 | AA42: pre_induc
C43: contig_536_42 | D43: 42 | E43: no_hit | F43: 0 | G43: no_hit | H43: no_hit | I43: 0 | Q43: 88 | R43: 1 | S43: 41443 | T43: 41706 | U43: =2003807+S43 -> 2045250 | V43: =2003808+T43 -> 2045514 | Y43: 10.524321 | Z43: 19.2
C44: contig_536_43 | D44: 43 | E44: no_hit | F44: 0 | G44: no_hit | H44: no_hit | I44: 0 | Q44: 197 | R44: 1 | S44: 42492 | T44: 43082 | U44: =2003807+S44 -> 2046299 | V44: =2003808+T44 -> 2046890 | Y44: 11.953634 | Z44: 46.5 | AA44: pre_induc
C45: contig_536_44 | D45: 44 | E45: no_hit | F45: 0 | G45: no_hit | H45: no_hit | I45: 0 | P45: Fanzor_B_nuclease | Q45: 1282 | R45: 1 | S45: 43225 | T45: 47070 | U45: =2003807+S45 -> 2047032 | V45: =2003808+T45 -> 2050878 | Y45: 0.60003314 | Z45: 17.5
C46: contig_536_45 | D46: 45 | E46: no_hit | F46: 0 | G46: no_hit | H46: no_hit | I46: 0 | Q46: 303 | R46: 1 | S46: 47061 | T46: 47969 | U46: =2003807+S46 -> 2050868 | V46: =2003808+T46 -> 2051777 | Y46: 40.050483 | Z46: 251.7
C47: contig_536_46 | D47: 46 | E47: no_hit | F47: 0 | G47: no_hit | H47: no_hit | I47: 0 | L47: Unknown | Q47: 208 | R47: 1 | S47: 47972 | T47: 48595 | U47: =2003807+S47 -> 2051779 | V47: =2003808+T47 -> 2052403 | Y47: 23.312436 | Z47: 98.3
C48: contig_536_47 | D48: 47 | E48: no_hit | F48: 0 | G48: no_hit | H48: no_hit | I48: 0 | Q48: 98 | R48: 1 | S48: 48902 | T48: 49195 | U48: =2003807+S48 -> 2052709 | V48: =2003808+T48 -> 2053003 | Y48: 3.9321872 | Z48: 7.3
C49: contig_536_48 | D49: 48 | E49: no_hit | F49: 0 | G49: no_hit | H49: no_hit | I49: 0 | Q49: 171 | R49: 1 | S49: 49288 | T49: 49800 | U49: =2003807+S49 -> 2053095 | V49: =2003808+T49 -> 2053608 | Y49: 4.8398756 | Z49: 16.5
C50: contig_536_49 | D50: 49 | E50: no_hit | F50: 0 | G50: no_hit | H50: no_hit | I50: 0 | Q50: 413 | R50: 1 | S50: 49775 | T50: 51013 | U50: =2003807+S50 -> 2053582 | V50: =2003808+T50 -> 2054821 | Y50: 8.0344008 | Z50: 67.5
C51: contig_536_50 | D51: 50 | E51: no_hit | F51: 0 | G51: no_hit | H51: no_hit | I51: 0 | Q51: 154 | R51: -1 | S51: 50915 | T51: 51376 | U51: =2003807+S51 -> 2054722 | V51: =2003808+T51 -> 2055184 | Y51: 5.0908656 | Z51: 15.2
C52: contig_536_51 | D52: 51 | E52: no_hit | F52: 0 | G52: no_hit | H52: no_hit | I52: 0 | Q52: 85 | R52: -1 | S52: 51570 | T52: 51824 | U52: =2003807+S52 -> 2055377 | V52: =2003808+T52 -> 2055632 | Y52: 13.792609 | Z52: 22.9
C53: contig_536_52 | D53: 52 | E53: no_hit | F53: 0 | G53: no_hit | H53: no_hit | I53: 0 | Q53: 64 | R53: -1 | S53: 52017 | T53: 52208 | U53: =2003807+S53 -> 2055824 | V53: =2003808+T53 -> 2056016 | Y53: 15.132038 | Z53: 19.9
C54: contig_536_53 | D54: 53 | E54: no_hit | F54: 0 | G54: no_hit | H54: no_hit | I54: 0 | Q54: 211 | R54: 1 | S54: 52544 | T54: 53176 | U54: =2003807+S54 -> 2056351 | V54: =2003808+T54 -> 2056984 | Y54: 5.2517058 | Z54: 20.9
C55: contig_536_54 | D55: 54 | E55: no_hit | F55: 0 | G55: no_hit | H55: no_hit | I55: 0 | Q55: 154 | R55: -1 | S55: 53078 | T55: 53539 | U55: =2003807+S55 -> 2056885 | V55: =2003808+T55 -> 2057347 | Y55: 4.780573 | Z55: 14.3
C56: contig_536_55 | D56: 55 | E56: no_hit | F56: 0 | G56: no_hit | H56: no_hit | I56: 0 | O56: Cre10.g439950_4532.5 | P56: (1 of 546) 2.7.11.1 - Non-specific serine/threonine protein kinase / Threonine-specific protein kinase | Q56: 218 | R56: 1 | S56: 54345 | T56: 54998 | U56: =2003807+S56 -> 2058152 | V56: =2003808+T56 -> 2058806 | Y56: 13.151889 | Z56: 59.2
C57: contig_536_56 | D57: 56 | E57: no_hit | F57: 0 | G57: no_hit | H57: no_hit | I57: 0 | Q57: 47 | R57: 1 | S57: 55078 | T57: 55218 | U57: =2003807+S57 -> 2058885 | V57: =2003808+T57 -> 2059026 | Y57: 31.112996 | Z57: 29.6
C58: contig_536_57 | D58: 57 | E58: no_hit | F58: 0 | G58: no_hit | H58: no_hit | I58: 0 | P58: early high expressed | Q58: 207 | R58: 1 | S58: 56672 | T58: 57292 | U58: =2003807+S58 -> 2060479 | V58: =2003808+T58 -> 2061100 | Y58: 21.010225 | Z58: 90.1 | AA58: pre_induc
C59: contig_536_58 | D59: 58 | E59: no_hit | F59: 0 | G59: no_hit | H59: no_hit | I59: 0 | P59: early high expressed | Q59: 752 | R59: 1 | S59: 58986 | T59: 61241 | U59: =2003807+S59 -> 2062793 | V59: =2003808+T59 -> 2065049 | Y59: 18.166627 | Z59: 279.5 | AA59: pre_induc
C60: contig_536_59 | D60: 59 | E60: GVOGm1062 | F60: 9.69536 | G60: NAD-dependent histone deacetylase activity (H3-K14 specific) | including yeast histone deacetylase and acetoin utilization protein | Histone deacetylase domain | including yeast histone deacetylase and acetoin utilization protein | tRNA guanylyltransferase activity | Histone deacetylase domain | protein deacetylase activity | NAD-dependent histone deacetylase activity (H3-K14 specific) | H60: Hist_deacetyl | I60: 13.93198 | J60: COG0123@1 | K60: B | M60: Belongs to the histone deacetylase family. HD Type 1 subfamily | Q60: 430 | R60: 1 | S60: 61358 | T60: 62647 | U60: =2003807+S60 -> 2065165 | V60: =2003808+T60 -> 2066455 | Y60: 16.447166 | Z60: 146.9
C61: contig_536_60 | D61: 60 | E61: no_hit | F61: 0 | G61: no_hit | H61: no_hit | I61: 0 | Q61: 238 | R61: 1 | S61: 62721 | T61: 63434 | U61: =2003807+S61 -> 2066528 | V61: =2003808+T61 -> 2067242 | Y61: 22.859841 | Z61: 110
C62: contig_536_61 | D62: 61 | E62: no_hit | F62: 0 | G62: no_hit | H62: no_hit | I62: 0 | Q62: 585 | R62: 1 | S62: 63775 | T62: 65529 | U62: =2003807+S62 -> 2067582 | V62: =2003808+T62 -> 2069337 | Y62: 13.880263 | Z62: 161.9 | AA62: post_induc
C63: contig_536_62 | D63: 62 | E63: no_hit | F63: 0 | G63: no_hit | H63: no_hit | I63: 0 | Q63: 82 | R63: 1 | S63: 66072 | T63: 66317 | U63: =2003807+S63 -> 2069879 | V63: =2003808+T63 -> 2070125 | Y63: 5.2164494 | Z63: 8
C64: contig_536_63 | D64: 63 | E64: no_hit | F64: 0 | G64: no_hit | H64: no_hit | I64: 0 | Q64: 82 | R64: 1 | S64: 66721 | T64: 66966 | U64: =2003807+S64 -> 2070528 | V64: =2003808+T64 -> 2070774 | Y64: 52.237803 | Z64: 87.9
C65: contig_536_64 | D65: 64 | E65: no_hit | F65: 0 | G65: no_hit | H65: no_hit | I65: 0 | Q65: 195 | R65: 1 | S65: 67027 | T65: 67611 | U65: =2003807+S65 -> 2070834 | V65: =2003808+T65 -> 2071419 | Y65: 26.782851 | Z65: 105.3
C66: contig_536_65 | D66: 65 | E66: no_hit | F66: 0 | G66: no_hit | H66: no_hit | I66: 0 | Q66: 371 | R66: 1 | S66: 67726 | T66: 68838 | U66: =2003807+S66 -> 2071533 | V66: =2003808+T66 -> 2072646 | Y66: 45.390132 | Z66: 337.7
C67: contig_536_66 | D67: 66 | E67: no_hit | F67: 0 | G67: no_hit | H67: no_hit | I67: 0 | Q67: 51 | R67: 1 | S67: 68903 | T67: 69055 | U67: =2003807+S67 -> 2072710 | V67: =2003808+T67 -> 2072863 | Y67: 36.066559 | Z67: 37
C68: contig_536_67 | D68: 67 | E68: no_hit | F68: 0 | G68: no_hit | H68: no_hit | I68: 0 | Q68: 126 | R68: -1 | S68: 69027 | T68: 69404 | U68: =2003807+S68 -> 2072834 | V68: =2003808+T68 -> 2073212 | Y68: 11.559445 | Z68: 29.6
C69: contig_536_68 | D69: 68 | E69: no_hit | F69: 0 | G69: no_hit | H69: no_hit | I69: 0 | Q69: 48 | R69: 1 | S69: 69703 | T69: 69846 | U69: =2003807+S69 -> 2073510 | V69: =2003808+T69 -> 2073654 | Y69: 16.004236 | Z69: 15.7
C70: contig_536_69 | D70: 69 | E70: no_hit | F70: 0 | G70: no_hit | H70: no_hit | I70: 0 | Q70: 182 | R70: 1 | S70: 69978 | T70: 70523 | U70: =2003807+S70 -> 2073785 | V70: =2003808+T70 -> 2074331 | Y70: 17.338983 | Z70: 63.4
C71: contig_536_70 | D71: 70 | E71: no_hit | F71: 0 | G71: no_hit | H71: no_hit | I71: 0 | P71: early high expressed | Q71: 51 | R71: 1 | S71: 71140 | T71: 71292 | U71: =2003807+S71 -> 2074947 | V71: =2003808+T71 -> 2075100 | Y71: 129.15002 | Z71: 136.2 | AA71: pre_induc
C72: contig_536_71 | D72: 71 | E72: no_hit | F72: 0 | G72: no_hit | H72: DNA_ligase_C | I72: 5.291503 | P72: early high expressed | Q72: 798 | R72: 1 | S72: 72722 | T72: 75115 | U72: =2003807+S72 -> 2076529 | V72: =2003808+T72 -> 2078923 | Y72: 23.383062 | Z72: 378 | AA72: pre_induc
C73: contig_536_72 | D73: 72 | E73: no_hit | F73: 0 | G73: no_hit | H73: no_hit | I73: 0 | Q73: 72 | R73: -1 | S73: 75776 | T73: 75991 | U73: =2003807+S73 -> 2079583 | V73: =2003808+T73 -> 2079799 | Y73: 425.20939 | Z73: 593.9 | AA73: post_induc
C74: contig_536_73 | D74: 73 | E74: no_hit | F74: 0 | G74: no_hit | H74: no_hit | I74: 0 | Q74: 72 | R74: -1 | S74: 76589 | T74: 76804 | U74: =2003807+S74 -> 2080396 | V74: =2003808+T74 -> 2080612 | Y74: 322.42526 | Z74: 455.8 | AA74: post_induc
C75: contig_536_74 | D75: 74 | E75: no_hit | F75: 0 | G75: no_hit | H75: rve | I75: 18.33366 | J75: COG2801@1 | K75: L | L75: Mobile elements | M75: DNA RNA polymerases superfamily protein | N75: Gag-Pol polyprotein | O75: Cre15.g801742_4532.1 | P75: early high expressed | Q75: 1564 | R75: -1 | S75: 78948 | T75: 83639 | U75: =2003807+S75 -> 2082755 | V75: =2003808+T75 -> 2087447 | Y75: 43.614256 | Z75: 1433.1 | AA75: pre_induc | AB75: Yes
C76: contig_536_75 | D76: 75 | E76: no_hit | F76: 0 | G76: no_hit | H76: no_hit | I76: 0 | N76: retrotransposon mcp? | O76: Cre15.g801743_4532.1 | P76: early high expressed | Q76: 486 | R76: -1 | S76: 83688 | T76: 85145 | U76: =2003807+S76 -> 2087495 | V76: =2003808+T76 -> 2088953 | Y76: 147.60224 | Z76: 1440 | AA76: pre_induc
C77: contig_536_76 | D77: 76 | E77: GVOGm0180 | F77: 14.27585 | G77: function. Source PGD | unknown | unknown | unknown | unknown | H77: no_hit | I77: 0 | J77: 2EG1T@1 | K77: S | L77: Mobile elements | M77: function. Source PGD | O77: Cre17.g712700_4532.1 | P77: putative transposase; Fanzor_C_nuclease | Q77: 660 | R77: -1 | S77: 86338 | T77: 88317 | U77: =2003807+S77 -> 2090145 | V77: =2003808+T77 -> 2092125 | Y77: 0.57396699 | Z77: 8.3 | AA77: post_induc | AB77: Yes
C78: contig_536_77 | D78: 77 | E78: no_hit | F78: 0 | G78: no_hit | H78: no_hit | I78: 0 | Q78: 98 | R78: 1 | S78: 88354 | T78: 88647 | U78: =2003807+S78 -> 2092161 | V78: =2003808+T78 -> 2092455 | Y78: 2.1192064 | Z78: 4.6
C79: contig_536_78 | D79: 78 | E79: GVOGm1077 | F79: 11.07249 | G79: Homeodomain-like domain | DDE superfamily endonuclease | DDE superfamily endonuclease | DDE superfamily endonuclease | DDE superfamily endonuclease | DDE superfamily endonuclease | DDE superfamily endonuclease | DDE superfamily endonuclease | DDE superfamily endonuclease | Source PGD | DDE superfamily endonuclease | unknown | unknown | DDE superfamily endonuclease | Transposase and inactivated derivatives | unknown | DDE superfamily endonuclease | H79: DDE_3 | I79: 8.133906 | J79: COG3335@1 | K79: L | M79: DDE superfamily endonuclease | P79: Fanzor_C_transposase | Q79: 331 | R79: -1 | S79: 88530 | T79: 89522 | U79: =2003807+S79 -> 2092337 | V79: =2003808+T79 -> 2093330 | Y79: 2.1720733 | Z79: 14.9
C80: contig_536_79 | D80: 79 | E80: no_hit | F80: 0 | G80: no_hit | H80: no_hit | I80: 0 | Q80: 112 | R80: -1 | S80: 90972 | T80: 91307 | U80: =2003807+S80 -> 2094779 | V80: =2003808+T80 -> 2095115 | Y80: 20.473609 | Z80: 44.3
C81: contig_536_80 | D81: 80 | E81: no_hit | F81: 0 | G81: no_hit | H81: no_hit | I81: 0 | Q81: 76 | R81: -1 | S81: 91274 | T81: 91501 | U81: =2003807+S81 -> 2095081 | V81: =2003808+T81 -> 2095309 | Y81: 20.575151 | Z81: 30.2
C82: contig_536_81 | D82: 81 | E82: no_hit | F82: 0 | G82: no_hit | H82: no_hit | I82: 0 | Q82: 93 | R82: 1 | S82: 91760 | T82: 92038 | U82: =2003807+S82 -> 2095567 | V82: =2003808+T82 -> 2095846 | Y82: 37.284621 | Z82: 69.2
C83: contig_536_82 | D83: 82 | E83: no_hit | F83: 0 | G83: no_hit | H83: no_hit | I83: 0 | Q83: 45 | R83: -1 | S83: 92149 | T83: 92283 | U83: =2003807+S83 -> 2095956 | V83: =2003808+T83 -> 2096091 | Y83: 6.8018922 | Z83: 5.4
C84: contig_536_83 | D84: 83 | E84: no_hit | F84: 0 | G84: no_hit | H84: no_hit | I84: 0 | Q84: 54 | R84: 1 | S84: 92496 | T84: 92657 | U84: =2003807+S84 -> 2096303 | V84: =2003808+T84 -> 2096465 | Y84: 15.631655 | Z84: 15.6
C85: contig_536_84 | D85: 84 | E85: no_hit | F85: 0 | G85: no_hit | H85: no_hit | I85: 0 | Q85: 149 | R85: 1 | S85: 93127 | T85: 93573 | U85: =2003807+S85 -> 2096934 | V85: =2003808+T85 -> 2097381 | Y85: 22.289733 | Z85: 67.7
C86: contig_536_85 | D86: 85 | E86: no_hit | F86: 0 | G86: no_hit | H86: no_hit | I86: 0 | Q86: 48 | R86: -1 | S86: 93960 | T86: 94103 | U86: =2003807+S86 -> 2097767 | V86: =2003808+T86 -> 2097911 | Y86: 0.5301825 | Z86: 0.3
C87: contig_536_86 | D87: 86 | E87: no_hit | F87: 0 | G87: no_hit | H87: HTH_33 | I87: 5.059644 | Q87: 150 | R87: -1 | S87: 94079 | T87: 94528 | U87: =2003807+S87 -> 2097886 | V87: =2003808+T87 -> 2098336 | Y87: 7.2384103 | Z87: 21.9
C88: contig_536_87 | D88: 87 | E88: no_hit | F88: 0 | G88: no_hit | H88: no_hit | I88: 0 | Q88: 33 | R88: -1 | S88: 95519 | T88: 95617 | U88: =2003807+S88 -> 2099326 | V88: =2003808+T88 -> 2099425 | Y88: 3.1386665 | Z88: 1.9
C89: contig_536_88 | D89: 88 | E89: no_hit | F89: 0 | G89: no_hit | H89: no_hit | I89: 0 | Q89: 75 | R89: -1 | S89: 95602 | T89: 95826 | U89: =2003807+S89 -> 2099409 | V89: =2003808+T89 -> 2099634 | Y89: 75.78634 | Z89: 113.9
C90: contig_536_89 | D90: 89 | E90: no_hit | F90: 0 | G90: no_hit | H90: no_hit | I90: 0 | Q90: 81 | R90: 1 | S90: 96458 | T90: 96700 | U90: =2003807+S90 -> 2100265 | V90: =2003808+T90 -> 2100508 | Y90: 29.86153 | Z90: 52.1
C91: contig_536_90 | D91: 90 | E91: no_hit | F91: 0 | G91: no_hit | H91: no_hit | I91: 0 | Q91: 209 | R91: 1 | S91: 97277 | T91: 97903 | U91: =2003807+S91 -> 2101084 | V91: =2003808+T91 -> 2101711 | Y91: 45.932041 | Z91: 200.8
C92: contig_536_91 | D92: 91 | E92: no_hit | F92: 0 | G92: no_hit | H92: no_hit | I92: 0 | Q92: 47 | R92: 1 | S92: 98251 | T92: 98391 | U92: =2003807+S92 -> 2102058 | V92: =2003808+T92 -> 2102199 | Y92: 13.051992 | Z92: 12.1
C93: contig_536_92 | D93: 92 | E93: GVOGm1077 | F93: 12.21065 | G93: Homeodomain-like domain | DDE superfamily endonuclease | DDE superfamily endonuclease | DDE superfamily endonuclease | DDE superfamily endonuclease | DDE superfamily endonuclease | DDE superfamily endonuclease | DDE superfamily endonuclease | DDE superfamily endonuclease | Source PGD | DDE superfamily endonuclease | unknown | unknown | DDE superfamily endonuclease | Transposase and inactivated derivatives | unknown | DDE superfamily endonuclease | H93: DDE_3 | I93: 8.319899 | J93: COG3335@1 | K93: L | M93: Evidence 3 Function proposed based on presence of conserved amino acid motif, structural feature or limited homology | P93: Fanzor_A_transposase | Q93: 317 | R93: 1 | S93: 98581 | T93: 99531 | U93: =2003807+S93 -> 2102388 | V93: =2003808+T93 -> 2103339 | Y93: 6.0280198 | Z93: 39.4
C94: contig_536_93 | D94: 93 | E94: GVOGm0180 | F94: 7.402702 | G94: function. Source PGD | unknown | unknown | unknown | unknown | H94: no_hit | I94: 0 | P94: Fanzor_A_nuclease | Q94: 1205 | R94: 1 | S94: 99694 | T94: 103308 | U94: =2003807+S94 -> 2103501 | V94: =2003808+T94 -> 2107116 | Y94: 1.1177134 | Z94: 29.6 | AA94: post_induc
C95: contig_536_94 | D95: 94 | E95: no_hit | F95: 0 | G95: no_hit | H95: no_hit | I95: 0 | Q95: 86 | R95: -1 | S95: 103476 | T95: 103733 | U95: =2003807+S95 -> 2107283 | V95: =2003808+T95 -> 2107541 | Y95: 42.241255 | Z95: 73.4
C96: contig_536_95 | D96: 95 | E96: no_hit | F96: 0 | G96: no_hit | H96: no_hit | I96: 0 | Q96: 96 | R96: 1 | S96: 103933 | T96: 104220 | U96: =2003807+S96 -> 2107740 | V96: =2003808+T96 -> 2108028 | Y96: 10.635325 | Z96: 19.2
C97: contig_536_96 | D97: 96 | E97: no_hit | F97: 0 | G97: no_hit | H97: no_hit | I97: 0 | Q97: 125 | R97: -1 | S97: 104178 | T97: 104552 | U97: =2003807+S97 -> 2107985 | V97: =2003808+T97 -> 2108360 | Y97: 42.274923 | Z97: 105
C98: contig_536_97 | D98: 97 | E98: no_hit | F98: 0 | G98: no_hit | H98: no_hit | I98: 0 | Q98: 43 | R98: -1 | S98: 104549 | T98: 104677 | U98: =2003807+S98 -> 2108356 | V98: =2003808+T98 -> 2108485 | Y98: 0.6471022 | Z98: 0.7
C99: contig_536_98 | D99: 98 | E99: GVOGm0339 | F99: 12.92285 | G99: unknown | unknown | unknown | unknown | H99: no_hit | I99: 0 | Q99: 313 | R99: -1 | S99: 104703 | T99: 105641 | U99: =2003807+S99 -> 2108510 | V99: =2003808+T99 -> 2109449 | Y99: 1.0660562 | Z99: 7.2
C100: contig_536_99 | D100: 99 | E100: no_hit | F100: 0 | G100: no_hit | H100: no_hit | I100: 0 | Q100: 352 | R100: -1 | S100: 105683 | T100: 106738 | U100: =2003807+S100 -> 2109490 | V100: =2003808+T100 -> 2110546 | Y100: 2.786245 | Z100: 21.8 | AA100: post_induc
...

Sheet no anno
B1: number | C1: GVOG | D1: virbit | E1: vdesc | F1: pfam | G1: pfambit | H1: eggNOG_OGs | I1: COG_category | J1: Functional category | K1: eggNOG_Desc | L1: HHPred | M1: hits_to_chlamy | N1: annotation_notes | O1: protlength | P1: strand | Q1: start | R1: end | S1: contig_start | T1: contig_end | U1: Proteome1_score | V1: Proteom2_score | W1: MeanRPKM_cf20 | X1: MeanCounts_cf20 | Y1: ExprCluster | Z1: Proteomics
A2: contig_536_1 | B2: 1 | C2: no_hit | D2: 0 | E2: no_hit | F2: no_hit | G2: 0 | O2: 75 | P2: -1 | Q2: 35 | R2: 259 | S2: =2003807+Q2 -> 2003842 | T2: =2003808+R2 -> 2004067 | W2: 0.10215924 | X2: 0.2
A3: contig_536_2 | B3: 2 | C3: no_hit | D3: 0 | E3: no_hit | F3: no_hit | G3: 0 | M3: Cre11.g801258_4532.1 | O3: 338 | P3: -1 | Q3: 579 | R3: 1592 | S3: =2003807+Q3 -> 2004386 | T3: =2003808+R3 -> 2005400 | W3: 1.4216146 | X3: 11.8
A4: contig_536_3 | B4: 3 | C4: no_hit | D4: 0 | E4: no_hit | F4: no_hit | G4: 0 | O4: 144 | P4: 1 | Q4: 3098 | R4: 3529 | S4: =2003807+Q4 -> 2006905 | T4: =2003808+R4 -> 2007337 | W4: 0.07121621 | X4: 0.2
A5: contig_536_4 | B5: 4 | C5: no_hit | D5: 0 | E5: no_hit | F5: no_hit | G5: 0 | M5: Cre01.g800142_4532.1 | O5: 204 | P5: -1 | Q5: 3786 | R5: 4397 | S5: =2003807+Q5 -> 2007593 | T5: =2003808+R5 -> 2008205 | W5: 239.83192 | X5: 957.7
A6: contig_536_5 | B6: 5 | C6: no_hit | D6: 0 | E6: no_hit | F6: no_hit | G6: 0 | O6: 212 | P6: 1 | Q6: 5604 | R6: 6239 | S6: =2003807+Q6 -> 2009411 | T6: =2003808+R6 -> 2010047 | W6: 0.2941414 | X6: 1.3
A7: contig_536_6 | B7: 6 | C7: no_hit | D7: 0 | E7: no_hit | F7: no_hit | G7: 0 | O7: 111 | P7: 1 | Q7: 6343 | R7: 6675 | S7: =2003807+Q7 -> 2010150 | T7: =2003808+R7 -> 2010483 | W7: 1.0941073 | X7: 2.4
A8: contig_536_7 | B8: 7 | C8: no_hit | D8: 0 | E8: no_hit | F8: no_hit | G8: 0 | M8: Cre01.g800142_4532.1 | O8: 135 | P8: 1 | Q8: 6984 | R8: 7388 | S8: =2003807+Q8 -> 2010791 | T8: =2003808+R8 -> 2011196 | W8: 706.63425 | X8: 1864.6
A9: contig_536_8 | B9: 8 | C9: no_hit | D9: 0 | E9: no_hit | F9: no_hit | G9: 0 | O9: 124 | P9: -1 | Q9: 7700 | R9: 8071 | S9: =2003807+Q9 -> 2011507 | T9: =2003808+R9 -> 2011879 | W9: 35.998925 | X9: 78.4
A10: contig_536_9 | B10: 9 | C10: no_hit | D10: 0 | E10: no_hit | F10: no_hit | G10: 0 | O10: 68 | P10: 1 | Q10: 8102 | R10: 8305 | S10: =2003807+Q10 -> 2011909 | T10: =2003808+R10 -> 2012113 | W10: 0.38770977 | X10: 0.5
A11: contig_536_10 | B11: 10 | C11: no_hit | D11: 0 | E11: no_hit | F11: no_hit | G11: 0 | O11: 140 | P11: 1 | Q11: 8430 | R11: 8849 | S11: =2003807+Q11 -> 2012237 | T11: =2003808+R11 -> 2012657 | W11: 1.8584556 | X11: 4.8
A12: contig_536_11 | B12: 11 | C12: no_hit | D12: 0 | E12: no_hit | F12: no_hit | G12: 0 | O12: 87 | P12: 1 | Q12: 8809 | R12: 9069 | S12: =2003807+Q12 -> 2012616 | T12: =2003808+R12 -> 2012877 | W12: 2.8228675 | X12: 5.2 | Y12: pre_induc
A13: contig_536_12 | B13: 12 | C13: no_hit | D13: 0 | E13: no_hit | F13: no_hit | G13: 0 | O13: 96 | P13: -1 | Q13: 10637 | R13: 10924 | S13: =2003807+Q13 -> 2014444 | T13: =2003808+R13 -> 2014732 | W13: 210.96673 | X13: 404.6 | Z13: Yes
A14: contig_536_13 | B14: 13 | C14: no_hit | D14: 0 | E14: no_hit | F14: no_hit | G14: 0 | O14: 122 | P14: 1 | Q14: 11216 | R14: 11581 | S14: =2003807+Q14 -> 2015023 | T14: =2003808+R14 -> 2015389 | W14: 38.392109 | X14: 94.1
A15: contig_536_14 | B15: 14 | C15: no_hit | D15: 0 | E15: no_hit | F15: no_hit | G15: 0 | O15: 39 | P15: 1 | Q15: 11836 | R15: 11952 | S15: =2003807+Q15 -> 2015643 | T15: =2003808+R15 -> 2015760 | W15: 3.5570678 | X15: 2.5
A16: contig_536_15 | B16: 15 | C16: no_hit | D16: 0 | E16: no_hit | F16: no_hit | G16: 0 | M16: Cre15.g635717_4532.1 | O16: 99 | P16: -1 | Q16: 12352 | R16: 12648 | S16: =2003807+Q16 -> 2016159 | T16: =2003808+R16 -> 2016456 | W16: 53.53054 | X16: 100.7
A17: contig_536_16 | B17: 16 | C17: no_hit | D17: 0 | E17: no_hit | F17: no_hit | G17: 0 | H17: 2E0K7@1 | I17: - | K17: - | O17: 168 | P17: -1 | Q17: 14143 | R17: 14646 | S17: =2003807+Q17 -> 2017950 | T17: =2003808+R17 -> 2018454 | W17: 203.10499 | X17: 655.2 | Y17: post_induc
A18: contig_536_17 | B18: 17 | C18: no_hit | D18: 0 | E18: no_hit | F18: no_hit | G18: 0 | M18: Cre07.g800828_4532.1 | O18: 182 | P18: -1 | Q18: 14848 | R18: 15393 | S18: =2003807+Q18 -> 2018655 | T18: =2003808+R18 -> 2019201 | W18: 642.21406 | X18: 2112.5 | Y18: post_induc
A19: contig_536_18 | B19: 18 | C19: no_hit | D19: 0 | E19: no_hit | F19: no_hit | G19: 0 | O19: 126 | P19: -1 | Q19: 16657 | R19: 17034 | S19: =2003807+Q19 -> 2020464 | T19: =2003808+R19 -> 2020842 | W19: 1076.7721 | X19: 2657 | Y19: post_induc
A20: contig_536_19 | B20: 19 | C20: no_hit | D20: 0 | E20: no_hit | F20: no_hit | G20: 0 | O20: 36 | P20: 1 | Q20: 17214 | R20: 17321 | S20: =2003807+Q20 -> 2021021 | T20: =2003808+R20 -> 2021129 | W20: 149.03284 | X20: 109.7
A21: contig_536_20 | B21: 20 | C21: no_hit | D21: 0 | E21: no_hit | F21: no_hit | G21: 0 | N21: early high expressed | O21: 288 | P21: -1 | Q21: 17549 | R21: 18412 | S21: =2003807+Q21 -> 2021356 | T21: =2003808+R21 -> 2022220 | W21: 52.410252 | X21: 304.4 | Y21: pre_induc
A22: contig_536_21 | B22: 21 | C22: GVOGm1522 | D22: 10.15382 | E22: A helicase nuclease that prepares dsDNA breaks (DSB) for recombinational DNA repair. Binds to DSBs and unwinds DNA via a highly rapid and processive ATP-dependent bidirectional helicase activity. Unwinds dsDNA until it encounters a Chi (crossover hotspot instigator) sequence from the 3' direction. Cuts ssDNA a few nucleotides 3' to the Chi site. The properties and activities of the enzyme are changed at Chi. The Chi-altered holoenzyme produces a long 3'-ssDNA overhang and facilitates RecA-binding to the ssDNA for homologous DNA recombination and repair. Holoenzyme degrades any linearized DNA that is unable to undergo homologous recombination. In the holoenzyme this subunit has ssDNA-dependent ATPase and 5'-3' helicase activity. When added to pre-assembled RecBC greatly stimulates nuclease activity and augments holoenzyme processivity. Negatively regulates the RecA-loading ability of RecBCD | Helix-turn-helix domain | G-quadruplex DNA unwinding | unknown | Helix-hairpin-helix containing domain | unknown | four-way junction helicase activity | unknown | unknown | unknown | PIF1-like helicase | Superfamily I DNA and RNA helicases and helicase subunits | DNA helicase | A helicase nuclease that prepares dsDNA breaks (DSB) for recombinational DNA repair. Binds to DSBs and unwinds DNA via a highly rapid and processive ATP-dependent bidirectional helicase activity. Unwinds dsDNA until it encounters a Chi (crossover hotspot instigator) sequence from the 3' direction. Cuts ssDNA a few nucleotides 3' to the Chi site. The properties and activities of the enzyme are changed at Chi. The Chi-altered holoenzyme produces a long 3'-ssDNA overhang and facilitates RecA-binding to the ssDNA for homologous DNA recombination and repair. Holoenzyme degrades any linearized DNA that is unable to undergo homologous recombination. In the holoenzyme this subunit has ssDNA-dependent ATPase and 5'-3' helicase activity. When added to pre-assembled RecBC greatly stimulates nuclease activity and augments holoenzyme processivity. Negatively regulates the RecA-loading ability of RecBCD | F22: AAA_30 | G22: 13.70782 | N22: early high expressed | O22: 300 | P22: -1 | Q22: 18682 | R22: 19581 | S22: =2003807+Q22 -> 2022489 | T22: =2003808+R22 -> 2023389 | W22: 97.312297 | X22: 611.6 | Y22: pre_induc
A23: contig_536_22 | B23: 22 | C23: no_hit | D23: 0 | E23: no_hit | F23: no_hit | G23: 0 | N23: TIR 1 start; early high expressed | O23: 1303 | P23: -1 | Q23: 20490 | R23: 24398 | S23: =2003807+Q23 -> 2024297 | T23: =2003808+R23 -> 2028206 | W23: 50.09561 | X23: 1345.3 | Y23: pre_induc
A24: contig_536_23 | B24: 23 | C24: no_hit | D24: 0 | E24: no_hit | F24: no_hit | G24: 0 | N24: early high expressed | O24: 213 | P24: -1 | Q24: 24401 | R24: 25039 | S24: =2003807+Q24 -> 2028208 | T24: =2003808+R24 -> 2028847 | W24: 716.52141 | X24: 3162 | Y24: pre_induc
A25: contig_536_24 | B25: 24 | C25: no_hit | D25: 0 | E25: no_hit | F25: no_hit | G25: 0 | O25: 62 | P25: 1 | Q25: 29503 | R25: 29688 | S25: =2003807+Q25 -> 2033310 | T25: =2003808+R25 -> 2033496 | W25: 0.8973179 | X25: 1.3
A26: contig_536_25 | B26: 25 | C26: no_hit | D26: 0 | E26: no_hit | F26: no_hit | G26: 0 | O26: 159 | P26: -1 | Q26: 29653 | R26: 30129 | S26: =2003807+Q26 -> 2033460 | T26: =2003808+R26 -> 2033937 | W26: 24.079208 | X26: 75.2
A27: contig_536_26 | B27: 26 | C27: no_hit | D27: 0 | E27: no_hit | F27: no_hit | G27: 0 | O27: 47 | P27: 1 | Q27: 30829 | R27: 30969 | S27: =2003807+Q27 -> 2034636 | T27: =2003808+R27 -> 2034777 | W27: 25.077644 | X27: 24.7
A28: contig_536_27 | B28: 27 | C28: no_hit | D28: 0 | E28: no_hit | F28: no_hit | G28: 0 | O28: 251 | P28: 1 | Q28: 31467 | R28: 32219 | S28: =2003807+Q28 -> 2035274 | T28: =2003808+R28 -> 2036027 | W28: 18.947865 | X28: 96.5
A29: contig_536_28 | B29: 28 | C29: no_hit | D29: 0 | E29: no_hit | F29: no_hit | G29: 0 | O29: 57 | P29: -1 | Q29: 32569 | R29: 32739 | S29: =2003807+Q29 -> 2036376 | T29: =2003808+R29 -> 2036547 | W29: 10.730382 | X29: 12.6
A30: contig_536_29 | B30: 29 | C30: no_hit | D30: 0 | E30: no_hit | F30: no_hit | G30: 0 | N30: TIR 1 end | O30: 95 | P30: -1 | Q30: 33143 | R30: 33427 | S30: =2003807+Q30 -> 2036950 | T30: =2003808+R30 -> 2037235 | W30: 6.6609876 | X30: 12.7
A31: contig_536_30 | B31: 30 | C31: no_hit | D31: 0 | E31: no_hit | F31: no_hit | G31: 0 | O31: 116 | P31: 1 | Q31: 33978 | R31: 34325 | S31: =2003807+Q31 -> 2037785 | T31: =2003808+R31 -> 2038133 | W31: 44.252759 | X31: 103.1
A32: contig_536_31 | B32: 31 | C32: no_hit | D32: 0 | E32: no_hit | F32: no_hit | G32: 0 | O32: 45 | P32: -1 | Q32: 34662 | R32: 34796 | S32: =2003807+Q32 -> 2038469 | T32: =2003808+R32 -> 2038604 | W32: 95.093289 | X32: 89.4
A33: contig_536_32 | B33: 32 | C33: no_hit | D33: 0 | E33: no_hit | F33: no_hit | G33: 0 | O33: 97 | P33: -1 | Q33: 34854 | R33: 35144 | S33: =2003807+Q33 -> 2038661 | T33: =2003808+R33 -> 2038952 | W33: 14.629262 | X33: 28.4
A34: contig_536_33 | B34: 33 | C34: no_hit | D34: 0 | E34: no_hit | F34: no_hit | G34: 0 | O34: 177 | P34: 1 | Q34: 36556 | R34: 37086 | S34: =2003807+Q34 -> 2040363 | T34: =2003808+R34 -> 2040894 | W34: 8.1042005 | X34: 29.6
A35: contig_536_34 | B35: 34 | C35: no_hit | D35: 0 | E35: no_hit | F35: no_hit | G35: 0 | O35: 178 | P35: -1 | Q35: 37338 | R35: 37871 | S35: =2003807+Q35 -> 2041145 | T35: =2003808+R35 -> 2041679 | W35: 5.9505576 | X35: 22
A36: contig_536_35 | B36: 35 | C36: no_hit | D36: 0 | E36: no_hit | F36: no_hit | G36: 0 | O36: 174 | P36: 1 | Q36: 37874 | R36: 38395 | S36: =2003807+Q36 -> 2041681 | T36: =2003808+R36 -> 2042203 | W36: 11.680902 | X36: 37.3
A37: contig_536_36 | B37: 36 | C37: no_hit | D37: 0 | E37: no_hit | F37: no_hit | G37: 0 | O37: 44 | P37: -1 | Q37: 38773 | R37: 38904 | S37: =2003807+Q37 -> 2042580 | T37: =2003808+R37 -> 2042712 | W37: 0.481057 | X37: 0.5
A38: contig_536_37 | B38: 37 | C38: no_hit | D38: 0 | E38: no_hit | F38: no_hit | G38: 0 | O38: 128 | P38: -1 | Q38: 39177 | R38: 39560 | S38: =2003807+Q38 -> 2042984 | T38: =2003808+R38 -> 2043368 | W38: 12077.39 | X38: 29703.4
A39: contig_536_38 | B39: 38 | C39: no_hit | D39: 0 | E39: no_hit | F39: no_hit | G39: 0 | O39: 70 | P39: -1 | Q39: 39560 | R39: 39769 | S39: =2003807+Q39 -> 2043367 | T39: =2003808+R39 -> 2043577 | W39: 33.516795 | X39: 47.1
A40: contig_536_39 | B40: 39 | C40: no_hit | D40: 0 | E40: no_hit | F40: no_hit | G40: 0 | O40: 136 | P40: -1 | Q40: 39770 | R40: 40177 | S40: =2003807+Q40 -> 2043577 | T40: =2003808+R40 -> 2043985 | W40: 30.688597 | X40: 73.9 | Y40: post_induc
A41: contig_536_40 | B41: 40 | C41: no_hit | D41: 0 | E41: no_hit | F41: no_hit | G41: 0 | O41: 173 | P41: -1 | Q41: 40170 | R41: 40688 | S41: =2003807+Q41 -> 2043977 | T41: =2003808+R41 -> 2044496 | W41: 19.874542 | X41: 70.3
A42: contig_536_41 | B42: 41 | C42: no_hit | D42: 0 | E42: no_hit | F42: no_hit | G42: 0 | N42: early high expressed | O42: 125 | P42: 1 | Q42: 41087 | R42: 41461 | S42: =2003807+Q42 -> 2044894 | T42: =2003808+R42 -> 2045269 | W42: 56.215534 | X42: 149.3 | Y42: pre_induc
A43: contig_536_42 | B43: 42 | C43: no_hit | D43: 0 | E43: no_hit | F43: no_hit | G43: 0 | O43: 88 | P43: 1 | Q43: 41443 | R43: 41706 | S43: =2003807+Q43 -> 2045250 | T43: =2003808+R43 -> 2045514 | W43: 10.524321 | X43: 19.2
A44: contig_536_43 | B44: 43 | C44: no_hit | D44: 0 | E44: no_hit | F44: no_hit | G44: 0 | O44: 197 | P44: 1 | Q44: 42492 | R44: 43082 | S44: =2003807+Q44 -> 2046299 | T44: =2003808+R44 -> 2046890 | W44: 11.953634 | X44: 46.5 | Y44: pre_induc
A45: contig_536_44 | B45: 44 | C45: no_hit | D45: 0 | E45: no_hit | F45: no_hit | G45: 0 | N45: Fanzor_B_nuclease | O45: 1282 | P45: 1 | Q45: 43225 | R45: 47070 | S45: =2003807+Q45 -> 2047032 | T45: =2003808+R45 -> 2050878 | W45: 0.60003314 | X45: 17.5
A46: contig_536_45 | B46: 45 | C46: no_hit | D46: 0 | E46: no_hit | F46: no_hit | G46: 0 | O46: 303 | P46: 1 | Q46: 47061 | R46: 47969 | S46: =2003807+Q46 -> 2050868 | T46: =2003808+R46 -> 2051777 | W46: 40.050483 | X46: 251.7
A47: contig_536_46 | B47: 46 | C47: no_hit | D47: 0 | E47: no_hit | F47: no_hit | G47: 0 | J47: Unknown | O47: 208 | P47: 1 | Q47: 47972 | R47: 48595 | S47: =2003807+Q47 -> 2051779 | T47: =2003808+R47 -> 2052403 | W47: 23.312436 | X47: 98.3 | Z47: Yes
A48: contig_536_47 | B48: 47 | C48: no_hit | D48: 0 | E48: no_hit | F48: no_hit | G48: 0 | O48: 98 | P48: 1 | Q48: 48902 | R48: 49195 | S48: =2003807+Q48 -> 2052709 | T48: =2003808+R48 -> 2053003 | W48: 3.9321872 | X48: 7.3
A49: contig_536_48 | B49: 48 | C49: no_hit | D49: 0 | E49: no_hit | F49: no_hit | G49: 0 | O49: 171 | P49: 1 | Q49: 49288 | R49: 49800 | S49: =2003807+Q49 -> 2053095 | T49: =2003808+R49 -> 2053608 | W49: 4.8398756 | X49: 16.5
A50: contig_536_49 | B50: 49 | C50: no_hit | D50: 0 | E50: no_hit | F50: no_hit | G50: 0 | O50: 413 | P50: 1 | Q50: 49775 | R50: 51013 | S50: =2003807+Q50 -> 2053582 | T50: =2003808+R50 -> 2054821 | W50: 8.0344008 | X50: 67.5
A51: contig_536_50 | B51: 50 | C51: no_hit | D51: 0 | E51: no_hit | F51: no_hit | G51: 0 | O51: 154 | P51: -1 | Q51: 50915 | R51: 51376 | S51: =2003807+Q51 -> 2054722 | T51: =2003808+R51 -> 2055184 | W51: 5.0908656 | X51: 15.2
A52: contig_536_51 | B52: 51 | C52: no_hit | D52: 0 | E52: no_hit | F52: no_hit | G52: 0 | O52: 85 | P52: -1 | Q52: 51570 | R52: 51824 | S52: =2003807+Q52 -> 2055377 | T52: =2003808+R52 -> 2055632 | W52: 13.792609 | X52: 22.9
A53: contig_536_52 | B53: 52 | C53: no_hit | D53: 0 | E53: no_hit | F53: no_hit | G53: 0 | O53: 64 | P53: -1 | Q53: 52017 | R53: 52208 | S53: =2003807+Q53 -> 2055824 | T53: =2003808+R53 -> 2056016 | W53: 15.132038 | X53: 19.9
A54: contig_536_53 | B54: 53 | C54: no_hit | D54: 0 | E54: no_hit | F54: no_hit | G54: 0 | O54: 211 | P54: 1 | Q54: 52544 | R54: 53176 | S54: =2003807+Q54 -> 2056351 | T54: =2003808+R54 -> 2056984 | W54: 5.2517058 | X54: 20.9
A55: contig_536_54 | B55: 54 | C55: no_hit | D55: 0 | E55: no_hit | F55: no_hit | G55: 0 | O55: 154 | P55: -1 | Q55: 53078 | R55: 53539 | S55: =2003807+Q55 -> 2056885 | T55: =2003808+R55 -> 2057347 | W55: 4.780573 | X55: 14.3
A56: contig_536_55 | B56: 55 | C56: no_hit | D56: 0 | E56: no_hit | F56: no_hit | G56: 0 | M56: Cre10.g439950_4532.5 | N56: (1 of 546) 2.7.11.1 - Non-specific serine/threonine protein kinase / Threonine-specific protein kinase | O56: 218 | P56: 1 | Q56: 54345 | R56: 54998 | S56: =2003807+Q56 -> 2058152 | T56: =2003808+R56 -> 2058806 | W56: 13.151889 | X56: 59.2
A57: contig_536_56 | B57: 56 | C57: no_hit | D57: 0 | E57: no_hit | F57: no_hit | G57: 0 | O57: 47 | P57: 1 | Q57: 55078 | R57: 55218 | S57: =2003807+Q57 -> 2058885 | T57: =2003808+R57 -> 2059026 | W57: 31.112996 | X57: 29.6
A58: contig_536_57 | B58: 57 | C58: no_hit | D58: 0 | E58: no_hit | F58: no_hit | G58: 0 | N58: early high expressed | O58: 207 | P58: 1 | Q58: 56672 | R58: 57292 | S58: =2003807+Q58 -> 2060479 | T58: =2003808+R58 -> 2061100 | W58: 21.010225 | X58: 90.1 | Y58: pre_induc
A59: contig_536_58 | B59: 58 | C59: no_hit | D59: 0 | E59: no_hit | F59: no_hit | G59: 0 | N59: early high expressed | O59: 752 | P59: 1 | Q59: 58986 | R59: 61241 | S59: =2003807+Q59 -> 2062793 | T59: =2003808+R59 -> 2065049 | W59: 18.166627 | X59: 279.5 | Y59: pre_induc
A60: contig_536_59 | B60: 59 | C60: GVOGm1062 | D60: 9.69536 | E60: NAD-dependent histone deacetylase activity (H3-K14 specific) | including yeast histone deacetylase and acetoin utilization protein | Histone deacetylase domain | including yeast histone deacetylase and acetoin utilization protein | tRNA guanylyltransferase activity | Histone deacetylase domain | protein deacetylase activity | NAD-dependent histone deacetylase activity (H3-K14 specific) | F60: Hist_deacetyl | G60: 13.93198 | H60: COG0123@1 | I60: B | K60: Belongs to the histone deacetylase family. HD Type 1 subfamily | O60: 430 | P60: 1 | Q60: 61358 | R60: 62647 | S60: =2003807+Q60 -> 2065165 | T60: =2003808+R60 -> 2066455 | W60: 16.447166 | X60: 146.9
A61: contig_536_60 | B61: 60 | C61: no_hit | D61: 0 | E61: no_hit | F61: no_hit | G61: 0 | O61: 238 | P61: 1 | Q61: 62721 | R61: 63434 | S61: =2003807+Q61 -> 2066528 | T61: =2003808+R61 -> 2067242 | W61: 22.859841 | X61: 110
A62: contig_536_61 | B62: 61 | C62: no_hit | D62: 0 | E62: no_hit | F62: no_hit | G62: 0 | O62: 585 | P62: 1 | Q62: 63775 | R62: 65529 | S62: =2003807+Q62 -> 2067582 | T62: =2003808+R62 -> 2069337 | W62: 13.880263 | X62: 161.9 | Y62: post_induc
A63: contig_536_62 | B63: 62 | C63: no_hit | D63: 0 | E63: no_hit | F63: no_hit | G63: 0 | O63: 82 | P63: 1 | Q63: 66072 | R63: 66317 | S63: =2003807+Q63 -> 2069879 | T63: =2003808+R63 -> 2070125 | W63: 5.2164494 | X63: 8
A64: contig_536_63 | B64: 63 | C64: no_hit | D64: 0 | E64: no_hit | F64: no_hit | G64: 0 | O64: 82 | P64: 1 | Q64: 66721 | R64: 66966 | S64: =2003807+Q64 -> 2070528 | T64: =2003808+R64 -> 2070774 | W64: 52.237803 | X64: 87.9
A65: contig_536_64 | B65: 64 | C65: no_hit | D65: 0 | E65: no_hit | F65: no_hit | G65: 0 | O65: 195 | P65: 1 | Q65: 67027 | R65: 67611 | S65: =2003807+Q65 -> 2070834 | T65: =2003808+R65 -> 2071419 | W65: 26.782851 | X65: 105.3
A66: contig_536_65 | B66: 65 | C66: no_hit | D66: 0 | E66: no_hit | F66: no_hit | G66: 0 | O66: 371 | P66: 1 | Q66: 67726 | R66: 68838 | S66: =2003807+Q66 -> 2071533 | T66: =2003808+R66 -> 2072646 | W66: 45.390132 | X66: 337.7
A67: contig_536_66 | B67: 66 | C67: no_hit | D67: 0 | E67: no_hit | F67: no_hit | G67: 0 | O67: 51 | P67: 1 | Q67: 68903 | R67: 69055 | S67: =2003807+Q67 -> 2072710 | T67: =2003808+R67 -> 2072863 | W67: 36.066559 | X67: 37
A68: contig_536_67 | B68: 67 | C68: no_hit | D68: 0 | E68: no_hit | F68: no_hit | G68: 0 | O68: 126 | P68: -1 | Q68: 69027 | R68: 69404 | S68: =2003807+Q68 -> 2072834 | T68: =2003808+R68 -> 2073212 | W68: 11.559445 | X68: 29.6
A69: contig_536_68 | B69: 68 | C69: no_hit | D69: 0 | E69: no_hit | F69: no_hit | G69: 0 | O69: 48 | P69: 1 | Q69: 69703 | R69: 69846 | S69: =2003807+Q69 -> 2073510 | T69: =2003808+R69 -> 2073654 | W69: 16.004236 | X69: 15.7
A70: contig_536_69 | B70: 69 | C70: no_hit | D70: 0 | E70: no_hit | F70: no_hit | G70: 0 | O70: 182 | P70: 1 | Q70: 69978 | R70: 70523 | S70: =2003807+Q70 -> 2073785 | T70: =2003808+R70 -> 2074331 | W70: 17.338983 | X70: 63.4
A71: contig_536_70 | B71: 70 | C71: no_hit | D71: 0 | E71: no_hit | F71: no_hit | G71: 0 | N71: early high expressed | O71: 51 | P71: 1 | Q71: 71140 | R71: 71292 | S71: =2003807+Q71 -> 2074947 | T71: =2003808+R71 -> 2075100 | W71: 129.15002 | X71: 136.2 | Y71: pre_induc
A72: contig_536_71 | B72: 71 | C72: no_hit | D72: 0 | E72: no_hit | F72: DNA_ligase_C | G72: 5.291503 | N72: early high expressed | O72: 798 | P72: 1 | Q72: 72722 | R72: 75115 | S72: =2003807+Q72 -> 2076529 | T72: =2003808+R72 -> 2078923 | W72: 23.383062 | X72: 378 | Y72: pre_induc
A73: contig_536_72 | B73: 72 | C73: no_hit | D73: 0 | E73: no_hit | F73: no_hit | G73: 0 | O73: 72 | P73: -1 | Q73: 75776 | R73: 75991 | S73: =2003807+Q73 -> 2079583 | T73: =2003808+R73 -> 2079799 | W73: 425.20939 | X73: 593.9 | Y73: post_induc
A74: contig_536_73 | B74: 73 | C74: no_hit | D74: 0 | E74: no_hit | F74: no_hit | G74: 0 | O74: 72 | P74: -1 | Q74: 76589 | R74: 76804 | S74: =2003807+Q74 -> 2080396 | T74: =2003808+R74 -> 2080612 | W74: 322.42526 | X74: 455.8 | Y74: post_induc
A75: contig_536_74 | B75: 74 | C75: no_hit | D75: 0 | E75: no_hit | F75: rve | G75: 18.33366 | H75: COG2801@1 | I75: L | J75: Mobile elements | K75: DNA RNA polymerases superfamily protein | L75: Gag-Pol polyprotein | M75: Cre15.g801742_4532.1 | N75: early high expressed | O75: 1564 | P75: -1 | Q75: 78948 | R75: 83639 | S75: =2003807+Q75 -> 2082755 | T75: =2003808+R75 -> 2087447 | W75: 43.614256 | X75: 1433.1 | Y75: pre_induc | Z75: Yes
A76: contig_536_75 | B76: 75 | C76: no_hit | D76: 0 | E76: no_hit | F76: no_hit | G76: 0 | L76: retrotransposon mcp? | M76: Cre15.g801743_4532.1 | N76: early high expressed | O76: 486 | P76: -1 | Q76: 83688 | R76: 85145 | S76: =2003807+Q76 -> 2087495 | T76: =2003808+R76 -> 2088953 | W76: 147.60224 | X76: 1440 | Y76: pre_induc
A77: contig_536_76 | B77: 76 | C77: GVOGm0180 | D77: 14.27585 | E77: function. Source PGD | unknown | unknown | unknown | unknown | F77: no_hit | G77: 0 | H77: 2EG1T@1 | I77: S | J77: Mobile elements | K77: function. Source PGD | M77: Cre17.g712700_4532.1 | N77: putative transposase; Fanzor_C_nuclease | O77: 660 | P77: -1 | Q77: 86338 | R77: 88317 | S77: =2003807+Q77 -> 2090145 | T77: =2003808+R77 -> 2092125 | W77: 0.57396699 | X77: 8.3 | Y77: post_induc | Z77: Yes
A78: contig_536_77 | B78: 77 | C78: no_hit | D78: 0 | E78: no_hit | F78: no_hit | G78: 0 | O78: 98 | P78: 1 | Q78: 88354 | R78: 88647 | S78: =2003807+Q78 -> 2092161 | T78: =2003808+R78 -> 2092455 | W78: 2.1192064 | X78: 4.6
A79: contig_536_78 | B79: 78 | C79: GVOGm1077 | D79: 11.07249 | E79: Homeodomain-like domain | DDE superfamily endonuclease | DDE superfamily endonuclease | DDE superfamily endonuclease | DDE superfamily endonuclease | DDE superfamily endonuclease | DDE superfamily endonuclease | DDE superfamily endonuclease | DDE superfamily endonuclease | Source PGD | DDE superfamily endonuclease | unknown | unknown | DDE superfamily endonuclease | Transposase and inactivated derivatives | unknown | DDE superfamily endonuclease | F79: DDE_3 | G79: 8.133906 | H79: COG3335@1 | I79: L | K79: DDE superfamily endonuclease | N79: Fanzor_C_transposase | O79: 331 | P79: -1 | Q79: 88530 | R79: 89522 | S79: =2003807+Q79 -> 2092337 | T79: =2003808+R79 -> 2093330 | W79: 2.1720733 | X79: 14.9
A80: contig_536_79 | B80: 79 | C80: no_hit | D80: 0 | E80: no_hit | F80: no_hit | G80: 0 | O80: 112 | P80: -1 | Q80: 90972 | R80: 91307 | S80: =2003807+Q80 -> 2094779 | T80: =2003808+R80 -> 2095115 | W80: 20.473609 | X80: 44.3
A81: contig_536_80 | B81: 80 | C81: no_hit | D81: 0 | E81: no_hit | F81: no_hit | G81: 0 | O81: 76 | P81: -1 | Q81: 91274 | R81: 91501 | S81: =2003807+Q81 -> 2095081 | T81: =2003808+R81 -> 2095309 | W81: 20.575151 | X81: 30.2
A82: contig_536_81 | B82: 81 | C82: no_hit | D82: 0 | E82: no_hit | F82: no_hit | G82: 0 | O82: 93 | P82: 1 | Q82: 91760 | R82: 92038 | S82: =2003807+Q82 -> 2095567 | T82: =2003808+R82 -> 2095846 | W82: 37.284621 | X82: 69.2
A83: contig_536_82 | B83: 82 | C83: no_hit | D83: 0 | E83: no_hit | F83: no_hit | G83: 0 | O83: 45 | P83: -1 | Q83: 92149 | R83: 92283 | S83: =2003807+Q83 -> 2095956 | T83: =2003808+R83 -> 2096091 | W83: 6.8018922 | X83: 5.4
A84: contig_536_83 | B84: 83 | C84: no_hit | D84: 0 | E84: no_hit | F84: no_hit | G84: 0 | O84: 54 | P84: 1 | Q84: 92496 | R84: 92657 | S84: =2003807+Q84 -> 2096303 | T84: =2003808+R84 -> 2096465 | W84: 15.631655 | X84: 15.6
A85: contig_536_84 | B85: 84 | C85: no_hit | D85: 0 | E85: no_hit | F85: no_hit | G85: 0 | O85: 149 | P85: 1 | Q85: 93127 | R85: 93573 | S85: =2003807+Q85 -> 2096934 | T85: =2003808+R85 -> 2097381 | W85: 22.289733 | X85: 67.7
A86: contig_536_85 | B86: 85 | C86: no_hit | D86: 0 | E86: no_hit | F86: no_hit | G86: 0 | O86: 48 | P86: -1 | Q86: 93960 | R86: 94103 | S86: =2003807+Q86 -> 2097767 | T86: =2003808+R86 -> 2097911 | W86: 0.5301825 | X86: 0.3
A87: contig_536_86 | B87: 86 | C87: no_hit | D87: 0 | E87: no_hit | F87: HTH_33 | G87: 5.059644 | O87: 150 | P87: -1 | Q87: 94079 | R87: 94528 | S87: =2003807+Q87 -> 2097886 | T87: =2003808+R87 -> 2098336 | W87: 7.2384103 | X87: 21.9
A88: contig_536_87 | B88: 87 | C88: no_hit | D88: 0 | E88: no_hit | F88: no_hit | G88: 0 | O88: 33 | P88: -1 | Q88: 95519 | R88: 95617 | S88: =2003807+Q88 -> 2099326 | T88: =2003808+R88 -> 2099425 | W88: 3.1386665 | X88: 1.9
A89: contig_536_88 | B89: 88 | C89: no_hit | D89: 0 | E89: no_hit | F89: no_hit | G89: 0 | O89: 75 | P89: -1 | Q89: 95602 | R89: 95826 | S89: =2003807+Q89 -> 2099409 | T89: =2003808+R89 -> 2099634 | W89: 75.78634 | X89: 113.9
A90: contig_536_89 | B90: 89 | C90: no_hit | D90: 0 | E90: no_hit | F90: no_hit | G90: 0 | O90: 81 | P90: 1 | Q90: 96458 | R90: 96700 | S90: =2003807+Q90 -> 2100265 | T90: =2003808+R90 -> 2100508 | W90: 29.86153 | X90: 52.1
A91: contig_536_90 | B91: 90 | C91: no_hit | D91: 0 | E91: no_hit | F91: no_hit | G91: 0 | O91: 209 | P91: 1 | Q91: 97277 | R91: 97903 | S91: =2003807+Q91 -> 2101084 | T91: =2003808+R91 -> 2101711 | W91: 45.932041 | X91: 200.8
A92: contig_536_91 | B92: 91 | C92: no_hit | D92: 0 | E92: no_hit | F92: no_hit | G92: 0 | O92: 47 | P92: 1 | Q92: 98251 | R92: 98391 | S92: =2003807+Q92 -> 2102058 | T92: =2003808+R92 -> 2102199 | W92: 13.051992 | X92: 12.1
A93: contig_536_92 | B93: 92 | C93: GVOGm1077 | D93: 12.21065 | E93: Homeodomain-like domain | DDE superfamily endonuclease | DDE superfamily endonuclease | DDE superfamily endonuclease | DDE superfamily endonuclease | DDE superfamily endonuclease | DDE superfamily endonuclease | DDE superfamily endonuclease | DDE superfamily endonuclease | Source PGD | DDE superfamily endonuclease | unknown | unknown | DDE superfamily endonuclease | Transposase and inactivated derivatives | unknown | DDE superfamily endonuclease | F93: DDE_3 | G93: 8.319899 | H93: COG3335@1 | I93: L | K93: Evidence 3 Function proposed based on presence of conserved amino acid motif, structural feature or limited homology | N93: Fanzor_A_transposase | O93: 317 | P93: 1 | Q93: 98581 | R93: 99531 | S93: =2003807+Q93 -> 2102388 | T93: =2003808+R93 -> 2103339 | W93: 6.0280198 | X93: 39.4
A94: contig_536_93 | B94: 93 | C94: GVOGm0180 | D94: 7.402702 | E94: function. Source PGD | unknown | unknown | unknown | unknown | F94: no_hit | G94: 0 | N94: Fanzor_A_nuclease | O94: 1205 | P94: 1 | Q94: 99694 | R94: 103308 | S94: =2003807+Q94 -> 2103501 | T94: =2003808+R94 -> 2107116 | W94: 1.1177134 | X94: 29.6 | Y94: post_induc
A95: contig_536_94 | B95: 94 | C95: no_hit | D95: 0 | E95: no_hit | F95: no_hit | G95: 0 | O95: 86 | P95: -1 | Q95: 103476 | R95: 103733 | S95: =2003807+Q95 -> 2107283 | T95: =2003808+R95 -> 2107541 | W95: 42.241255 | X95: 73.4
A96: contig_536_95 | B96: 95 | C96: no_hit | D96: 0 | E96: no_hit | F96: no_hit | G96: 0 | O96: 96 | P96: 1 | Q96: 103933 | R96: 104220 | S96: =2003807+Q96 -> 2107740 | T96: =2003808+R96 -> 2108028 | W96: 10.635325 | X96: 19.2
A97: contig_536_96 | B97: 96 | C97: no_hit | D97: 0 | E97: no_hit | F97: no_hit | G97: 0 | O97: 125 | P97: -1 | Q97: 104178 | R97: 104552 | S97: =2003807+Q97 -> 2107985 | T97: =2003808+R97 -> 2108360 | W97: 42.274923 | X97: 105
A98: contig_536_97 | B98: 97 | C98: no_hit | D98: 0 | E98: no_hit | F98: no_hit | G98: 0 | O98: 43 | P98: -1 | Q98: 104549 | R98: 104677 | S98: =2003807+Q98 -> 2108356 | T98: =2003808+R98 -> 2108485 | W98: 0.6471022 | X98: 0.7
A99: contig_536_98 | B99: 98 | C99: GVOGm0339 | D99: 12.92285 | E99: unknown | unknown | unknown | unknown | F99: no_hit | G99: 0 | O99: 313 | P99: -1 | Q99: 104703 | R99: 105641 | S99: =2003807+Q99 -> 2108510 | T99: =2003808+R99 -> 2109449 | W99: 1.0660562 | X99: 7.2
A100: contig_536_99 | B100: 99 | C100: no_hit | D100: 0 | E100: no_hit | F100: no_hit | G100: 0 | O100: 352 | P100: -1 | Q100: 105683 | R100: 106738 | S100: =2003807+Q100 -> 2109490 | T100: =2003808+R100 -> 2110546 | W100: 2.786245 | X100: 21.8 | Y100: post_induc
...

Sheet hhpred proteomics
A1: gene | B1: Category | C1: Nr | D1: Hit | E1: Name | F1: Probability | G1: E-value | H1: Score | I1: SS | J1: Aligned cols | K1: Target Length
A2: contig_536_46 | B2: Unknown | C2: 1 | D2: 7BVW_A | E2: AT5G66160 protein; C3H2C3, ring finger, E3 ligase, TRANSPORT PROTEIN; 2.1A {Arabidopsis thaliana} | F2: 23.78 | G2: 110 | H2: 15.52 | I2: 1.1 | J2: 14 | K2: 82
C3: 2 | D3: 1I27_A | E3: TRANSCRIPTION FACTOR IIF; GENERAL TRANSCRIPTION FACTOR, RAP74, RAP30, TFIIF, RNA POLYMERASE II, WINGED-HELIX DOMAIN, TRA | F3: 20.57 | G3: 99 | H3: 21.86 | I3: 0.7 | J3: 12 | K3: 73
A4: contig_536_74 | B4: Mobile elements | C4: 1 | D4: 7Q5B_C | E4: Transposon Ty3-G Gag-Pol polyprotein; Transcription, RNA Pol III, Ty3 Retrotransposon, Intasome, DNA BINDING PROTEIN;{Sa | F4: 100 | G4: 3.9e-56 | H4: 650.06 | I4: 100.9 | J4: 1150 | K4: 1547
C5: 2 | D5: P03359 | E5: POL_WMSV Gag-Pol polyprotein OS=Woolly monkey sarcoma virus OX=11970 GN=pol PE=3 SV=2 | F5: 100 | G5: 2e-53 | H5: 619.81 | I5: 88.6 | J5: 889 | K5: 1687
C6: 3 | D6: P10272 | E6: POL_BAEVM Gag-Pol polyprotein OS=Baboon endogenous virus (strain M7) OX=11764 GN=pol PE=3 SV=2 | F6: 100 | G6: 7.5e-54 | H6: 619.25 | I6: 81.9 | J6: 895 | K6: 1727
C7: 4 | D7: O92815 | E7: POL_WDSV Gag-Pol polyprotein OS=Walleye dermal sarcoma virus OX=39720 GN=gag-pol PE=1 SV=2 | F7: 100 | G7: 6.5e-49 | H7: 580.91 | I7: 95.7 | J7: 1137 | K7: 1752
C8: 5 | D8: P03355 | E8: POL_MLVMS Gag-Pol polyprotein OS=Moloney murine leukemia virus (isolate Shinnick) OX=928306 GN=gag-pol PE=1 SV=5 | F8: 100 | G8: 3e-46 | H8: 551.45 | I8: 86 | J8: 1115 | K8: 1738
A9: contig_536_76 | B9: Mobile elements | C9: 1 | D9: 8GKH_P | E9: Maltodextrin-binding protein (Fragment),OrfB_Zn_ribbon domain-containing protein; Fanzor, Eukaryotic, RNA-guided, nuclea | F9: 100 | G9: 1.1e-60 | H9: 570.41 | I9: 49.2 | J9: 584 | K9: 1032
B10: Fanzor_C_nuclease | C10: 2 | D10: Q5UPF5 | E10: YL079_MIMIV Putative transposase L79 OS=Acanthamoeba polyphaga mimivirus OX=212035 GN=MIMI_L79 PE=3 SV=1 | F10: 99.5 | G10: 1.8e-13 | H10: 152.19 | I10: 11.8 | J10: 104 | K10: 520
C11: 3 | D11: O41107 | E11: A625_PBCV1 Putative transposase A625R OS=Paramecium bursaria Chlorella virus 1 OX=10506 GN=A625R PE=3 SV=1 | F11: 99.49 | G11: 3e-13 | H11: 147.27 | I11: 12.6 | J11: 110 | K11: 433
C12: 4 | D12: Q5URB4 | E12: YR186_MIMIV Putative transposase R186 OS=Acanthamoeba polyphaga mimivirus OX=212035 GN=MIMI_R186 PE=3 SV=1 | F12: 99.46 | G12: 9.5e-13 | H12: 145.16 | I12: 14.1 | J12: 221 | K12: 482
C13: 5 | D13: Q3V4S9 | E13: Y409_ATV Putative transposase ORF409 OS=Acidianus two-tailed virus OX=315953 PE=3 SV=1 | F13: 99.42 | G13: 1.4e-12 | H13: 140.88 | I13: 11.6 | J13: 207 | K13: 409
A14: contig_536_100 | B14: Metabolism, miscellaneous | C14: 1 | D14: 5LW3_A | E14: Poly(beta-D-mannuronate) C5 epimerase 6; C-5 Epimerase, isomerase; HET: B3P; 1.19A {Azotobacter vinelandii} | F14: 99.84 | G14: 1.8e-17 | H14: 183.93 | I14: 35.3 | J14: 261 | K14: 387
C15: 2 | D15: 3ZPP_A | E15: CELL WALL SURFACE ANCHOR FAMILY PROTEIN; CELL ADHESION, PFBA, SURFACE ADHESIN, SP1833, MSCRAMM; 2.28A {STREPTOCOCCUS PNE | F15: 99.8 | G15: 2.7e-16 | H15: 178.13 | I15: 35.5 | J15: 321 | K15: 443
C16: 3 | D16: 5ZRU_C | E16: Alpha-1,3-glucanase; Agl-KA GH87, HYDROLASE; HET: CA, SO4, PE5; 1.833A {Bacillus circulans} | F16: 99.8 | G16: 1.6e-15 | H16: 186.36 | I16: 45.1 | J16: 325 | K16: 578
C17: 4 | D17: 7JWF_B | E17: Glycoside hydrolase family 110; beta helix, HYDROLASE; HET: GAL, EDO, EPE, ACT, MLT, CL, IOD, GLA, PG4; 2.187A {Pseudoal | F17: 99.75 | G17: 8e-15 | H17: 180.26 | I17: 39.2 | J17: 322 | K17: 620
C18: 5 | D18: 7C7D_A | E18: alpha-1,3-glucanase; glycosidase, HYDROLASE; HET: 1PE; 1.16A {Streptomyces thermodiastaticus} | F18: 99.75 | G18: 1.1e-14 | H18: 178.22 | I18: 40.1 | J18: 336 | K18: 610
A19: contig_536_101 | B19: Metabolism, miscellaneous | C19: 1 | D19: 3WX7_A | E19: Chitin oligosaccharide deacetylase; oligosaccharide deacetylace, carbohydrate-binding, HYDROLASE; HET: GOL; 1.349A {Vibr | F19: 96.54 | G19: 0.017 | H19: 71.22 | I19: 9.4 | J19: 86 | K19: 402
C20: 2 | D20: 3WX7_A | E20: Chitin oligosaccharide deacetylase; oligosaccharide deacetylace, carbohydrate-binding, HYDROLASE; HET: GOL; 1.349A {Vibr | F20: 96.24 | G20: 0.034 | H20: 68.69 | I20: 9.6 | J20: 84 | K20: 402
C21: 3 | D21: 3WX7_A | E21: Chitin oligosaccharide deacetylase; oligosaccharide deacetylace, carbohydrate-binding, HYDROLASE; HET: GOL; 1.349A {Vibr | F21: 96.03 | G21: 0.056 | H21: 66.94 | I21: 10 | J21: 93 | K21: 402
C22: 4 | D22: 3WX7_A | E22: Chitin oligosaccharide deacetylase; oligosaccharide deacetylace, carbohydrate-binding, HYDROLASE; HET: GOL; 1.349A {Vibr | F22: 95.9 | G22: 0.059 | H22: 66.77 | I22: 9.4 | J22: 98 | K22: 402
C23: 5 | D23: SM00495 | E23: ChtBD3; Chitin-binding domain type 3 | F23: 91.51 | G23: 0.91 | H23: 37.43 | I23: 5.1 | J23: 40 | K23: 41
A24: contig_536_102 | B24: Metabolism, miscellaneous | C24: 1 | D24: 3WX7_A | E24: Chitin oligosaccharide deacetylase; oligosaccharide deacetylace, carbohydrate-binding, HYDROLASE; HET: GOL; 1.349A {Vibr | F24: 91.54 | G24: 0.93 | H24: 60.56 | I24: 7.9 | J24: 91 | K24: 402
C25: 2 | D25: 3WX7_A | E25: Chitin oligosaccharide deacetylase; oligosaccharide deacetylace, carbohydrate-binding, HYDROLASE; HET: GOL; 1.349A {Vibr | F25: 89.97 | G25: 1.4 | H25: 59.02 | I25: 7.5 | J25: 91 | K25: 402
C26: 3 | D26: 3WX7_A | E26: Chitin oligosaccharide deacetylase; oligosaccharide deacetylace, carbohydrate-binding, HYDROLASE; HET: GOL; 1.349A {Vibr | F26: 86.08 | G26: 5.9 | H26: 53.62 | I26: 9.5 | J26: 115 | K26: 402
C27: 4 | D27: 3WX7_A | E27: Chitin oligosaccharide deacetylase; oligosaccharide deacetylace, carbohydrate-binding, HYDROLASE; HET: GOL; 1.349A {Vibr | F27: 84.34 | G27: 4.7 | H27: 54.46 | I27: 7.5 | J27: 90 | K27: 402
C28: 5 | D28: 7R5K_V0 | E28: Nuclear pore complex protein Nup214; multiprotein complex, nucleocytoplasmic transport, TRANSPORT PROTEIN; 12.0A {Homo s | F28: 69.87 | G28: 25 | H28: 56.78 | I28: 8.6 | J28: 89 | K28: 2090
A29: contig_536_107 | B29: Transcription, replication | C29: 1 | D29: 1W36_G | E29: EXODEOXYRIBONUCLEASE V ALPHA CHAIN; RECOMBINATION, HELICASE, NUCLEASE, HYDROLASE, DNA REPAIR; 3.1A {ESCHERICHIA COLI} SC | F29: 99.97 | G29: 4.7e-30 | H29: 319.57 | I29: 32 | J29: 342 | K29: 608
C30: 2 | D30: 3E1S_A | E30: Exodeoxyribonuclease V, subunit RecD; alpha and beta protein, ATP-binding, Nucleotide-binding, HYDROLASE; 2.2A {Deinococ | F30: 99.97 | G30: 1.7e-28 | H30: 301.81 | I30: 31.6 | J30: 338 | K30: 574
C31: 3 | D31: 8BNS_C | E31: AAA ATPase; Helicase Thermophile, HYDROLASE; HET: ADP; 3.24A {Sulfurihydrogenibium sp. YO3AOP1} | F31: 99.96 | G31: 3e-28 | H31: 293.84 | I31: 27.8 | J31: 351 | K31: 517
C32: 4 | D32: 7BIL_B | E32: PIF1 helicase; DNA helicase, HYDROLASE; HET: ADP, ALF; 2.21A {Thermus oshimai JL-2} | F32: 99.96 | G32: 4.1e-28 | H32: 292.98 | I32: 25.8 | J32: 382 | K32: 507
C33: 5 | D33: 8BNV_A | E33: AAA family ATPase; Helicase Thermophile, HYDROLASE; HET: GOL; 2.86A {Deferribacter desulfuricans} | F33: 99.95 | G33: 4.5e-26 | H33: 271.63 | I33: 29 | J33: 349 | K33: 510
A34: contig_536_113 | B34: Unknown | C34: 1 | D34: 5SY7_B | E34: Neuronal PAS domain-containing protein 3; bHLH-PAS protein, transcription factor, heterodimeric complex, transcription-D | F34: 16.02 | G34: 110 | H34: 23.06 | I34: 0.1 | J34: 34 | K34: 410
A35: contig_536_120 | B35: Unknown | C35: 1 | D35: 8ANV_F | E35: Arbitrium putative lysogeny regulator; Arbitrium, Phi3T, lysis-lysogeny decission, VIRAL PROTEIN; 2.2A {Bacillus phage p | F35: 63.01 | G35: 18 | H35: 25.71 | I35: 2.6 | J35: 28 | K35: 52
C36: 2 | D36: PF05130.16 | E36: ; FlgN ; FlgN protein | F36: 54.77 | G36: 88 | H36: 21.88 | I36: 4.8 | J36: 63 | K36: 142
C37: 3 | D37: 2BO4_D | E37: MANNOSYLGLYCERATE SYNTHASE; CATALYSIS, GLYCOSYLTRANSFERASE, MANNOSE, TRANSFERASE, STEREOSELECTIVITY; HET: FLC; 1.95A {RH | F37: 45.82 | G37: 250 | H37: 23.5 | I37: 6.8 | J37: 56 | K37: 397
C38: 4 | D38: 7LV9_B | E38: Histone doublet Delta-Gamma (Delta); Structural Protein/DNA, STRUCTURAL PROTEIN, STRUCTURAL PROTEIN-DNA complex; 4.5A {M | F38: 41.13 | G38: 180 | H38: 21.69 | I38: 4.9 | J38: 47 | K38: 97
C39: 5 | D39: 1TAF_A | E39: TFIID TBP ASSOCIATED FACTOR 42; TRANSCRIPTION INITIATION, HISTONE FOLD, COMPLEX (TWO TRANSCRIPTION FACTORS); 2.0A {Droso | F39: 41.11 | G39: 81 | H39: 20.22 | I39: 2.8 | J39: 46 | K39: 68
A40: contig_536_123 | B40: Unknown | C40: 1 | D40: 6RBG_B | E40: Chain length determinant protein; membrane protein, enzyme, polysaccharide, co-polymerase; 3.0A {Escherichia coli (strai | F40: 91.82 | G40: 11 | H40: 31.54 | I40: 12.2 | J40: 150 | K40: 341
C41: 2 | D41: 8QOX_B | E41: Conserved membrane protein; S-layer, dimer, N-glycosylation, STRUCTURAL PROTEIN;{Sulfolobus acidocaldarius DSM 639} | F41: 90.03 | G41: 19 | H41: 33.54 | I41: 12.3 | J41: 135 | K41: 475
C42: 3 | D42: PF09577.14 | E42: ; Spore_YpjB ; Sporulation protein YpjB (SpoYpjB) | F42: 90.02 | G42: 18 | H42: 30.83 | I42: 13.2 | J42: 124 | K42: 229
C43: 4 | D43: Q66676 | E43: VGE9_EHV2 Uncharacterized gene E9 protein OS=Equine herpesvirus 2 (strain 86/87) OX=82831 GN=E9 PE=3 SV=1 | F43: 84.78 | G43: 2.7 | H43: 37.97 | I43: 3.9 | J43: 44 | K43: 205
C44: 5 | D44: 3IMM_C | E44: Putative secreted glycosylhydrolase; YP_001301887.1, Putative glycosyl hydrolase, Structural Genomics, Joint Center for | F44: 82.83 | G44: 25 | H44: 25.62 | I44: 7.4 | J44: 66 | K44: 201
A45: contig_536_129 | B45: Unknown | C45: 1 | D45: 2AQX_B | E45: PREDICTED: inositol 1,4,5-trisphosphate 3-kinase B; IP3K, ITPKB, IP3-3K, IP3-3KB, inositol, kinase, IP3, Calmodulin bind | F45: 59.16 | G45: 89 | H45: 28.11 | I45: 6.7 | J45: 71 | K45: 289
C46: 2 | D46: 5W2I_A | E46: Inositol polyphosphate multikinase,Inositol polyphosphate multikinase; kinase, inositol, inositol polyphosphate, phospha | F46: 48.51 | G46: 110 | H46: 26.36 | I46: 5.5 | J46: 44 | K46: 257
C47: 3 | D47: 4O4F_A | E47: Inositol hexakisphosphate kinase; PDGK Kinase, Inositol Phosphate, TRANSFERASE; HET: IHP, ATP, PO4; 1.7A {Entamoeba hist | F47: 46.18 | G47: 180 | H47: 25.15 | I47: 6.3 | J47: 50 | K47: 248
C48: 4 | D48: 4FRF_B | E48: Inositol polyphosphate multikinase alpha; ATP Grasp, Inositol phosphate kinase, TRANSFERASE; HET: SO4; 2.9A {Arabidopsis | F48: 46.11 | G48: 100 | H48: 27.08 | I48: 5 | J48: 44 | K48: 275
C49: 5 | D49: PF08844.14 | E49: ; DUF1815 ; Domain of unknown function (DUF1815) | F49: 39.46 | G49: 88 | H49: 27.88 | I49: 3.6 | J49: 40 | K49: 101
A50: contig_536_130 | B50: Transcription, replication | D50: GVOGm0461 | E50: DNA topoisomerase type II (ATP-hydrolyzing) activity | A type II topoisomerase that negatively supercoils closed circular double-stranded (ds) DNA in an ATP-dependent manner to modulate DNA topology and maintain chromosomes in an underwound state. Negative supercoiling favors strand separation, and DNA replication, transcription, recombination and repair, all of which involve strand separation. Also able to catalyze the interconversion of other topological isomers of dsDNA rings, including catenanes and knotted rings. Type II topoisomerases break and join 2 DNA strands simultaneously in an ATP-dependent manner | protein K63-linked ubiquitination | methyltransferase activity | A type II topoisomerase that negatively supercoils closed circular double-stranded (ds) DNA in an ATP-dependent manner to modulate DNA topology and maintain chromosomes in an underwound state. Negative supercoiling favors strand separation, and DNA replication, transcription, recombination and repair, all of which involve strand separation. Also able to catalyze the interconversion of other topological isomers of dsDNA rings, including catenanes and knotted rings. Type II topoisomerases break and join 2 DNA strands simultaneously in an ATP-dependent manner | DNA topoisomerase II activity | A type II topoisomerase that negatively supercoils closed circular double-stranded (ds) DNA in an ATP-dependent manner to modulate DNA topology and maintain chromosomes in an underwound state. Negative supercoiling favors strand separation, and DNA replication, transcription, recombination and repair, all of which involve strand separation. Also able to catalyze the interconversion of other topological isomers of dsDNA rings, including catenanes and knotted rings. Type II topoisomerases break and join 2 DNA strands simultaneously in an ATP-dependent manner | F50: - | G50: - | H50: - | I50: - | J50: - | K50: -
A51: contig_536_144 | B51: Mobile elements | E51: Fanzor_B_nuclease | F51: - | G51: - | H51: - | I51: - | J51: - | K51: -
A52: contig_536_146 | B52: Mobile elements | E52: Fanzor_B_transposase | F52: - | G52: - | H52: - | I52: - | J52: - | K52: -
A53: contig_536_164 | B53: Transcription, replication | D53: GVOGm0022 | E53: DNA-directed 5'-3' RNA polymerase activity | DNA-directed 5'-3' RNA polymerase activity | DNA-dependent RNA polymerase catalyzes the transcription of DNA into RNA using the four ribonucleoside triphosphates as substrates | DNA-directed 5'-3' RNA polymerase activity | structural constituent of ribosome | RNA polymerase activity | tRNA methyltransferase 11-2 homolog | F53: - | G53: - | H53: - | I53: - | J53: - | K53: -
A54: contig_536_167 | B54: Metabolism, miscellaneous | C54: 1 | D54: 7QP0_B | E54: Metacaspase-1; METACASPASE, PROTEASE, CA2+-DEPENDENT ACTIVATION, APOPTOSIS; HET: EPE; 1.6A {[Candida] glabrata} | F54: 99.96 | G54: 6.5e-26 | H54: 175.4 | I54: 26.3 | J54: 245 | K54: 392
C55: 2 | D55: 4AF8_A | E55: METACASPASE MCA2; HYDROLASE, CYSTEINE PEPTIDASE, CASPASE/HEMOGLOBIN FOLD; 1.4A {TRYPANOSOMA BRUCEI} | F55: 99.96 | G55: 3.5e-25 | H55: 170.03 | I55: 27.7 | J55: 249 | K55: 367
C56: 3 | D56: 4F6P_A | E56: Metacaspase-1; Rossmann fold, metacaspase, HYDROLASE; HET: DFH; 1.619A {Saccharomyces cerevisiae} | F56: 99.96 | G56: 3.3e-25 | H56: 169.2 | I56: 26.8 | J56: 246 | K56: 350
C57: 4 | D57: 8A53_A | E57: Metacaspase-9; Metacaspase, Cysteine protease, Caspase-hemoglobinase fold, Plant protein, HYDROLASE; HET: NO3; 1.95A {Ar | F57: 99.95 | G57: 6.2e-25 | H57: 167.32 | I57: 26.4 | J57: 246 | K57: 348
C58: 5 | D58: SM00115 | E58: CASc; Caspase, interleukin-1 beta converting enzyme (ICE) homologu | F58: 99.93 | G58: 9.7e-23 | H58: 147.71 | I58: 24.8 | J58: 225 | K58: 241
A59: contig_536_168 | B59: Unknown | C59: 1 | D59: 7MQA_LT | E59: WD repeat-containing protein 36; Ribosomal assembly intermediate, RIBOSOME; HET: ATP, SAH, GTP, 4AC, OMU, OMC, PSU, OMG, | F59: 64.43 | G59: 71 | H59: 33.41 | I59: 7.9 | J59: 74 | K59: 951
C60: 2 | D60: PF07624.15 | E60: ; PSD2 ; Protein of unknown function (DUF1585) | F60: 61.57 | G60: 49 | H60: 22.74 | I60: 4.5 | J60: 60 | K60: 74
C61: 3 | D61: PF07587.15 | E61: ; PSD1 ; Protein of unknown function (DUF1553) | F61: 58.04 | G61: 36 | H61: 30.43 | I61: 4.2 | J61: 58 | K61: 263
C62: 4 | D62: PF18834.5 | E62: ; LPD22 ; Large polyvalent protein associated domain 22 | F62: 52.76 | G62: 57 | H62: 27.32 | I62: 4.3 | J62: 63 | K62: 96
C63: 5 | D63: 5ICA_D | E63: Periodic tryptophan protein 2-like protein; rRNA processing, 90S preribosome, protein binding, STRUCTURAL PROTEIN; 3.507 | F63: 48.87 | G63: 250 | H63: 23.21 | I63: 9.3 | J63: 83 | K63: 149
A64: contig_536_176 | B64: Transcription, replication | D64: GVOGm0020 | E64: helicase activity | histone H2A-H2B dimer displacement | Type III restriction enzyme res subunit | Type III restriction enzyme, res subunit | Transcription regulator that activates transcription by stimulating RNA polymerase (RNAP) recycling in case of stress conditions such as supercoiled DNA or high salt concentrations. Probably acts by releasing the RNAP, when it is trapped or immobilized on tightly supercoiled DNA. Does not activate transcription on linear DNA. Probably not involved in DNA repair | ATP binding | DNA repair and recombination protein | unknown | helicase activity | pyrimidine dimer repair by nucleotide-excision repair | annealing helicase activity | F64: - | G64: - | H64: - | I64: - | J64: - | K64: -
A65: contig_536_177 | B65: Unknown | C65: 1 | D65: PF19196.4 | E65: ; DUF5871 ; Family of unknown function (DUF5871) | F65: 95.39 | G65: 0.01 | H65: 46.2 | I65: 0.4 | J65: 95 | K65: 136
C66: 2 | D66: P18178 | E66: VP31_FRG3G Early 31 kDa protein OS=Frog virus 3 (isolate Goorha) OX=654924 PE=4 SV=1 | F66: 95.09 | G66: 0.038 | H66: 47.34 | I66: 2.8 | J66: 99 | K66: 261
C67: 3 | D67: Q5UPW9 | E67: YL291_MIMIV Uncharacterized protein L291 OS=Acanthamoeba polyphaga mimivirus OX=212035 GN=MIMI_L291 PE=4 SV=1 | F67: 94.14 | G67: 0.012 | H67: 59 | I67: -2.5 | J67: 101 | K67: 595
C68: 4 | D68: PF10927.12 | E68: ; DUF2738 ; Protein of unknown function (DUF2738) | F68: 93.28 | G68: 0.11 | H68: 43.52 | I68: 2 | J68: 97 | K68: 244
C69: 5 | D69: Q5UQ67 | E69: YR506_MIMIV Uncharacterized protein R506 OS=Acanthamoeba polyphaga mimivirus OX=212035 GN=MIMI_R506 PE=4 SV=1 | F69: 89.92 | G69: 0.16 | H69: 46.9 | I69: -0.6 | J69: 45 | K69: 320
A70: contig_536_181 | B70: Transcription, replication | C70: 1 | D70: Q91FI9 | E70: VF335_IIV6 Uncharacterized protein 335L OS=Invertebrate iridescent virus 6 OX=176652 GN=IIV6-335L PE=3 SV=1 | F70: 99.93 | G70: 8.1e-24 | H70: 208.29 | I70: 22.2 | J70: 161 | K70: 331
C71: 2 | D71: Q5UQP9 | E71: TBPL_MIMIV TATA-box-binding protein-like OS=Acanthamoeba polyphaga mimivirus OX=212035 GN=MIMI_R453 PE=3 SV=1 | F71: 99.92 | G71: 8.2e-23 | H71: 203.74 | I71: 28 | J71: 200 | K71: 367
C72: 3 | D72: Q65175 | E72: VF263_ASFB7 Uncharacterized protein B263R OS=African swine fever virus (strain Badajoz 1971 Vero-adapted) OX=10498 GN=Ba | F72: 99.9 | G72: 3.5e-22 | H72: 190.79 | I72: 19.5 | J72: 164 | K72: 263
C73: 4 | D73: 1YTB_A | E73: PROTEIN (TATA BINDING PROTEIN (TBP)); PROTEIN-DNA COMPLEX, TRANSCRIPTION-DNA COMPLEX; 1.8A {Saccharomyces cerevisiae} SC | F73: 99.89 | G73: 1.2e-21 | H73: 172.92 | I73: 19.4 | J73: 139 | K73: 180
C74: 5 | D74: Q197E3 | E74: VF335_IIV3 Uncharacterized protein 017R OS=Invertebrate iridescent virus 3 OX=345201 GN=IIV3-017R PE=3 SV=1 | F74: 99.88 | G74: 3e-21 | H74: 187.01 | I74: 19.3 | J74: 152 | K74: 289
A75: contig_536_184 | B75: Transcription, replication | C75: 1 | D75: Q5UPU2 | E75: YR252_MIMIV Uncharacterized protein R252 OS=Acanthamoeba polyphaga mimivirus OX=212035 GN=MIMI_R252 PE=4 SV=1 | F75: 90.98 | G75: 1.6 | H75: 40.49 | I75: 6.5 | J75: 106 | K75: 278
C76: 2 | D76: PF05854.15 | E76: ; MC1 ; Non-histone chromosomal protein MC1 | F76: 74.48 | G76: 3.8 | H76: 31.91 | I76: 1.4 | J76: 65 | K76: 92
C77: 3 | D77: 2NBJ_A | E77: Chromosomal protein MC1; DNA-protein complex, bent DNA, archaea, DNA BINDING PROTEIN-DNA complex; NMR {Methanosarcina th | F77: 62.26 | G77: 18 | H77: 28.6 | I77: 2.8 | J77: 65 | K77: 93
C78: 4 | D78: SM00537 | E78: DCX; Domain in the Doublecortin (DCX) gene product | F78: 61.16 | G78: 17 | H78: 25.49 | I78: 2.2 | J78: 65 | K78: 89
C79: 5 | D79: PF09435.14 | E79: ; DUF2015 ; Fungal protein of unknown function (DUF2015) | F79: 36.07 | G79: 54 | H79: 27.09 | I79: 1.8 | J79: 18 | K79: 111
A80: contig_536_202 | B80: Unknown | C80: 1 | D80: PF12901.11 | E80: ; SUZ-C ; SUZ-C motif | F80: 18.07 | G80: 210 | H80: 15.75 | I80: 1.5 | J80: 16 | K80: 25
A81: contig_536_263 | B81: Transcription, replication | D81: GVOGm0036 | E81: mRNA (guanine-N7-)-methyltransferase activity | mRNA guanylyltransferase activity | mRNA capping enzyme | F81: - | G81: - | H81: - | I81: - | J81: - | K81: -
A82: contig_536_297 | B82: Mobile elements | E82: Fanzor_B_nuclease | F82: - | G82: - | H82: - | I82: - | J82: - | K82: -
A83: contig_536_329 | B83: Unknown | C83: 1 | D83: 2CZV_D | E83: Ribonuclease P protein component 2; Ribonuclease, RNA binding protein, RNA recognition motif, Protein-protein complex, H | F83: 60.55 | G83: 24 | H83: 24.82 | I83: 3 | J83: 35 | K83: 120
C84: 2 | D84: 6AHU_H | E84: Ribonuclease P protein subunit p14; Ribonuclease P, RNA-protein complex, HYDROLASE-RNA complex; 3.66A {Homo sapiens} | F84: 46.57 | G84: 100 | H84: 21.11 | I84: 4.1 | J84: 54 | K84: 124
C85: 3 | D85: 6WQ2_a | E85: Structural protein MCP1; helical symmetry, archaeal virus, rod-like virus, structural protein, VIRUS;{Sulfolobus islandi | F85: 46.4 | G85: 34 | H85: 31.17 | I85: 2.3 | J85: 32 | K85: 204
C86: 4 | D86: Q914J4 | E86: Y036_SIFVH Uncharacterized protein 36 OS=Sulfolobus islandicus filamentous virus (isolate Iceland/Hveragerdi) OX=654908 | F86: 46.34 | G86: 34 | H86: 31.1 | I86: 2.3 | J86: 32 | K86: 204
C87: 5 | D87: 6K0B_A | E87: Ribonuclease P protein component 2; Ribonuclease P, RNA-protein complex, RNA BINDING PROTEIN-RNA complex; 4.3A {Methanoc | F87: 45.95 | G87: 51 | H87: 24.49 | I87: 2.8 | J87: 35 | K87: 134
A88: contig_536_343 | B88: Unknown | C88: 1 | D88: Q5UPW9 | E88: YL291_MIMIV Uncharacterized protein L291 OS=Acanthamoeba polyphaga mimivirus OX=212035 GN=MIMI_L291 PE=4 SV=1 | F88: 100 | G88: 1.4e-31 | H88: 278.07 | I88: 23.5 | J88: 194 | K88: 595
C89: 2 | D89: Q5UQ67 | E89: YR506_MIMIV Uncharacterized protein R506 OS=Acanthamoeba polyphaga mimivirus OX=212035 GN=MIMI_R506 PE=4 SV=1 | F89: 100 | G89: 6.4e-31 | H89: 263.91 | I89: 24.8 | J89: 193 | K89: 320
C90: 3 | D90: P18178 | E90: VP31_FRG3G Early 31 kDa protein OS=Frog virus 3 (isolate Goorha) OX=654924 PE=4 SV=1 | F90: 99.97 | G90: 1.2e-30 | H90: 258.31 | I90: 20.9 | J90: 198 | K90: 261
C91: 4 | D91: Q5UQ68 | E91: YR505_MIMIV Uncharacterized protein R505 OS=Acanthamoeba polyphaga mimivirus OX=212035 GN=MIMI_R505 PE=4 SV=1 | F91: 99.97 | G91: 4.3e-30 | H91: 266.69 | I91: 25.6 | J91: 264 | K91: 405
C92: 5 | D92: PF10927.12 | E92: ; DUF2738 ; Protein of unknown function (DUF2738) | F92: 99.97 | G92: 4.2e-30 | H92: 252.48 | I92: 20.4 | J92: 201 | K92: 244
A93: contig_536_348 | B93: Unknown | C93: 1 | D93: P52365 | E93: UL91_HHV7J Protein U62 OS=Human herpesvirus 7 (strain JI) OX=57278 GN=U62 PE=3 SV=1 | F93: 41.46 | G93: 55 | H93: 26 | I93: 2.5 | J93: 21 | K93: 75
C94: 2 | D94: 5MPO_C | E94: Molybdopterin synthase catalytic subunit; MOCS2A, MOCS2B, transferase; 2.43A {Homo sapiens} SCOP: d.41.5.0 | F94: 37.32 | G94: 110 | H94: 24.16 | I94: 3.5 | J94: 54 | K94: 154
C95: 3 | D95: 4AP8_D | E95: MOLYBDOPTERIN SYNTHASE CATALYTIC SUBUNIT; TRANSFERASE; HET: GOL; 2.78A {HOMO SAPIENS} SCOP: d.41.5.0 | F95: 35.4 | G95: 140 | H95: 22.54 | I95: 3.8 | J95: 54 | K95: 135
C96: 4 | D96: 1FM0_E | E96: MOLYBDOPTERIN CONVERTING FACTOR, SUBUNIT 2; MOLYBDENUM COFACTOR BIOSYNTHESIS, TRANSFERASE; 1.45A {Escherichia coli} SCOP | F96: 32.95 | G96: 170 | H96: 22.68 | I96: 3.9 | J96: 54 | K96: 150
C97: 5 | D97: 2Q5W_E | E97: Molybdopterin-converting factor subunit 2; MOLYBDOPTERIN, MOCO, MPT SYNTHASE, MOAD, MOAE, TRANSFERASE, MOLYBDENUM COFACT | F97: 31.17 | G97: 140 | H97: 23.12 | I97: 3.2 | J97: 54 | K97: 149
A98: contig_536_353 | B98: Structural | C98: 1 | D98: 6NCL_a6 | E98: P1; tape-measure protein, minor capsid proteins, zip protein, giant virus, VIRUS; 3.5A {Paramecium bursaria Chlorella vi | F98: 98.65 | G98: 3.9e-07 | H98: 77.8 | I98: 9.6 | J98: 48 | K98: 170
C99: 2 | D99: 8H2I_bG | E99: P1v1; giant virus, nucleocytoplasmic large DNA viruses (NCLDVs), viral assembly, Paramecium bursaria chlorella virus 1 ( | F99: 96.63 | G99: 0.049 | H99: 57.09 | I99: 11.7 | J99: 146 | K99: 530
C100: 3 | D100: Q5UQU9 | E100: YL356_MIMIV Uncharacterized protein L356 OS=Acanthamoeba polyphaga mimivirus OX=212035 GN=MIMI_L356 PE=4 SV=1 | F100: 89.64 | G100: 2.1 | H100: 47.12 | I100: 7.1 | J100: 61 | K100: 621
...

Sheet hhpred pre induction genes
A1: gene | B1: expr_cluster | C1: Nr | D1: Hit | E1: Name | F1: Probability | G1: E-value | H1: Score | I1: SS | J1: Aligned cols | K1: Target Length
A2: contig_536_20 | B2: pre_induc | C2: 1 | D2: 5O6B_A | E2: ATP-dependent DNA helicase PIF1; Helicase SF1 ssDNA ATP analog, HYDROLASE; HET: ALF, ADP; 2.029A {Saccharomyces cerevisi | F2: 92.69 | G2: 0.42 | H2: 42.11 | I2: 4.6 | J2: 111 | K2: 545
C3: 2 | D3: 7OTJ_A | E3: ATP-dependent DNA helicase PIF1; Helicase Pif1, HYDROLASE; HET: K, PO4, ALF, ADP; 2.58A {Candida albicans} | F3: 90.79 | G3: 0.41 | H3: 40.59 | I3: 2.4 | J3: 119 | K3: 518
C4: 3 | D4: Q9QSK3 | E4: VF030_IIV6 Uncharacterized protein 030L OS=Invertebrate iridescent virus 6 OX=176652 GN=IIV6-030L PE=3 SV=1 | F4: 80.6 | G4: 1.1 | H4: 39.04 | I4: 0 | J4: 119 | K4: 530
C5: 4 | D5: Q196V4 | E5: VF030_IIV3 Uncharacterized protein 106R OS=Invertebrate iridescent virus 3 OX=345201 GN=IIV3-106R PE=3 SV=1 | F5: 75.16 | G5: 3.3 | H5: 35.54 | I5: 1.2 | J5: 78 | K5: 473
C6: 5 | D6: 8BNS_C | E6: AAA ATPase; Helicase Thermophile, HYDROLASE; HET: ADP; 3.24A {Sulfurihydrogenibium sp. YO3AOP1} | F6: 63.24 | G6: 4.2 | H6: 35.24 | I6: -0.5 | J6: 22 | K6: 517
A7: contig_536_21 | B7: pre_induc | C7: 1 | D7: 8BNS_C | E7: AAA ATPase; Helicase Thermophile, HYDROLASE; HET: ADP; 3.24A {Sulfurihydrogenibium sp. YO3AOP1} | F7: 99.64 | G7: 1.4e-15 | H7: 125.26 | I7: 9 | J7: 230 | K7: 517
C8: 2 | D8: P03214 | E8: HELI_EBVB9 DNA replication helicase OS=Epstein-Barr virus (strain B95-8) OX=10377 GN=HELI PE=3 SV=1 | F8: 99.56 | G8: 4.9e-15 | H8: 135.82 | I8: 4.9 | J8: 232 | K8: 809
C9: 3 | D9: Q2HR89 | E9: HELI_HHV8P DNA replication helicase OS=Human herpesvirus 8 type P (isolate GK18) OX=868565 GN=HELI PE=3 SV=1 | F9: 99.54 | G9: 7.3e-15 | H9: 135.11 | I9: 4.6 | J9: 238 | K9: 788
C10: 4 | D10: Q01014 | E10: HELI_SHV21 DNA replication helicase OS=Saimiriine herpesvirus 2 (strain 11) OX=10383 GN=HELI PE=3 SV=1 | F10: 99.52 | G10: 2.9e-14 | H10: 130.7 | I10: 6.2 | J10: 244 | K10: 781
C11: 5 | D11: 8BNV_A | E11: AAA family ATPase; Helicase Thermophile, HYDROLASE; HET: GOL; 2.86A {Deferribacter desulfuricans} | F11: 99.5 | G11: 2.5e-13 | H11: 109.41 | I11: 9.1 | J11: 230 | K11: 510
A12: contig_536_22 | B12: pre_induc | C12: 1 | D12: 8BPO_s2 | E12: S phase cyclin A-associated protein in the endoplasmic reticulum; tubulin auto-regulation mRNA decay translation SCAPER, | F12: 94.41 | G12: 39 | H12: 45 | I12: 27.4 | J12: 193 | K12: 1411
C13: 2 | D13: 7C4J_C | E13: Transcription regulatory protein SNF6; SWI/SNF remodeling, Swi-Snf complex, nucleosome, DNA BINDING PROTEIN; 2.89A {Sacc | F13: 90.74 | G13: 6.8 | H13: 45.28 | I13: 12.2 | J13: 134 | K13: 332
C14: 3 | D14: 8J6S_K | E14: Chromatin assembly factor 1 subunit A; REPLICATION-DNA COMPLEX; 3.8A {Homo sapiens} | F14: 88.41 | G14: 100 | H14: 39.82 | I14: 20.6 | J14: 129 | K14: 956
C15: 4 | D15: PF11932.13 | E15: ; DUF3450 ; Protein of unknown function (DUF3450) | F15: 86.44 | G15: 15 | H15: 36.13 | I15: 9.9 | J15: 144 | K15: 240
C16: 5 | D16: 7UK1_B | E16: Splicing factor, proline- and glutamine-rich; Polypyridimine-binding splicing factor, 5'-polyuridine negative-sense (5'- | F16: 83.44 | G16: 21 | H16: 37.75 | I16: 10 | J16: 61 | K16: 412
A17: contig_536_23 | B17: pre_induc | C17: 1 | D17: 6R4L_A | E17: NPC intracellular cholesterol transporter 1-related protein 1; Vacuole, Ergosterol, LIPID TRANSPORT, membrane protein; H | F17: 21.08 | G17: 150 | H17: 29.39 | I17: 2.2 | J17: 26 | K17: 1198
A18: contig_536_41 | B18: pre_induc | C18: 1 | D18: PF22560.1 | E18: ; GMT-wHTH ; GMT-like wHTH domain | F18: 29.59 | G18: 170 | H18: 18.03 | I18: 2.8 | J18: 24 | K18: 85
C19: 2 | D19: 8GLV_As | E19: Flagellar outer dynein arm light chain 2; cilia, microtubule, dynein, MOTOR PROTEIN; HET: GDP, MG, GTP; 3.1A {Chlamydomo | F19: 28.02 | G19: 52 | H19: 22.23 | I19: 0.4 | J19: 75 | K19: 136
C20: 3 | D20: PF12119.13 | E20: ; DUF3581 ; Protein of unknown function (DUF3581) | F20: 21.34 | G20: 67 | H20: 27.72 | I20: 0 | J20: 9 | K20: 217
A21: contig_536_42 | B21: not DEG | C21: 1 | D21: 5KOL_A | E21: Uncharacterized protein; CinA, Competence-damaged protein, outer membrane biogenesis, structural genomics, CSGID, Center | F21: 31.15 | G21: 36 | H21: 21.42 | I21: 0.1 | J21: 15 | K21: 173
C22: 2 | D22: PF02059.20 | E22: ; IL3 ; Interleukin-3 | F22: 28.78 | G22: 75 | H22: 23.43 | I22: 1.3 | J22: 26 | K22: 112
C23: 3 | D23: PF10871.13 | E23: ; DUF2748 ; Protein of unknown function (DUF2748) | F23: 24.95 | G23: 91 | H23: 28.26 | I23: 1.4 | J23: 17 | K23: 433
C24: 4 | D24: 3VZ9_B | E24: Uncharacterized protein; RWD domain, kinetochore component, chromosome segregation, Ndc80 complex, CELL CYCLE; 1.03A {Ga | F24: 22.71 | G24: 210 | H24: 18.33 | I24: 2.4 | J24: 38 | K24: 106
C25: 5 | D25: 2L3O_A | E25: Interleukin 3; cytokine, Murine Interleukin-3; NMR {Mus musculus} SCOP: a.26.1.0 | F25: 20.56 | G25: 130 | H25: 22.73 | I25: 1.3 | J25: 26 | K25: 127
A26: contig_536_43 | B26: pre_induc | C26: 1 | D26: PF11027.13 | E26: ; DUF2615 ; Protein of unknown function (DUF2615) | F26: 32 | G26: 74 | H26: 24.79 | I26: 1.9 | J26: 30 | K26: 97
C27: 2 | D27: 3BCH_A | E27: 40S ribosomal protein SA; laminin receptor, p40 ribosomal protein, Acetylation, Cytoplasm, Phosphorylation, Polymorphism | F27: 30.53 | G27: 64 | H27: 26.47 | I27: 1.4 | J27: 31 | K27: 253
C28: 3 | D28: 8DU5_B | E28: Sialidase-1; sialic acid, sialidase, glycosidase, lysosome, HYDROLASE; HET: BMA, NAG, MAN, FUC; 3.5A {Mus musculus} | F28: 29.85 | G28: 62 | H28: 23.9 | I28: 1.1 | J28: 12 | K28: 378
C29: 4 | D29: 4N4G_A | E29: Zinc finger MYND domain-containing protein 11; tandem bromodomain-zinc finger-PWWP motif, histone H3.3-specific, TRANSCR | F29: 28.24 | G29: 93 | H29: 22.46 | I29: 1.7 | J29: 33 | K29: 252
C30: 5 | D30: PF21432.2 | E30: ; 56B_RHH ; 56B-like, Ribbon-helix-helix | F30: 28 | G30: 170 | H30: 15.46 | I30: 2.3 | J30: 22 | K30: 33
A31: contig_536_57 | B31: pre_induc | C31: 1 | D31: P90212 | E31: OPEP3_NPVOP OPEP-3 protein OS=Orgyia pseudotsugata multicapsid polyhedrosis virus OX=262177 GN=OPEP-3 PE=4 SV=1 | F31: 45.21 | G31: 18 | H31: 34.39 | I31: 0.5 | J31: 27 | K31: 285
C32: 2 | D32: 1GTF_K | E32: TRP RNA-BINDING ATTENUATION PROTEIN (TRAP); RNA BINDING PROTEIN-RNA COMPLEX, TRANSCRIPTION ATTENUATION, RNA-BINDING PROT | F32: 25.69 | G32: 85 | H32: 25.26 | I32: 1.3 | J32: 21 | K32: 74
C33: 3 | D33: 4J0W_A | E33: U3 small nucleolar RNA-interacting protein 2; Beta-Propeller, WD domain, RNA Binding protein, preribosome; 1.7A {Homo sa | F33: 25.6 | G33: 240 | H33: 20 | I33: 3.2 | J33: 75 | K33: 343
C34: 4 | D34: PF02081.20 | E34: ; TrpBP ; Tryptophan RNA-binding attenuator protein | F34: 23.16 | G34: 100 | H34: 24.54 | I34: 1.2 | J34: 21 | K34: 68
C35: 5 | D35: 8CM1_A | E35: Outer-membrane lipoprotein LolB; Localization of Lipoproteins, PROTEIN TRANSPORT; 1.46A {Vibrio cholerae} | F35: 22.83 | G35: 230 | H35: 21.73 | I35: 3 | J35: 30 | K35: 212
A36: contig_536_58 | B36: pre_induc | C36: 1 | D36: 3TUL_A | E36: Cell invasion protein sipB; translocator, type three secretion system, coiled-coil, virulence, CELL INVASION; HET: MSE; | F36: 75.35 | G36: 120 | H36: 28.59 | I36: 12.3 | J36: 139 | K36: 158
C37: 2 | D37: 7R5K_I3 | E37: Nucleoporin p58/p45; multiprotein complex, nucleocytoplasmic transport, TRANSPORT PROTEIN; 12.0A {Homo sapiens} | F37: 58 | G37: 680 | H37: 30.84 | I37: 16.3 | J37: 154 | K37: 599
C38: 3 | D38: 1TQQ_C | E38: Outer membrane protein tolC; Beta-barrel, alpha-barrel, transport protein; 2.75A {Escherichia coli} SCOP: f.5.1.1 | F38: 56 | G38: 320 | H38: 26.47 | I38: 16.9 | J38: 163 | K38: 471
C39: 4 | D39: 6U94_A | E39: RND efflux system, outer membrane lipoprotein, NodT family; outer membrane lipoprotein, NodT family, Structural Genomics | F39: 53.71 | G39: 520 | H39: 28.12 | I39: 13.9 | J39: 107 | K39: 600
C40: 5 | D40: 6U94_A | E40: RND efflux system, outer membrane lipoprotein, NodT family; outer membrane lipoprotein, NodT family, Structural Genomics | F40: 51.78 | G40: 550 | H40: 27.9 | I40: 13.9 | J40: 107 | K40: 600
A41: contig_536_70 | B41: pre_induc | C41: 1 | D41: PF14933.11 | E41: ; CEP19 ; CEP19-like protein | F41: 29.18 | G41: 130 | H41: 19.14 | I41: 2.3 | J41: 22 | K41: 150
C42: 2 | D42: PF10968.13 | E42: ; DUF2770 ; Protein of unknown function (DUF2770) | F42: 28.24 | G42: 27 | H42: 20.17 | I42: -0.7 | J42: 6 | K42: 36
C43: 3 | D43: 3LB9_A | E43: Endo-1,4-beta-xylanase; permutation, BcX, Glycosidase, Xylan degradation, HYDROLASE; 3.0A {Bacillus circulans} | F43: 25.12 | G43: 17 | H43: 22.9 | I43: -2.1 | J43: 21 | K43: 182
C44: 4 | D44: PF18704.6 | E44: ; Chromo_2 ; Chromatin organization modifier domain 2 | F44: 22.34 | G44: 110 | H44: 16.6 | I44: 0.9 | J44: 5 | K44: 58
A45: contig_536_71 | B45: pre_induc | C45: 1 | D45: 7VF2_B | E45: Zinc finger CCCH domain-containing protein 13; m6A-METTL associated complex, cryo-EM, WTAP, Virma., RNA BINDING PROTEIN; | F45: 51.43 | G45: 31 | H45: 40.7 | I45: 3.5 | J45: 184 | K45: 563
C46: 2 | D46: 7K3H_A | E46: Network hallucinated protein 0217; helical bundle, machine learning, DE NOVO PROTEIN; 3.0A {synthetic construct} | F46: 27.83 | G46: 260 | H46: 27.96 | I46: 5 | J46: 50 | K46: 121
C47: 3 | D47: 7VF2_B | E47: Zinc finger CCCH domain-containing protein 13; m6A-METTL associated complex, cryo-EM, WTAP, Virma., RNA BINDING PROTEIN; | F47: 22.11 | G47: 270 | H47: 33.68 | I47: 4.7 | J47: 126 | K47: 563
C48: 4 | D48: 1YKH_B | E48: RNA polymerase II holoenzyme component SRB7; GENE REGULATION; 3.0A {Saccharomyces cerevisiae} SCOP: a.252.1.1 | F48: 20.37 | G48: 720 | H48: 23.1 | I48: 6 | J48: 62 | K48: 132
A49: contig_536_74 | B49: pre_induc | C49: 1 | D49: 7Q5B_C | E49: Transposon Ty3-G Gag-Pol polyprotein; Transcription, RNA Pol III, Ty3 Retrotransposon, Intasome, DNA BINDING PROTEIN;{Sa | F49: 100 | G49: 4.3e-72 | H49: 590.12 | I49: 51.1 | J49: 912 | K49: 1547
C50: 2 | D50: P14350 | E50: POL_FOAMV Pro-Pol polyprotein OS=Human spumaretrovirus OX=11963 GN=pol PE=1 SV=2 | F50: 100 | G50: 2.1e-73 | H50: 580.22 | I50: 38 | J50: 917 | K50: 1143
C51: 3 | D51: O92815 | E51: POL_WDSV Gag-Pol polyprotein OS=Walleye dermal sarcoma virus OX=39720 GN=gag-pol PE=1 SV=2 | F51: 100 | G51: 1.1e-71 | H51: 607.14 | I51: 42.5 | J51: 888 | K51: 1752
C52: 4 | D52: P03355 | E52: POL_MLVMS Gag-Pol polyprotein OS=Moloney murine leukemia virus (isolate Shinnick) OX=928306 GN=gag-pol PE=1 SV=5 | F52: 100 | G52: 1.9e-69 | H52: 596.62 | I52: 40.1 | J52: 1058 | K52: 1738
C53: 5 | D53: P10273 | E53: POL_FLV Gag-Pol polyprotein OS=Feline leukemia virus OX=11768 GN=pol PE=3 SV=2 | F53: 100 | G53: 8.7e-69 | H53: 585.05 | I53: 37.3 | J53: 949 | K53: 1712
A54: contig_536_75 | B54: pre_induc | C54: 1 | D54: 6R23_B | E54: Transposon Ty3-I Gag-Pol polyprotein; Ty3, retrotransposon, retrovirus, capsid, Gag polyprotein, capsid-CTD, VIRUS LIKE | F54: 99.33 | G54: 7.6e-11 | H54: 84.59 | I54: 11.8 | J54: 144 | K54: 309
C55: 2 | D55: 6TAS_G | E55: Activity-regulated cytoskeleton associated protein 1; dArc, Gag, Virus, VLP, VIRUS LIKE PARTICLE; 2.75A {Drosophila mela | F55: 99.12 | G55: 4.5e-10 | H55: 79.56 | I55: 6.8 | J55: 141 | K55: 254
C56: 3 | D56: P03543 | E56: CAPSD_CAMVC Capsid protein OS=Cauliflower mosaic virus (strain CM-1841) OX=10644 GN=ORF IV PE=3 SV=1 | F56: 98.97 | G56: 1.6e-08 | H56: 92.62 | I56: 12.1 | J56: 128 | K56: 488
C57: 4 | D57: Q7TD09 | E57: CAPSD_CYLCV Capsid protein OS=Cestrum yellow leaf curling virus OX=175814 GN=ORF IV PE=3 SV=1 | F57: 98.89 | G57: 9.4e-08 | H57: 86.09 | I57: 14 | J57: 242 | K57: 501
C58: 5 | D58: P09519 | E58: CAPSD_FMVD Probable capsid protein OS=Figwort mosaic virus (strain DxS) OX=10650 GN=ORF IV PE=3 SV=1 | F58: 98.89 | G58: 7.3e-08 | H58: 90.14 | I58: 13.5 | J58: 249 | K58: 489
A59: contig_536_205 | B59: pre_induc | C59: 1 | D59: 7DWN_C | E59: Predicted DNA-binding transcriptional regulator; transcriptional regulators, tetramer, DNA BINDING PROTEIN; HET: MES; 2. | F59: 84.82 | G59: 1.7 | H59: 27.19 | I59: 2 | J59: 26 | K59: 293
C60: 2 | D60: 7DMW_A | E60: CcpC; CcpC, Complex, Bacillus amyloliquefaciens, Transcriptional regulator, citrate, TRANSCRIPTION; HET: FLC; 2.29A {Bac | F60: 81.27 | G60: 2.9 | H60: 25.7 | I60: 1.9 | J60: 26 | K60: 293
C61: 3 | D61: 2UYF_B | E61: REGULATORY PROTEIN; LTTR, LYSR, DNA-BINDING, TRANSCRIPTION, TRANSCRIPTION REGULATION, TRANSCRIPTIONAL REGULATOR; HET: SC | F61: 80.1 | G61: 3.1 | H61: 26.82 | I61: 1.8 | J61: 26 | K61: 307
C62: 4 | D62: 7L4S_B | E62: Transcriptional regulator of oxidative stress OxyR; OxyR, DNA BINDING PROTEIN; 2.4A {Shewanella oneidensis} | F62: 76.86 | G62: 5 | H62: 25.23 | I62: 2 | J62: 26 | K62: 304
C63: 5 | D63: 3FZV_C | E63: Probable transcriptional regulator; LysR, transcriptional regulator, structural genomics, PSI-2, Protein Structure Initi | F63: 76.56 | G63: 5.4 | H63: 24.99 | I63: 2.1 | J63: 26 | K63: 306
A64: contig_536_227 | B64: pre_induc | C64: 1 | D64: 2CQ7_A | E64: Cysteine-rich secretory protein-2; CRISP, CRISP-2, TPX-1, CRD, cystein-rich domain, structural genomics, NPPSFA, Nationa | F64: 59.6 | G64: 9.8 | H64: 18.68 | I64: 0.7 | J64: 17 | K64: 49
C65: 2 | D65: 1YF3_A | E65: DNA adenine methylase; T4DAM, METHYLTRANSFERASE, DNA, Transferase-DNA COMPLEX; HET: GOL, SAH; 2.29A {Enterobacteria phag | F65: 56.38 | G65: 7 | H65: 24.16 | I65: -0.2 | J65: 12 | K65: 259
C66: 3 | D66: P12427 | E66: DMA_BPT2 DNA adenine methylase OS=Enterobacteria phage T2 OX=10664 GN=DAM PE=3 SV=1 | F66: 51.46 | G66: 8.8 | H66: 23.51 | I66: -0.3 | J66: 12 | K66: 259
C67: 4 | D67: 2DPM_A | E67: PROTEIN (ADENINE-SPECIFIC METHYLTRANSFERASE DPNII 1); DNA ADENINE METHYLTRANSFERASE, METHYLTRANSFERASE, METHYLASE, DNA M | F67: 49.59 | G67: 14 | H67: 22.95 | I67: 0.4 | J67: 18 | K67: 284
C68: 5 | D68: PF03884.18 | E68: ; YacG ; DNA gyrase inhibitor YacG | F68: 47.34 | G68: 13 | H68: 21.23 | I68: -0.1 | J68: 7 | K68: 52
C69: 6 | D69: 2G1P_A | E69: DNA adenine methylase; Dam methylation GATC recognition Base flipping Bacterial virulence factor, TRANSFERASE-DNA COMPLE | F69: 44.53 | G69: 15 | H69: 23 | I69: -0.1 | J69: 12 | K69: 278
A70: contig_536_228 | B70: pre_induc | C70: 1 | D70: PF19001.4 | E70: ; DUF5730 ; Family of unknown function (DUF5730) | F70: 64.96 | G70: 14 | H70: 31.7 | I70: 2.9 | J70: 24 | K70: 184
C71: 2 | D71: PF12734.11 | E71: ; CYSTM ; Cysteine-rich TM module stress tolerance | F71: 54.42 | G71: 21 | H71: 20.58 | I71: 1.5 | J71: 28 | K71: 39
C72: 3 | D72: P09731 | E72: US07_HCMVA Unique short US7 glycoprotein OS=Human cytomegalovirus (strain AD169) OX=10360 GN=US7 PE=3 SV=1 | F72: 44.02 | G72: 52 | H72: 29.31 | I72: 3 | J72: 54 | K72: 225
C73: 4 | D73: 1PEX_A | E73: COLLAGENASE-3; C-TERMINAL HEMOPEXIN-LIKE DOMAIN OF MATRIX-METALLOPROTEINASE, METALLOPROTEASE; 2.7A {Homo sapiens} SCOP: | F73: 36.35 | G73: 57 | H73: 21.24 | I73: 1.6 | J73: 17 | K73: 207
C74: 5 | D74: PF18539.5 | E74: ; DUF5625 ; Domain of unknown function (DUF5625) | F74: 34.75 | G74: 53 | H74: 22.94 | I74: 1.4 | J74: 14 | K74: 134
A75: contig_536_229 | B75: pre_induc | C75: 1 | D75: 7CY6_A | E75: Maltodextrin-binding protein,5-methylcytosine-modifying enzyme 1; TET, Vitamin C, dioxygenase, 5gmC, DNA modification, 2 | F75: 37.44 | G75: 32 | H75: 26.8 | I75: 0.7 | J75: 34 | K75: 917
C76: 2 | D76: PF08074.15 | E76: ; CHDCT2 ; CHDCT2 (NUC038) domain | F76: 29.27 | G76: 80 | H76: 19.49 | I76: 1.4 | J76: 13 | K76: 142
C77: 3 | D77: 6Q67_B | E77: 3A; complex, aichivirus, picornavirus, VIRAL PROTEIN; HET: BGC; 2.249A {Sus scrofa} | F77: 20.92 | G77: 110 | H77: 17.38 | I77: 0.8 | J77: 13 | K77: 34
C78: 4 | D78: PF07150.15 | E78: ; DUF1390 ; Protein of unknown function (DUF1390) | F78: 20.57 | G78: 160 | H78: 21.75 | I78: 1.7 | J78: 32 | K78: 220
A79: contig_536_230 | B79: pre_induc | C79: 1 | D79: PF08591.14 | E79: ; RNR_inhib ; Ribonucleotide reductase inhibitor | F79: 35.41 | G79: 26 | H79: 25.16 | I79: -0.1 | J79: 14 | K79: 111
C80: 2 | D80: 6T6E_A | E80: Pol protein; HIV, integrase, PNL4.3, VIRAL PROTEIN; 1.302A {Human immunodeficiency virus 1} SCOP: b.34.7.1, l.1.1.1 | F80: 29.84 | G80: 120 | H80: 20.32 | I80: 2.3 | J80: 27 | K80: 59
C81: 3 | D81: PF11896.12 | E81: ; GlgE_dom_N_S ; Alpha-1,4-glucan:maltose-1-phosphate maltosyltransferase, domain N/S | F81: 22.68 | G81: 150 | H81: 22.21 | I81: 2 | J81: 24 | K81: 195
C82: 4 | D82: PF03871.18 | E82: ; RNA_pol_Rpb5_N ; RNA polymerase Rpb5, N-terminal domain | F82: 20.92 | G82: 150 | H82: 17.18 | I82: 1.4 | J82: 19 | K82: 85
A83: contig_536_231 | B83: pre_induc | C83: 1 | D83: 7CY6_A | E83: Maltodextrin-binding protein,5-methylcytosine-modifying enzyme 1; TET, Vitamin C, dioxygenase, 5gmC, DNA modification, 2 | F83: 99.97 | G83: 2.1e-31 | H83: 249.76 | I83: 13.3 | J83: 106 | K83: 917
C84: 2 | D84: 8JKK_G | E84: 2OGFeDO JBP1/TET oxygenase domain-containing protein; DNA demethylase, DNA BINDING PROTEIN, DNA BINDING PROTEIN-DNA comp | F84: 99.15 | G84: 3e-10 | H84: 98.68 | I84: 8.3 | J84: 78 | K84: 415
C85: 3 | D85: 5CG9_A | E85: Tet-like dioxygenase; dioxygenase, 5-methylcytosine, NgTET1, OXIDOREDUCTASE-DNA complex; HET: 5CM, SO4, AKG; 2.693A {Nae | F85: 99.04 | G85: 8.3e-10 | H85: 88.93 | I85: 6.3 | J85: 78 | K85: 267
C86: 4 | D86: 4LT5_A | E86: Naegleria Tet-like dioxygenase; 5-METHYLCYTOSINE, DIOXYGENASE-DNA COMPLEX, OXIDOREDUCTASE-DNA complex; HET: 5CM, SO4, OG | F86: 99 | G86: 1.9e-09 | H86: 90.61 | I86: 6.8 | J86: 76 | K86: 327
C87: 5 | D87: 6T8M_A | E87: Prolyl 4-hydroxylase subunit alpha; Prolyl Hydroxylase, Oxygen Sensing, 2-oxoglutarate and iron dependent oxygenase, OXI | F87: 97.77 | G87: 0.0003 | H87: 51.61 | I87: 7.3 | J87: 73 | K87: 227
C88: 6 | D88: 6NMQ_A | E88: Egl nine homolog 1; PHD2, hypoxia-inducible factor prolyl hydroxylase, iron-containing enzyme, cinnoline, OXIDOREDUCTASE | F88: 97.45 | G88: 0.0013 | H88: 47.16 | I88: 6.6 | J88: 73 | K88: 213
C89: 7 | D89: 5V1B_A | E89: Egl nine homolog 2; HIF Prolylhydroxylase Domain-1, Inhibitor, momodentate binding, Oxidoreductase-Inhibitor complex; HE | F89: 97.26 | G89: 0.0053 | H89: 45.77 | I89: 8.2 | J89: 81 | K89: 240
C90: 8 | D90: SM00702 | E90: P4Hc; Prolyl 4-hydroxylase alpha subunit homologues. | F90: 97.18 | G90: 0.0041 | H90: 45.49 | I90: 6.9 | J90: 70 | K90: 165
C91: 9 | D91: 6EY1_A | E91: HIF prolyl hydroxylase; Prolyl hydroxylase, oxygenase, oxidoreductase, oxygen sensing, hypoxia inducible factor; HET: AC | F91: 97.1 | G91: 0.0075 | H91: 47.62 | I91: 8 | J91: 82 | K91: 257
C92: 10 | D92: 7Q5V_A | E92: Egl nine homolog 1; PHD2, HIF-2Alpha, Complex, OXIDOREDUCTASE, Hypoxia; HET: GOL, PEG, OGA, FMT; 1.17A {Homo sapiens} | F92: 97.05 | G92: 0.0077 | H92: 44.22 | I92: 7.2 | J92: 79 | K92: 233
C93: 11 | D93: 6IUQ_A | E93: Prolyl 4-hydroxylase; hydroxylase, iron, DSBH core fold, OXIDOREDUCTASE; HET: MSE; 2.348A {Phytophthora capsici LT1534} | F93: 97.02 | G93: 0.0077 | H93: 50.67 | I93: 7.9 | J93: 73 | K93: 345
C94: 12 | D94: 4J25_D | E94: Putative uncharacterized protein; 2-oxoglutarate oxygenase, oxygen sensing, double-stranded beta helix, jellyroll fold, | F94: 96.93 | G94: 0.011 | H94: 43.41 | I94: 7 | J94: 74 | K94: 229
C95: 13 | D95: 7ZSC_A | E95: Prolyl 4-hydroxylase subunit alpha-2; Collagen synthesis, PDI, DSBH fold, thioredoxin, dioxygenase, HYDROLASE; HET: SO4; | F95: 96.79 | G95: 0.007 | H95: 47.28 | I95: 5.5 | J95: 71 | K95: 262
... C100: 18 | D100: 6AX7_A | E100: Procollagen lysyl hydroxylase and glycosyltransferase; double-stranded ?-helix, dimer, dioxygenase, collagen, OXIDOREDUC | F100: 96.17 | G100: 0.046 | H100: 42.6 | I100: 6.5 | J100: 71 | K100: 235
A101: contig_536_232 | B101: pre_induc | C101: 1 | D101: 1YA5_T | E101: TELETHONIN; TELETHONIN T-CAP Ig-LIKE DOMAINS Z1 Z2 TITIN, STRUCTURAL PROTEIN; HET: SO4; 2.445A {Homo sapiens} | F101: 66.25 | G101: 14 | H101: 23.57 | I101: 2.3 | J101: 18 | K101: 90
C102: 2 | D102: PF20086.3 | E102: ; DUF6478 ; Family of unknown function (DUF6478) | F102: 55.27 | G102: 27 | H102: 25.38 | I102: 2.5 | J102: 32 | K102: 253
C103: 3 | D103: 2V33_B | E103: E1 ENVELOPE GLYCOPROTEIN; GLYCOPROTEIN, TRANSMEMBRANE, VIRAL PROTEIN; 1.55A {SEMLIKI FOREST VIRUS} SCOP: b.1.18.4 | F103: 48.5 | G103: 34 | H103: 22.61 | I103: 1.9 | J103: 15 | K103: 91
C104: 4 | D104: 3G7M_A | E104: Xylanase inhibitor TL-XI; beta-sheets, Xylan degradation, HYDROLASE INHIBITOR; HET: GOL; 2.91A {Triticum aestivum} | F104: 48.47 | G104: 36 | H104: 19.96 | I104: 1.9 | J104: 15 | K104: 151
...

Sheet hhpred chr_16
A1: gene | B1: Nr | C1: Hit | D1: Name | E1: Probability | F1: E-value | G1: Score | H1: SS | I1: Aligned cols | J1: Target Length
A2: contig_437_1 | B2: 1 | C2: 8BPO_s2 | D2: S phase cyclin A-associated protein in the endoplasmic reticulum; tubulin auto-regulation mRNA decay translation SCAPER, | E2: 90.46 | F2: 110 | G2: 40.52 | H2: 27.6 | I2: 193 | J2: 1411
B3: 2 | C3: 7C4J_C | D3: Transcription regulatory protein SNF6; SWI/SNF remodeling, Swi-Snf complex, nucleosome, DNA BINDING PROTEIN; 2.89A {Sacc | E3: 89.26 | F3: 11 | G3: 42.98 | H3: 12.2 | I3: 134 | J3: 332
B4: 3 | C4: PF11932.13 | D4: ; DUF3450 ; Protein of unknown function (DUF3450) | E4: 86.07 | F4: 18 | G4: 34.89 | H4: 10.1 | I4: 144 | J4: 240
B5: 4 | C5: 7NRC_A | D5: GCN1; Ribosome, Disome, GCN1, Translation, GAAC, ISR, Rbg2, Gir2; HET: 5CT; 3.9A {Saccharomyces cerevisiae S288C} | E5: 82.97 | F5: 11 | G5: 48.5 | H5: 8.9 | I5: 198 | J5: 1209
B6: 5 | C6: 8PPL_Iu | D6: Eukaryotic translation initiation factor 3 subunit A; Nsp1, MERS, SARS, SARS-CoV2, ribosome, 40S ribosomal subunit, tran | E6: 80.7 | F6: 340 | G6: 36.75 | H6: 22.1 | I6: 318 | J6: 1382
A7: contig_437_2 | B7: 1 | C7: SM00547 | D7: ZnF_RBZ; Zinc finger domain | E7: 78.85 | F7: 2.7 | G7: 19.21 | H7: 1 | I7: 25 | J7: 25
B8: 2 | C8: 6U75_B | D8: E3 SUMO-protein ligase SIZ2; SUMO, SIGNAL TRANSDUCTION, REPLICATION, RING E3, PIAS, SIZ, UBIQUITIN, UBC9, LIGASE, METAL- | E8: 50.75 | F8: 10 | G8: 31.4 | H8: -0.2 | I8: 35 | J8: 269
B9: 3 | C9: PF16988.10 | D9: ; Vps36-NZF-N ; Vacuolar protein sorting 36 NZF-N zinc-finger domain | E9: 38.45 | F9: 30 | G9: 25.16 | H9: 0.6 | I9: 14 | J9: 68
B10: 4 | C10: PF19134.5 | D10: ; DUF5817 ; Domain of unknown function (DUF5817) | E10: 35.85 | F10: 63 | G10: 18.24 | H10: 1.6 | I10: 51 | J10: 57
B11: 5 | C11: SM00734 | D11: ZnF_Rad18; Rad18-like CCHC zinc finger | E11: 34.41 | F11: 26 | G11: 19.93 | H11: -0.1 | I11: 9 | J11: 24
A12: contig_437_3 | C12: GVOGm0054 | D12: PolB
A13: contig_437_4 | B13: 1 | C13: 3WX7_A | D13: Chitin oligosaccharide deacetylase; oligosaccharide deacetylace, carbohydrate-binding, HYDROLASE; HET: GOL; 1.349A {Vibr | E13: 90.88 | F13: 0.51 | G13: 62.28 | H13: 4.6 | I13: 91 | J13: 402
B14: 2 | C14: 3WX7_A | D14: Chitin oligosaccharide deacetylase; oligosaccharide deacetylace, carbohydrate-binding, HYDROLASE; HET: GOL; 1.349A {Vibr | E14: 86.04 | F14: 2.5 | G14: 56.32 | H14: 6.1 | I14: 91 | J14: 402
B15: 3 | C15: 3WX7_A | D15: Chitin oligosaccharide deacetylase; oligosaccharide deacetylace, carbohydrate-binding, HYDROLASE; HET: GOL; 1.349A {Vibr | E15: 85.41 | F15: 4.6 | G15: 54.11 | H15: 7.9 | I15: 87 | J15: 402
B16: 4 | C16: 3WX7_A | D16: Chitin oligosaccharide deacetylase; oligosaccharide deacetylace, carbohydrate-binding, HYDROLASE; HET: GOL; 1.349A {Vibr | E16: 82.13 | F16: 5.2 | G16: 53.63 | H16: 6.5 | I16: 91 | J16: 402
B17: 5 | C17: 7R5K_V0 | D17: Nuclear pore complex protein Nup214; multiprotein complex, nucleocytoplasmic transport, TRANSPORT PROTEIN; 12.0A {Homo s | E17: 71.99 | F17: 21 | G17: 57.05 | H17: 8.6 | I17: 89 | J17: 2090
A18: contig_437_5 | B18: 1 | C18: 3WX7_A | D18: Chitin oligosaccharide deacetylase; oligosaccharide deacetylace, carbohydrate-binding, HYDROLASE; HET: GOL; 1.349A {Vibr | E18: 96.48 | F18: 0.023 | G18: 70.13 | H18: 9.9 | I18: 91 | J18: 402
B19: 2 | C19: 3WX7_A | D19: Chitin oligosaccharide deacetylase; oligosaccharide deacetylace, carbohydrate-binding, HYDROLASE; HET: GOL; 1.349A {Vibr | E19: 95.97 | F19: 0.053 | G19: 67.08 | H19: 9.4 | I19: 84 | J19: 402
B20: 3 | C20: 3WX7_A | D20: Chitin oligosaccharide deacetylase; oligosaccharide deacetylace, carbohydrate-binding, HYDROLASE; HET: GOL; 1.349A {Vibr | E20: 95.69 | F20: 0.092 | G20: 65.09 | H20: 9.9 | I20: 93 | J20: 402
B21: 4 | C21: 3WX7_A | D21: Chitin oligosaccharide deacetylase; oligosaccharide deacetylace, carbohydrate-binding, HYDROLASE; HET: GOL; 1.349A {Vibr | E21: 95.65 | F21: 0.096 | G21: 64.96 | H21: 9.8 | I21: 101 | J21: 402
B22: 5 | C22: SM00495 | D22: ChtBD3; Chitin-binding domain type 3 | E22: 90.8 | F22: 1.2 | G22: 36.78 | H22: 5.1 | I22: 40 | J22: 41
A23: contig_437_6 | B23: 1 | C23: 5LW3_A | D23: Poly(beta-D-mannuronate) C5 epimerase 6; C-5 Epimerase, isomerase; HET: B3P; 1.19A {Azotobacter vinelandii} | E23: 99.77 | F23: 6.2e-16 | G23: 184.02 | H23: 33.9 | I23: 311 | J23: 387
B24: 2 | C24: 3ZPP_A | D24: CELL WALL SURFACE ANCHOR FAMILY PROTEIN; CELL ADHESION, PFBA, SURFACE ADHESIN, SP1833, MSCRAMM; 2.28A {STREPTOCOCCUS PNE | E24: 99.73 | F24: 8.2e-15 | G24: 177.99 | H24: 35.7 | I24: 317 | J24: 443
B25: 3 | C25: 7CHU_C | D25: Putative pectin lyase; Tailspike protein, Thermophilic bacteriophage, CELL INVASION; 2.008A {Geobacillus virus E2} | E25: 99.68 | F25: 1.4e-13 | G25: 174.87 | H25: 37.9 | I25: 295 | J25: 519
B26: 4 | C26: 5ZRU_C | D26: Alpha-1,3-glucanase; Agl-KA GH87, HYDROLASE; HET: CA, SO4, PE5; 1.833A {Bacillus circulans} | E26: 99.68 | F26: 1.2e-13 | G26: 179.43 | H26: 37.6 | I26: 330 | J26: 578
B27: 5 | C27: P07537 | D27: FIB12_BPPZA Preneck appendage protein OS=Bacillus phage PZA OX=10757 GN=12 PE=3 SV=1 | E27: 99.67 | F27: 1.1e-13 | G27: 189.37 | H27: 38.5 | I27: 320 | J27: 854
A28: contig_437_7 | B28: 1 | C28: PF14779.11 | D28: ; BBS1 ; Ciliary BBSome complex subunit 1 | E28: 52.25 | F28: 72 | G28: 25.4 | H28: 4.2 | I28: 25 | J28: 256
B29: 2 | C29: 6LJ9_B | D29: Cysteine protease S273R; HYDROLASE; HET: MSE; 2.307A {African swine fever virus pig/Kenya/KEN-50/1950} | E29: 46.42 | F29: 170 | G29: 21.64 | H29: 5 | I29: 31 | J29: 281
B30: 3 | C30: PF15702.10 | D30: ; HPS6 ; Hermansky-Pudlak syndrome 6 protein N-terminal domain | E30: 44.64 | F30: 110 | G30: 25.94 | H30: 4.2 | I30: 36 | J30: 379
B31: 4 | C31: 7FIK_Y | D31: Nucleoporin Nup88A; CR, NPC, nucleoporin, Nup358, Nup93, Y complex, STRUCTURAL PROTEIN; 3.7A {Xenopus laevis} | E31: 40.86 | F31: 100 | G31: 26.47 | H31: 3.6 | I31: 34 | J31: 728
B32: 5 | C32: 2XET_A | D32: F1 CAPSULE-ANCHORING PROTEIN; TRANSPORT PROTEIN; HET: SO4; 1.6A {YERSINIA PESTIS} | E32: 40.75 | F32: 120 | G32: 17.52 | H32: 3 | I32: 27 | J32: 89
A33: contig_437_8 | B33: 1 | C33: P69549 | D33: J_BPPHK DNA-binding protein J OS=Enterobacteria phage phiK OX=10848 GN=J PE=3 SV=1 | E33: 28.65 | F33: 72 | G33: 20.22 | H33: 1.1 | I33: 9 | J33: 24
B34: 2 | C34: PF10593.14 | D34: ; Z1 ; Z1 domain | E34: 28.38 | F34: 58 | G34: 25.56 | H34: 0.8 | I34: 13 | J34: 228
B35: 3 | C35: PF19901.4 | D35: ; DUF6374 ; Family of unknown function (DUF6374) | E35: 26.14 | F35: 200 | G35: 21.05 | H35: 3 | I35: 26 | J35: 59
B36: 4 | C36: 6I1I_A | D36: Peptidoglycan D,D-transpeptidase FtsI,Peptidoglycan D,D-transpeptidase FtsI; penicillin-binding protein, peptidoglycan, | E36: 25.36 | F36: 130 | G36: 23.09 | H36: 2.1 | I36: 31 | J36: 348
B37: 5 | C37: PF21026.2 | D37: ; SLFN_GTPase-like ; Schlafen, GTPase-like domain | E37: 24.09 | F37: 110 | G37: 23.45 | H37: 1.6 | I37: 19 | J37: 139
A38: contig_437_9 | C38: GVOGm0054 | D38: PolB
A39: contig_437_10 | B39: 1 | C39: 6JSX_A | D39: Flagellar biosynthesis protein FlaG; Helicobacter pylori, flagella, BIOSYNTHETIC PROTEIN; 2.7A {Helicobacter pylori} | E39: 29.31 | F39: 210 | G39: 20.45 | H39: 3.6 | I39: 36 | J39: 73
B40: 2 | C40: PF17684.6 | D40: ; SCAB-PH ; PH domain of plant-specific actin-binding protein | E40: 26.38 | F40: 42 | G40: 29.06 | H40: -0.3 | I40: 11 | J40: 108
B41: 3 | C41: PF20556.3 | D41: ; DUF6768 ; Family of unknown function (DUF6768) | E41: 24.95 | F41: 20 | G41: 29.39 | H41: -2.3 | I41: 55 | J41: 123
B42: 4 | C42: 2X9Q_A | D42: CYCLODIPEPTIDE SYNTHETASE; LIGASE; HET: MSE; 2.02A {MYCOBACTERIUM TUBERCULOSIS} | E42: 22.79 | F42: 950 | G42: 22.66 | H42: 7.3 | I42: 103 | J42: 289
B43: 5 | C43: C1BEG3 | D43: UL74A_HCMVM Uncharacterized protein UL74A OS=Human cytomegalovirus (strain Merlin) OX=295027 GN=UL74A PE=4 SV=2 | E43: 22.61 | F43: 47 | G43: 27.5 | H43: -0.6 | I43: 22 | J43: 70
A44: contig_437_11 | B44: 1 | C44: 4JH2_B | D44: Metallothiol transferase FosB; Bacillithiol-S-Transferase, Transferase; HET: SO4; 1.27A {Bacillus cereus} SCOP: d.32.1.0 | E44: 34.14 | F44: 120 | G44: 19.08 | H44: 2.6 | I44: 38 | J44: 138
B45: 2 | C45: 4KYX_B | D45: ADP-ribose pyrophosphatase MutT; ADP-ribose pyrophosphatase MutT, MutT, Structural Genomics, Seattle Structural Genomics | E45: 33.53 | F45: 220 | G45: 17.95 | H45: 3.8 | I45: 60 | J45: 149
A46: contig_437_27 | B46: 1 | C46: SM00547 | D46: ZnF_RBZ; Zinc finger domain | E46: 78.85 | F46: 2.7 | G46: 19.21 | H46: 1 | I46: 25 | J46: 25
B47: 2 | C47: 6U75_B | D47: E3 SUMO-protein ligase SIZ2; SUMO, SIGNAL TRANSDUCTION, REPLICATION, RING E3, PIAS, SIZ, UBIQUITIN, UBC9, LIGASE, METAL- | E47: 50.75 | F47: 10 | G47: 31.4 | H47: -0.2 | I47: 35 | J47: 269
B48: 3 | C48: PF16988.10 | D48: ; Vps36-NZF-N ; Vacuolar protein sorting 36 NZF-N zinc-finger domain | E48: 38.45 | F48: 30 | G48: 25.16 | H48: 0.6 | I48: 14 | J48: 68
B49: 4 | C49: PF19134.5 | D49: ; DUF5817 ; Domain of unknown function (DUF5817) | E49: 35.85 | F49: 63 | G49: 18.24 | H49: 1.6 | I49: 51 | J49: 57
B50: 5 | C50: SM00734 | D50: ZnF_Rad18; Rad18-like CCHC zinc finger | E50: 34.41 | F50: 26 | G50: 19.93 | H50: -0.1 | I50: 9 | J50: 24
A51: contig_437_28 | B51: 1 | C51: 8BPO_s2 | D51: S phase cyclin A-associated protein in the endoplasmic reticulum; tubulin auto-regulation mRNA decay translation SCAPER, | E51: 94.94 | F51: 25 | G51: 45.28 | H51: 29.1 | I51: 199 | J51: 1411
B52: 2 | C52: 7C4J_C | D52: Transcription regulatory protein SNF6; SWI/SNF remodeling, Swi-Snf complex, nucleosome, DNA BINDING PROTEIN; 2.89A {Sacc | E52: 90.73 | F52: 8.1 | G52: 43.47 | H52: 12.5 | I52: 134 | J52: 332
B53: 3 | C53: 7UK1_B | D53: Splicing factor, proline- and glutamine-rich; Polypyridimine-binding splicing factor, 5'-polyuridine negative-sense (5'- | E53: 87.68 | F53: 19 | G53: 36.86 | H53: 11.6 | I53: 69 | J53: 412
B54: 4 | C54: 8J6S_K | D54: Chromatin assembly factor 1 subunit A; REPLICATION-DNA COMPLEX; 3.8A {Homo sapiens} | E54: 84.35 | F54: 200 | G54: 36.53 | H54: 20.6 | I54: 130 | J54: 956
B55: 5 | C55: 7UIO_Bb | D55: Mediator of RNA polymerase II transcription subunit 2; Divergent transcription, Mediator, RNA Polymerase II, PIC, Pre-In | E55: 84.1 | F55: 20 | G55: 41.92 | H55: 10.9 | I55: 72 | J55: 431

Sheet Chlamy_genes
A1: transcript | B1: Chlamy_cds_homolog | C1: gene_name | D1: MeanRPKM_cf20 | E1: MeanCounts_cf20 | F1: gene_start | G1: gene_end | H1: evalue | I1: bitscore | J1: percid | K1: alignment_length | L1: cds_length | M1: alignment_coverage | N1: chromosome | O1: feature | P1: chlamy_annotation | Q1: arabi_annotation | R1: rice_annotation
A2: contig_536:2003808-2691226_15 | B2: Cre15.g635717_4532.1 | D2: 53.53054 | E2: 100.7 | F2: 441385 | G2: 441675 | H2: 1.5e-132 | I2: 430 | J2: 96.89 | K2: 289 | L2: 291 | M2: 0.99312715 | N2: chromosome_15 | O2: gene
A3: contig_536:2003808-2691226_17 | B3: Cre07.g800828_4532.1 | D3: 642.21406 | E3: 2112.5 | F3: 4293450 | G3: 4293797 | H3: 6.8e-145 | I3: 503 | J3: 94.51 | K3: 364 | L3: 348 | M3: 1.045977 | N3: chromosome_07 | O3: gene
A4: contig_536:2003808-2691226_2 | B4: Cre11.g801258_4532.1 | D4: 1.4216146 | E4: 11.8 | F4: 1463001 | G4: 1463367 | H4: 4.6e-10 | I4: 68 | J4: 84.51 | K4: 71 | L4: 135 | M4: 0.52592593 | N4: chromosome_11 | O4: gene
A5: contig_536:2003808-2691226_335 | B5: Cre17.g712700_4532.1 | D5: 0.72841735 | E5: 10.6 | F5: 2207648 | G5: 2208487 | H5: 1.2e-205 | I5: 718 | J5: 84.58 | K5: 655 | L5: 678 | M5: 0.9660767 | N5: chromosome_17 | O5: gene | P5: putative transposase
A6: contig_536:2003808-2691226_339 | B6: Cre17.g712700_4532.1 | D6: 1.0372611 | E6: 15 | F6: 2207648 | G6: 2208487 | H6: 1.4e-206 | I6: 721 | J6: 84.73 | K6: 655 | L6: 678 | M6: 0.9660767 | N6: chromosome_17 | O6: gene | P6: putative transposase
A7: contig_536:2003808-2691226_4 | B7: Cre01.g800142_4532.1 | D7: 239.83192 | E7: 957.7 | F7: 7819664 | G7: 7819915 | H7: 9.2e-44 | I7: 179 | J7: 84.39 | K7: 173 | L7: 252 | M7: 0.68650794 | N7: chromosome_01 | O7: gene
A8: contig_536:2003808-2691226_409 | B8: Cre17.g712700_4532.1 | D8: 0.79540135 | E8: 11.6 | F8: 2207648 | G8: 2208487 | H8: 1.2e-205 | I8: 718 | J8: 84.58 | K8: 655 | L8: 678 | M8: 0.9660767 | N8: chromosome_17 | O8: gene | P8: putative transposase
A9: contig_536:2003808-2691226_55 | B9: Cre10.g439950_4532.5 | D9: 13.151889 | E9: 59.2 | F9: 2924609 | G9: 2933461 | H9: 6e-122 | I9: 436 | J9: 85.25 | K9: 400 | L9: 690 | M9: 0.57971014 | N9: chromosome_10 | O9: gene | P9: (1 of 546) 2.7.11.1 - Non-specific serine/threonine protein kinase / Threonine-specific protein kinase
A10: contig_536:2003808-2691226_606 | B10: Cre07.g800766_4532.1 | D10: 2.3671396 | E10: 4.2 | F10: 96415 | G10: 97077 | H10: 1.5e-129 | I10: 414 | J10: 100 | K10: 261 | L10: 516 | M10: 0.50581395 | N10: chromosome_07 | O10: gene
A11: contig_536:2003808-2691226_608 | B11: Cre15.g801740_4532.1 | D11: 1782.6834 | E11: 8907.5 | F11: 1658744 | G11: 1661920 | H11: 5.4e-232 | I11: 783 | J11: 87.29 | K11: 700 | L11: 1398 | M11: 0.50071531 | N11: chromosome_15 | O11: gene
A12: contig_536:2003808-2691226_627 | B12: Cre01.g800142_4532.1 | D12: 598.88919 | E12: 1200.1 | F12: 7819664 | G12: 7819915 | H12: 2.8e-50 | I12: 198 | J12: 90.79 | K12: 152 | L12: 252 | M12: 0.6031746 | N12: chromosome_01 | O12: gene
A13: contig_536:2003808-2691226_628 | B13: Cre14.g801655_4532.1 | D13: 852.56334 | E13: 3308.6 | F13: 3423341 | G13: 3423772 | H13: 1.5e-95 | I13: 349 | J13: 88.73 | K13: 284 | L13: 432 | M13: 0.65740741 | N13: chromosome_14 | O13: gene
A14: contig_536:2003808-2691226_630 | B14: Cre01.g800147_4532.1 | D14: 0.64023722 | E14: 2.8 | F14: 8221836 | G14: 8222762 | H14: 1.8e-252 | I14: 825 | J14: 97.62 | K14: 547 | L14: 927 | M14: 0.59007551 | N14: chromosome_01 | O14: gene
A15: contig_536:2003808-2691226_631 | B15: Cre08.g800941_4532.1 | D15: 920.98913 | E15: 2288.6 | F15: 3176179 | G15: 3176856 | H15: 3.1e-55 | I15: 215 | J15: 91.76 | K15: 170 | L15: 285 | M15: 0.59649123 | N15: chromosome_08 | O15: gene
A16: contig_536:2003808-2691226_636 | B16: Cre02.g800227_4532.1 | D16: 45.129431 | E16: 279.5 | F16: 4480729 | G16: 4481484 | H16: 9.3e-183 | I16: 639 | J16: 97.19 | K16: 427 | L16: 558 | M16: 0.76523297 | N16: chromosome_02 | O16: gene
A17: contig_536:2003808-2691226_640 | B17: Cre15.g635700_4532.5 | D17: 4.3503298 | E17: 30.8 | F17: 431804 | G17: 440910 | H17: 0 | I17: 1370 | J17: 93.53 | K17: 1036 | L17: 1209 | M17: 0.85690653 | N17: chromosome_15 | O17: gene | P17: Mitogen-Activated Protein Kinase Kinase Kinase | Q17: protein kinase family protein / peptidoglycan-binding LysM domain-containing protein
A18: contig_536:2003808-2691226_7 | B18: Cre01.g800142_4532.1 | D18: 706.63425 | E18: 1864.6 | F18: 7819664 | G18: 7819915 | H18: 9.9e-41 | I18: 168 | J18: 88.36 | K18: 146 | L18: 252 | M18: 0.57936508 | N18: chromosome_01 | O18: gene
A19: contig_536:2003808-2691226_74 | B19: Cre15.g801742_4532.1 | D19: 43.614256 | E19: 1433.1 | F19: 1705320 | G19: 1713991 | H19: 0 | I19: 7240 | J19: 98.76 | K19: 4692 | L19: 4692 | M19: 1 | N19: chromosome_15 | O19: transposable_element_gene | R19: expressed protein
A20: contig_536:2003808-2691226_75 | B20: Cre15.g801743_4532.1 | D20: 147.60224 | E20: 1440 | F20: 1711893 | G20: 1713991 | H20: 0 | I20: 2270 | J20: 99.18 | K20: 1458 | L20: 1458 | M20: 1 | N20: chromosome_15 | O20: transposable_element_gene
A21: contig_536:2003808-2691226_76 | B21: Cre17.g712700_4532.1 | D21: 0.57396699 | E21: 8.3 | F21: 2207648 | G21: 2208487 | H21: 1.1e-204 | I21: 715 | J21: 84.43 | K21: 655 | L21: 678 | M21: 0.9660767 | N21: chromosome_17 | O21: gene | P21: putative transposase
A22: g1.t1 | B22: Cre27.g757397_4532.1 | D22: 14.34105 | E22: 107.1 | F22: 4481460 | G22: 4483765 | H22: 0 | I22: 1730 | J22: 98.58 | K22: 1125 | L22: 2214 | M22: 0.50813008 | N22: chromosome_06 | O22: transposable_element_gene
A23: g10.t1 | B23: Cre06.g278350_4532.1 | C23: AGD1 | D23: 27.256024 | E23: 215.3 | F23: 4650966 | G23: 4654871 | H23: 0 | I23: 1640 | J23: 99.71 | K23: 1041 | L23: 1212 | M23: 0.85891089 | N23: chromosome_06 | O23: gene | P23: Arogenate/prephenate dehydrogenase | Q23: prephenate dehydrogenase family protein | R23: arogenate dehydrogenase 1, chloroplast precursor, putative, expressed
A24: g100.t1 | B24: Cre06.g282251_4532.1 | D24: 1.8596687 | E24: 34.6 | F24: 5057583 | G24: 5062895 | H24: 0 | I24: 1340 | J24: 94.28 | K24: 962 | L24: 1791 | M24: 0.53713009 | N24: chromosome_06 | O24: gene | P24: (1 of 96) PF01753 - MYND finger (zf-MYND)
A25: g1000.t1 | B25: Cre06.g264400_4532.1 | D25: 6.2190802 | E25: 340.6 | F25: 1918261 | G25: 1931086 | H25: 0 | I25: 12300 | J25: 98.62 | K25: 8032 | L25: 9090 | M25: 0.88360836 | N25: chromosome_06 | O25: gene | P25: (1 of 1) PTHR13992 - NUCLEAR RECEPTOR CO-REPRESSOR RELATED NCOR
A26: g10000.t1 | B26: Cre07.g314650_4532.1 | C26: RECA1 | D26: 6.5132368 | E26: 45.2 | F26: 356703 | G26: 362748 | H26: 0 | I26: 1660 | J26: 99.25 | K26: 1064 | L26: 1248 | M26: 0.8525641 | N26: chromosome_07 | O26: gene | P26: Chloroplast RecA recombination protein | Q26: recA DNA recombination family protein | R26: recA protein, putative, expressed
A27: g10001.t1 | B27: Cre07.g314600_4532.1 | C27: RPI2 | D27: 16.164888 | E27: 91.2 | F27: 353214 | G27: 357035 | H27: 0 | I27: 1350 | J27: 98.52 | K27: 876 | L27: 876 | M27: 1 | N27: chromosome_07 | O27: gene | P27: ribose-5 phosphate isomerase-related protein | Q27: NagB/RpiA/CoA transferase-like superfamily protein | R27: ribose-5-phosphate isomerase A, putative, expressed
A28: g10002.t1 | B28: Cre07.g314550_4532.1 | D28: 13.93167 | E28: 84.1 | F28: 349608 | G28: 353299 | H28: 0 | I28: 1340 | J28: 98.31 | K28: 885 | L28: 882 | M28: 1.0034014 | N28: chromosome_07 | O28: gene | P28: tRNA (guanine-N7)-methyltransferase | Q28: tRNA (guanine-N-7) methyltransferase | R28: tRNA methyltransferase, putative, expressed
A29: g10003.t1 | B29: Cre07.g314500_4532.1 | D29: 9.3858717 | E29: 194.4 | F29: 337648 | G29: 349633 | H29: 0 | I29: 4770 | J29: 98.58 | K29: 3105 | L29: 3378 | M29: 0.91918295 | N29: chromosome_07 | O29: gene | P29: (1 of 104) 2.7.11.25 - Mitogen-activated protein kinase kinase kinase / MLTK
A30: g10004.t1 | B30: Cre07.g314450_4532.1 | C30: CGL33B | D30: 6.1328652 | E30: 45.7 | F30: 333514 | G30: 337492 | H30: 0 | I30: 1600 | J30: 96.8 | K30: 1095 | L30: 1212 | M30: 0.90346535 | N30: chromosome_07 | O30: gene | P30: conserved methyltransferase of unknown function | Q30: S-adenosyl-L-methionine-dependent methyltransferases superfamily protein | R30: expressed protein
A31: g10006.t1 | B31: Cre07.g314300_4532.1 | D31: 10.673435 | E31: 87.1 | F31: 311508 | G31: 317216 | H31: 0 | I31: 1820 | J31: 98.08 | K31: 1200 | L31: 1200 | M31: 1 | N31: chromosome_07 | O31: gene | P31: (1 of 1) PF07092 - Protein of unknown function (DUF1356) (DUF1356)
A32: g10007.t1 | B32: Cre07.g314250_4532.1 | D32: 6.1845715 | E32: 108 | F32: 305809 | G32: 311088 | H32: 0 | I32: 4360 | J32: 99.01 | K32: 2820 | L32: 2928 | M32: 0.96311475 | N32: chromosome_07 | O32: gene
A33: g1001.t1 | B33: Cre06.g264450_4532.1 | D33: 4.1810681 | E33: 42.1 | F33: 1931046 | G33: 1936734 | H33: 0 | I33: 2360 | J33: 100 | K33: 1494 | L33: 1899 | M33: 0.78672986 | N33: chromosome_06 | O33: gene | P33: Amino acid transporter
A34: g10010.t1 | B34: Cre07.g314150_4532.1 | C34: ZDS1 | D34: 102.79825 | E34: 1204.1 | F34: 291934 | G34: 298677 | H34: 0 | I34: 2760 | J34: 99.89 | K34: 1749 | L34: 1749 | M34: 1 | N34: chromosome_07 | O34: gene | P34: Zeta-carotene desaturase | Q34: zeta-carotene desaturase | R34: zeta-carotene desaturase, chloroplast/chromoplast precursor, putative, expressed
A35: g10011.t1 | B35: Cre07.g314100_4532.1 | D35: 20.103983 | E35: 118.3 | F35: 289247 | G35: 291959 | H35: 0 | I35: 1350 | J35: 99.65 | K35: 861 | L35: 861 | M35: 1 | N35: chromosome_07 | O35: gene | P35: (1 of 1) K14775 - ribosome biogenesis protein UTP30 (UTP30, RSL1D1) | Q35: Ribosomal protein L1p/L10e family | R35: 60S ribosomal protein-related, putative, expressed
A36: g10012.t1 | B36: Cre07.g314050_4532.1 | D36: 4.3316001 | E36: 172 | F36: 277715 | G36: 289395 | H36: 0 | I36: 5670 | J36: 99.12 | K36: 3646 | L36: 6792 | M36: 0.53680801 | N36: chromosome_07 | O36: gene | P36: (1 of 15) 2.7.11.18 - [Myosin light-chain] kinase / Smooth-muscle-myosin-light-chain kinase
A37: g10013.t1 | B37: Cre14.g612900_4532.1 | D37: 11.276997 | E37: 183.7 | F37: 821529 | G37: 823504 | H37: 0 | I37: 2740 | J37: 99.77 | K37: 1743 | L37: 1743 | M37: 1 | N37: chromosome_14 | O37: transposable_element_gene
A38: g10014.t1 | B38: Cre07.g314000_4532.1 | D38: 15.772698 | E38: 119.7 | F38: 272283 | G38: 275889 | H38: 0 | I38: 1720 | J38: 97.34 | K38: 1164 | L38: 1413 | M38: 0.82377919 | N38: chromosome_07 | O38: gene | P38: (1 of 1) PF16156 - Domain of unknown function (DUF4864) (DUF4864)
A39: g10015.t1 | B39: Cre07.g313950_4532.1 | D39: 2.3946135 | E39: 33.4 | F39: 264840 | G39: 272049 | H39: 0 | I39: 2120 | J39: 98.55 | K39: 1380 | L39: 2556 | M39: 0.5399061 | N39: chromosome_07 | O39: gene | P39: (1 of 14) PF04577 - Protein of unknown function (DUF563) (DUF563)
A40: g10016.t1 | B40: Cre07.g313900_4532.1 | D40: 17.98335 | E40: 364.5 | F40: 259816 | G40: 265149 | H40: 0 | I40: 4800 | J40: 98.72 | K40: 3126 | L40: 3123 | M40: 1.0009606 | N40: chromosome_07 | O40: gene
A41: g10017.t1 | B41: Cre07.g313850_4532.1 | D41: 7.6435802 | E41: 198.3 | F41: 247116 | G41: 258578 | H41: 0 | I41: 5900 | J41: 98.4 | K41: 3881 | L41: 3930 | M41: 0.98753181 | N41: chromosome_07 | O41: gene | P41: (1 of 1) PTHR22844//PTHR22844:SF219 - F-BOX AND WD40 DOMAIN PROTEIN // WD REPEAT-CONTAINING PROTEIN 49
A42: g10018.t1 | B42: Cre07.g313800_4532.1 | C42: CGL138 | D42: 6.9284592 | E42: 15.4 | F42: 245874 | G42: 246755 | H42: 6.2e-166 | I42: 525 | J42: 99.7 | K42: 333 | L42: 333 | M42: 1 | N42: chromosome_07 | O42: gene | P42: Conserved in the Green Lineage | R42: THION26 - Plant thionin family protein precursor, expressed
A43: g10019.t1 | B43: Cre07.g313750_4532.1 | D43: 4.5443696 | E43: 110.9 | F43: 239629 | G43: 245399 | H43: 0 | I43: 3780 | J43: 99.63 | K43: 2407 | L43: 4203 | M43: 0.57268618 | N43: chromosome_07 | O43: gene
A44: g1002.t1 | B44: Cre06.g264500_4532.1 | D44: 6.814333 | E44: 61.4 | F44: 1936715 | G44: 1939897 | H44: 0 | I44: 2180 | J44: 100 | K44: 1380 | L44: 1380 | M44: 1 | N44: chromosome_06 | O44: gene | P44: (1 of 1) K14785 - ESF2/ABP1 family protein (ESF2, ABT1)
A45: g10020.t1 | B45: Cre07.g313700_4532.1 | C45: TSX2 | D45: 133.87426 | E45: 1237.1 | F45: 234503 | G45: 239931 | H45: 0 | I45: 2210 | J45: 99.22 | K45: 1419 | L45: 1692 | M45: 0.83865248 | N45: chromosome_07 | O45: gene | P45: Glutamyl/glutaminyl-tRNA synthetase | Q45: glutamate tRNA synthetase | R45: glutamyl-tRNA synthetase, putative, expressed
A46: g10021.t1 | B46: Cre07.g313650_4532.1 | D46: 1.1394168 | E46: 63.6 | F46: 219260 | G46: 227403 | H46: 0 | I46: 4020 | J46: 93.93 | K46: 2965 | L46: 5313 | M46: 0.55806512 | N46: chromosome_07 | O46: gene | P46: (1 of 25) PTHR11017//PTHR11017:SF145 - LEUCINE-RICH REPEAT-CONTAINING PROTEIN // SUBFAMILY NOT NAMED
A47: g10022.t1 | B47: Cre07.g313600_4532.1 | C47: CGL33A | D47: 0.043699294 | E47: 0.3 | F47: 215572 | G47: 218868 | H47: 0 | I47: 1190 | J47: 98.23 | K47: 789 | L47: 1122 | M47: 0.70320856 | N47: chromosome_07 | O47: gene | P47: conserved methyltransferase of unknown function | Q47: S-adenosyl-L-methionine-dependent methyltransferases superfamily protein | R47: expressed protein
A48: g10023.t1 | B48: Cre07.g313550_4532.1 | D48: 17.679562 | E48: 99.1 | F48: 211445 | G48: 215658 | H48: 0 | I48: 1410 | J48: 100 | K48: 888 | L48: 966 | M48: 0.91925466 | N48: chromosome_07 | O48: gene | P48: (1 of 1) PTHR15495//PTHR15495:SF17 - NEGATIVE REGULATOR OF VESICLE FORMATION-RELATED // SUBFAMILY NOT NAMED | Q48: alpha/beta-Hydrolases superfamily protein | R48: expressed protein
A49: g10024.t1 | B49: Cre07.g313500_4532.1 | C49: NUP214 | D49: 1.3744537 | E49: 77.7 | F49: 197103 | G49: 215607 | H49: 0 | I49: 9600 | J49: 99.95 | K49: 6079 | L49: 9321 | M49: 0.65218324 | N49: chromosome_07 | O49: gene | Q49: Nuclear pore complex protein
A50: g10025.t1 | B50: Cre07.g313450_4532.2 | D50: 12.100161 | E50: 114.7 | F50: 193103 | G50: 196998 | H50: 0 | I50: 2170 | J50: 98.39 | K50: 1425 | L50: 1425 | M50: 1 | N50: chromosome_07 | O50: gene
A51: g10026.t1 | B51: Cre07.g313400_4532.1 | D51: 7.7772004 | E51: 167.9 | F51: 186310 | G51: 192800 | H51: 0 | I51: 4950 | J51: 97.68 | K51: 3312 | L51: 3876 | M51: 0.85448916 | N51: chromosome_07 | O51: gene
A52: g10027.t1 | B52: Cre07.g313350_4532.1 | D52: 1.3894108 | E52: 26.2 | F52: 181063 | G52: 185291 | H52: 0 | I52: 2860 | J52: 97.31 | K52: 1935 | L52: 2073 | M52: 0.93342981 | N52: chromosome_07 | O52: gene | P52: (1 of 2) 3.5.1.17 - Acyl-lysine deacylase / Epsilon-lysine acylase | Q52: Amidohydrolase family | R52: amidohydrolase, putative, expressed
A53: g10028.t1 | B53: Cre07.g313302_4532.1 | D53: 18.812249 | E53: 154.4 | F53: 176116 | G53: 180991 | H53: 0 | I53: 1810 | J53: 99.31 | K53: 1161 | L53: 1161 | M53: 1 | N53: chromosome_07 | O53: gene | P53: (1 of 1) K03027 - DNA-directed RNA polymerases I and III subunit RPAC1 (RPC40, POLR1C) | Q53: RNA polymerase I subunit 43 | R53: DNA-directed RNA polymerase subunit, putative, expressed
A54: g10029.t1 | B54: Cre07.g313250_4532.1 | D54: 43.201134 | E54: 539.6 | F54: 169829 | G54: 175975 | H54: 0 | I54: 2940 | J54: 99.73 | K54: 1866 | L54: 2100 | M54: 0.88857143 | N54: chromosome_07 | O54: gene | P54: (1 of 13) 3.6.3.25 - Sulfate-transporting ATPase
A55: g1003.t1 | B55: Cre06.g264550_4532.1 | C55: CGL81 | D55: 82.170117 | E55: 309.3 | F55: 1940043 | G55: 1943191 | H55: 3.7e-288 | I55: 897 | J55: 100 | K55: 566 | L55: 819 | M55: 0.69108669 | N55: chromosome_06 | O55: gene | P55: Conserved in the Green Lineage | Q55: Protein of unknown function (DUF1997) | R55: expressed protein
A56: g10031.t1 | B56: Cre07.g313185_4532.1 | D56: 26.193774 | E56: 73.2 | F56: 158541 | G56: 159646 | H56: 1.3e-205 | I56: 648 | J56: 98.35 | K56: 423 | L56: 423 | M56: 1 | N56: chromosome_07 | O56: gene | P56: (1 of 1) K03012 - DNA-directed RNA polymerase II subunit RPB4 (RPB4, POLR2D) | Q56: RNA polymerase II, Rpb4, core protein | R56: DNA-directed RNA polymerase II subunit RPB4, putative, expressed
A57: g10032.t1 | B57: Cre07.g313164_4532.1 | D57: 3.2978616 | E57: 36.8 | F57: 152687 | G57: 157758 | H57: 0 | I57: 2710 | J57: 99.42 | K57: 1731 | L57: 1731 | M57: 1 | N57: chromosome_07 | O57: gene | P57: (1 of 2) K16296 - serine carboxypeptidase-like clade I [EC:3.4.16.-] (SCPL-I)
A58: g10033.t1 | B58: Cre07.g313143_4532.1 | D58: 1.5941513 | E58: 27.7 | F58: 148184 | G58: 152600 | H58: 0 | I58: 3730 | J58: 98.36 | K58: 2445 | L58: 2502 | M58: 0.97721823 | N58: chromosome_07 | O58: gene
A59: g10034.t1 | B59: Cre07.g313122_4532.1 | D59: 6.3523533 | E59: 136.7 | F59: 138991 | G59: 148454 | H59: 0 | I59: 4830 | J59: 98.08 | K59: 3174 | L59: 3198 | M59: 0.99249531 | N59: chromosome_07 | O59: gene | P59: (1 of 2) 3.4.19.1 - Acylaminoacyl-peptidase / N-acylpeptide hydrolase | Q59: Prolyl oligopeptidase family protein | R59: OsPOP7 - Putative Prolyl Oligopeptidase homologue, expressed
A60: g10035.t1 | B60: Cre07.g313100_4532.1 | D60: 2.2333349 | E60: 38 | F60: 133083 | G60: 138697 | H60: 0 | I60: 3880 | J60: 97.13 | K60: 2616 | L60: 2613 | M60: 1.0011481 | N60: chromosome_07 | O60: gene
A61: g10036.t1 | B61: Cre07.g313050_4532.1 | D61: 0.69572983 | E61: 19.4 | F61: 131538 | G61: 133029 | H61: 0 | I61: 1250 | J61: 97.39 | K61: 842 | L61: 906 | M61: 0.92935982 | N61: chromosome_07 | O61: gene
A62: g10037.t1 | B62: Cre07.g312950_4532.1 | D62: 73.466719 | E62: 185.4 | F62: 122252 | G62: 122717 | H62: 6.1e-182 | I62: 574 | J62: 99.45 | K62: 366 | L62: 366 | M62: 1 | N62: chromosome_07 | O62: gene | P62: DEAD/DEAH box DNA/RNA helicase
A63: g10038.t1 | B63: Cre07.g312900_4532.1 | D63: 23.536092 | E63: 985.1 | F63: 111773 | G63: 121498 | H63: 0 | I63: 9990 | J63: 99.92 | K63: 6330 | L63: 6330 | M63: 1 | N63: chromosome_07 | O63: gene | P63: (1 of 1) K10590 - E3 ubiquitin-protein ligase TRIP12 (TRIP12) | Q63: HEAT repeat ;HECT-domain (ubiquitin-transferase) | R63: HECT-domain domain containing protein, expressed
A64: g10039.t1 | B64: Cre07.g312850_4532.1 | D64: 12.506202 | E64: 77.2 | F64: 109169 | G64: 111694 | H64: 0 | I64: 1450 | J64: 100 | K64: 918 | L64: 918 | M64: 1 | N64: chromosome_07 | O64: gene | P64: (1 of 1) PTHR31621//PTHR31621:SF1 - FAMILY NOT NAMED // DUF679 DOMAIN MEMBRANE PROTEIN 1 | Q64: Protein of unknown function (DUF679) | R64: expressed protein
A65: g1004.t1 | B65: Cre06.g264600_4532.1 | C65: HFO14 | D65: 4.043568 | E65: 8.5 | F65: 1943444 | G65: 1943755 | H65: 3.4e-156 | I65: 495 | J65: 100 | K65: 312 | L65: 312 | M65: 1 | N65: chromosome_06 | O65: gene | P65: Histone H4 | Q65: Histone superfamily protein | R65: Core histone H2A/H2B/H3/H4 domain containing protein, putative, expressed
A66: g10040.t1 | B66: Cre07.g312800_4532.1 | D66: 14.426098 | E66: 203.6 | F66: 101051 | G66: 106549 | H66: 0 | I66: 2540 | J66: 99.57 | K66: 1620 | L66: 2610 | M66: 0.62068966 | N66: chromosome_07 | O66: gene | P66: (1 of 17) PF12906 - RING-variant domain (RINGv)
A67: g10041.t1 | B67: Cre07.g312750_4532.1 | C67: CSL4 | D67: 19.613927 | E67: 78.8 | F67: 98259 | G67: 101250 | H67: 9.9e-304 | I67: 942 | J67: 99.83 | K67: 597 | L67: 597 | M67: 1 | N67: chromosome_07 | O67: gene | P67: Exosome component, Csl4 | Q67: Nucleic acid-binding, OB-fold-like protein | R67: 3-5 exoribonuclease CSL4, putative, expressed
A68: g10044.t1 | B68: Cre06.g800699_4532.1 | D68: 5.4817092 | E68: 10.2 | F68: 5587164 | G68: 5588411 | H68: 1.5e-47 | I68: 188 | J68: 85.54 | K68: 166 | L68: 309 | M68: 0.53721683 | N68: chromosome_06 | O68: gene
A69: g10045.t1 | B69: Cre07.g312650_4532.1 | D69: 11.055957 | E69: 27.8 | F69: 85880 | G69: 87631 | H69: 2.6e-90 | I69: 326 | J69: 99.52 | K69: 207 | L69: 297 | M69: 0.6969697 | N69: chromosome_07 | O69: gene
A70: g10046.t1 | B70: Cre07.g312600_4532.1 | D70: 0 | E70: 0 | F70: 80490 | G70: 82254 | H70: 0 | I70: 1240 | J70: 100 | K70: 783 | L70: 1194 | M70: 0.65577889 | N70: chromosome_07 | O70: gene
A71: g10048.t1 | B71: Cre07.g312495_4532.1 | D71: 79.74276 | E71: 606.6 | F71: 70693 | G71: 72958 | H71: 0 | I71: 1840 | J71: 99.83 | K71: 1167 | L71: 1167 | M71: 1 | N71: chromosome_07 | O71: gene
A72: g10049.t1 | B72: Cre07.g312400_4532.2 | D72: 4.7586354 | E72: 115.4 | F72: 60528 | G72: 70350 | H72: 0 | I72: 2920 | J72: 99.95 | K72: 1845 | L72: 3225 | M72: 0.57209302 | N72: chromosome_07 | O72: gene | P72: Diacylglycerol kinase | Q72: diacylglycerol kinase 2 | R72: diacylglycerol kinase 1, putative, expressed
A73: g1005.t1 | B73: Cre06.g264650_4532.1 | C73: HTR14 | D73: 2.1456576 | E73: 5.7 | F73: 1944038 | G73: 1944445 | H73: 2.6e-206 | I73: 647 | J73: 100 | K73: 408 | L73: 408 | M73: 1 | N73: chromosome_06 | O73: gene | P73: Histone H3 | Q73: Histone superfamily protein | R73: histone H3, putative, expressed
A74: g10050.t1 | B74: Cre07.g312350_4532.1 | C74: POLA4 | D74: 41.862522 | E74: 352.7 | F74: 55550 | G74: 60473 | H74: 0 | I74: 2050 | J74: 99.85 | K74: 1302 | L74: 1377 | M74: 0.94553377 | N74: chromosome_07 | O74: gene | P74: DNA polymerase alpha, primase subunit | Q74: DNA primases;DNA primases | R74: POLA4 - Putative DNA polymerase alpha complex subunit, expressed
A75: g10051.t1 | B75: Cre07.g312300_4532.1 | C75: LFO1 | D75: 124.90638 | E75: 428.5 | F75: 54062 | G75: 55811 | H75: 2.7e-230 | I75: 734 | J75: 96.36 | K75: 522 | L75: 516 | M75: 1.0116279 | N75: chromosome_07 | O75: gene | P75: (1 of 3) 1.14.99.3 - Heme oxygenase (biliverdin-producing) / Heme oxygenase (decyclizing)
A76: g10052.t1 | B76: Cre07.g312150_4532.1 | D76: 7.4598154 | E76: 197.4 | F76: 39258 | G76: 47414 | H76: 0 | I76: 3520 | J76: 98.48 | K76: 2305 | L76: 2448 | M76: 0.94158497 | N76: chromosome_07 | O76: gene | P76: (1 of 1) PF00580//PF13361 - UvrD/REP helicase N-terminal domain (UvrD-helicase) // UvrD-like helicase C-terminal domain (UvrD_C)
A77: g10053.t1 | B77: Cre07.g312100_4532.1 | D77: 11.273298 | E77: 148.2 | F77: 32134 | G77: 35642 | H77: 0 | I77: 2990 | J77: 99.42 | K77: 1911 | L77: 1911 | M77: 1 | N77: chromosome_07 | O77: gene | P77: (1 of 1) PTHR15323//PTHR15323:SF6 - D123 PROTEIN // CELL DIVISION CYCLE PROTEIN 123 HOMOLOG
A78: g1006.t1 | B78: Cre06.g264700_4532.1 | D78: 0 | E78: 0 | F78: 1946695 | G78: 1949229 | H78: 0 | I78: 2060 | J78: 99.92 | K78: 1302 | L78: 1302 | M78: 1 | N78: chromosome_06 | O78: gene | P78: Chlamydomonas specific family S protein
A79: g10065.t1 | B79: Cre11.g483400_4532.1 | D79: 24.022877 | E79: 341 | F79: 4441503 | G79: 4449333 | H79: 0 | I79: 2830 | J79: 99.56 | K79: 1802 | L79: 2091 | M79: 0.86178862 | N79: chromosome_11 | O79: gene | P79: Exostosin-like glycosyltransferase 10 | R79: exostosin family domain containing protein, expressed
A80: g10066.t1 | B80: Cre11.g483351_4532.4 | D80: 1.3111274 | E80: 11.5 | F80: 4436014 | G80: 4441386 | H80: 1.1e-193 | I80: 677 | J80: 99.77 | K80: 429 | L80: 429 | M80: 1 | N80: chromosome_11 | O80: gene | P80: Pherophorin-chlamydomonas homolog 44
A81: g10069.t1 | B81: Cre11.g483200_4532.1 | D81: 6.9190278 | E81: 63.9 | F81: 4421290 | G81: 4425744 | H81: 0 | I81: 2200 | J81: 98.54 | K81: 1437 | L81: 1653 | M81: 0.86932849 | N81: chromosome_11 | O81: gene | P81: (1 of 2) PTHR31350:SF1 - F-BOX ONLY PROTEIN 21
A82: g1007.t1 | B82: Cre06.g264750_4532.1 | C82: HTA14 | D82: 4.3586246 | E82: 11 | F82: 1950280 | G82: 1950678 | H82: 1.3e-201 | I82: 632 | J82: 100 | K82: 399 | L82: 399 | M82: 1 | N82: chromosome_06 | O82: gene | P82: Histone H2A | Q82: histone H2A 10 | R82: Core histone H2A/H2B/H3/H4 domain containing protein, putative, expressed
A83: g10070.t1 | B83: Cre11.g483150_4532.1 | D83: 11.889932 | E83: 86.4 | F83: 4418566 | G83: 4421479 | H83: 0 | I83: 1370 | J83: 97.39 | K83: 918 | L83: 918 | M83: 1 | N83: chromosome_11 | O83: gene | P83: (1 of 1) PTHR15955 - RWD DOMAIN CONTAINING PROTEIN 2
A84: g10071.t1 | B84: Cre11.g483100_4532.1 | D84: 1.9296499 | E84: 57.2 | F84: 4410052 | G84: 4418409 | H84: 0 | I84: 4240 | J84: 99.23 | K84: 2739 | L84: 3042 | M84: 0.90039448 | N84: chromosome_11 | O84: gene
A85: g10073.t1 | B85: Cre11.g482952_4532.2 | D85: 6.9380733 | E85: 188.3 | F85: 4377081 | G85: 4388668 | H85: 0 | I85: 1670 | J85: 94.42 | K85: 1200 | L85: 1950 | M85: 0.61538462 | N85: chromosome_11 | O85: gene
A86: g10074.t1 | B86: Cre11.g482900_4532.1 | C86: RAB18C | D86: 32.251851 | E86: 128 | F86: 4373333 | G86: 4377000 | H86: 2.5e-306 | I86: 952 | J86: 99.34 | K86: 609 | L86: 609 | M86: 1 | N86: chromosome_11 | O86: gene | P86: Small Rab-related GTPase | Q86: RAB GTPASE HOMOLOG B18 | R86: ras-related protein, putative, expressed
A87: g10075.t1 | B87: Cre11.g482850_4532.1 | D87: 0.64237726 | E87: 9.9 | F87: 4368242 | G87: 4373392 | H87: 0 | I87: 3270 | J87: 98.01 | K87: 2163 | L87: 2163 | M87: 1 | N87: chromosome_11 | O87: gene | P87: (1 of 1) K16812 - targeting protein for Xklp2 (TPX2) | Q87: targeting protein for XKLP2 | R87: targeting protein-related, putative, expressed
A88: g10076.t1 | B88: Cre11.g482841_4532.1 | D88: 2.2122539 | E88: 16 | F88: 4365270 | G88: 4368737 | H88: 0 | I88: 1620 | J88: 97.78 | K88: 1080 | L88: 1095 | M88: 0.98630137 | N88: chromosome_11 | O88: gene | P88: (1 of 2) K11145 - ribonuclease III family protein [EC:3.1.26.-] (K11145) | Q88: Ribonuclease III family protein
A89: g10077.t1 | B89: Cre11.g482800_4532.1 | D89: 6.9321458 | E89: 150 | F89: 4357172 | G89: 4365186 | H89: 0 | I89: 4810 | J89: 98 | K89: 3195 | L89: 3177 | M89: 1.0056657 | N89: chromosome_11 | O89: gene | P89: Serine/threonine protein kinase | Q89: cysteine-rich RLK (RECEPTOR-like protein kinase) 10 | R89: TKL_IRAK_DUF26-ld.3 - DUF26 kinases have homology to DUF26 containing loci, expressed
A90: g10078.t1 | B90: Cre11.g482750_4532.2 | D90: 0.72837082 | E90: 21 | F90: 4343598 | G90: 4355326 | H90: 0 | I90: 5630 | J90: 96.15 | K90: 3900 | L90: 3945 | M90: 0.98859316 | N90: chromosome_11 | O90: gene | P90: (1 of 3) PTHR12363 - TRANSPORTIN 3 AND IMPORTIN 13
A91: g10079.t1 | B91: Cre11.g482700_4532.1 | D91: 0.98756839 | E91: 11.8 | F91: 4340244 | G91: 4343925 | H91: 0 | I91: 2410 | J91: 97.01 | K91: 1641 | L91: 1629 | M91: 1.0073665 | N91: chromosome_11 | O91: gene | P91: (1 of 1) PF09011 - HMG-box domain (HMG_box_2)
A92: g1008.t1 | B92: Cre06.g264800_4532.1 | C92: HTB14 | D92: 7.9891495 | E92: 23.5 | F92: 1950918 | G92: 1951470 | H92: 1.7e-234 | I92: 732 | J92: 100 | K92: 462 | L92: 462 | M92: 1 | N92: chromosome_06 | O92: gene | P92: Histone H2B | Q92: Histone superfamily protein | R92: OsFBO1 - F-box and other domain containing protein, expressed
A93: g10080.t1 | B93: Cre11.g482650_4532.1 | C93: EZY3 | D93: 3.9819703 | E93: 13.1 | F93: 4334612 | G93: 4337294 | H93: 1.7e-242 | I93: 759 | J93: 98.98 | K93: 489 | L93: 489 | M93: 1 | N93: chromosome_11 | O93: gene | P93: Early zygote expressed protein
A94: g10081.t1 | B94: Cre11.g482600_4532.1 | D94: 61.533182 | E94: 111.4 | F94: 4327608 | G94: 4329337 | H94: 4e-114 | I94: 378 | J94: 99.58 | K94: 240 | L94: 282 | M94: 0.85106383 | N94: chromosome_11 | O94: gene
A95: g10083.t1 | B95: Cre11.g482483_4532.1 | D95: 3.3730826 | E95: 97.6 | F95: 4303120 | G95: 4319714 | H95: 0 | I95: 4810 | J95: 96.32 | K95: 3342 | L95: 4791 | M95: 0.69755792 | N95: chromosome_11 | O95: gene | P95: (1 of 1) K12599 - antiviral helicase SKI2 (SKI2, SKIV2L) | Q95: RNA helicase, ATP-dependent, SK12/DOB1 protein | R95: DSHCT domain containing protein, expressed
A96: g10084.t1 | B96: Cre11.g482450_4532.1 | D96: 6.1520535 | E96: 62.4 | F96: 4298678 | G96: 4302626 | H96: 0 | I96: 1950 | J96: 93.71 | K96: 1463 | L96: 1647 | M96: 0.88828172 | N96: chromosome_11 | O96: gene
A97: g10085.t1 | B97: Cre11.g482400_4532.1 | D97: 17.833139 | E97: 104.6 | F97: 4296180 | G97: 4297255 | H97: 3.6e-243 | I97: 829 | J97: 95.96 | K97: 569 | L97: 573 | M97: 0.9930192 | N97: chromosome_11 | O97: gene
A98: g10086.t1 | B98: Cre11.g482400_4532.1 | D98: 1.7323824 | E98: 6 | F98: 4296180 | G98: 4297255 | H98: 1.3e-218 | I98: 715 | J98: 94.83 | K98: 503 | L98: 573 | M98: 0.87783595 | N98: chromosome_11 | O98: gene
A99: g10087.t1 | B99: Cre10.g801124_4532.1 | D99: 4.3934176 | E99: 71.9 | F99: 2275571 | G99: 2276835 | H99: 0 | I99: 1770 | J99: 99.29 | K99: 1132 | L99: 1263 | M99: 0.8962787 | N99: chromosome_10 | O99: transposable_element_gene
A100: g10088.t1 | B100: Cre11.g482300_4532.1 | C100: MOT17 | D100: 50.870866 | E100: 427.5 | F100: 4290070 | G100: 4295118 | H100: 0 | I100: 1960 | J100: 98.21 | K100: 1284 | L100: 1284 | M100: 1 | N100: chromosome_11 | O100: gene | P100: Flagellar Associated Protein 305
...
